[
  {
    "state": "CT",
    "city": "Hartford",
    "zip": "06106",
    "theater_name": "Apple Cinemas Xtreme Hartford",
    "chainName": "Apple Cinemas",
    "chainCode": "APPL",
    "showtime_id": 515450061,
    "date": "2025-09-14+12:15",
    "format": "Standard",
    "language": "Telugu",
    "totalSeatSold": 13,
    "occupancy": 31.71,
    "totalAvailableSeatCount": 28,
    "totalSeatCount": 41,
    "grossRevenueUSD": 74.75,
    "adultTicketPrice": 5.75
  },
  {
    "state": "CT",
    "city": "Hartford",
    "zip": "06106",
    "theater_name": "Apple Cinemas Xtreme Hartford",
    "chainName": "Apple Cinemas",
    "chainCode": "APPL",
    "showtime_id": 515450060,
    "date": "2025-09-14+21:30",
    "format": "Standard",
    "language": "Telugu",
    "totalSeatSold": 5,
    "occupancy": 12.2,
    "totalAvailableSeatCount": 36,
    "totalSeatCount": 41,
    "grossRevenueUSD": 28.75,
    "adultTicketPrice": 5.75
  },
  {
    "state": "CT",
    "city": "Waterbury",
    "zip": "06706",
    "theater_name": "Apple Cinemas Brass Mill",
    "chainName": "Apple Cinemas",
    "chainCode": "APPL",
    "showtime_id": 515719102,
    "date": "2025-09-14+15:30",
    "format": "Standard",
    "language": "Telugu",
    "totalSeatSold": 1,
    "occupancy": 0.79,
    "totalAvailableSeatCount": 125,
    "totalSeatCount": 126,
    "grossRevenueUSD": 9.0,
    "adultTicketPrice": 9.0
  },
  {
    "state": "CT",
    "city": "Waterbury",
    "zip": "06706",
    "theater_name": "Apple Cinemas Brass Mill",
    "chainName": "Apple Cinemas",
    "chainCode": "APPL",
    "showtime_id": 515719103,
    "date": "2025-09-14+18:40",
    "format": "Standard",
    "language": "Telugu",
    "totalSeatSold": 1,
    "occupancy": 0.79,
    "totalAvailableSeatCount": 125,
    "totalSeatCount": 126,
    "grossRevenueUSD": 10.5,
    "adultTicketPrice": 10.5
  },
  {
    "state": "NH",
    "city": "Merrimack",
    "zip": "03054",
    "theater_name": "Apple Cinemas Merrimack",
    "chainName": "Apple Cinemas",
    "chainCode": "APPL",
    "showtime_id": 515742643,
    "date": "2025-09-14+15:20",
    "format": "Standard",
    "language": "Telugu",
    "totalSeatSold": 5,
    "occupancy": 11.9,
    "totalAvailableSeatCount": 37,
    "totalSeatCount": 42,
    "grossRevenueUSD": 60.0,
    "adultTicketPrice": 12.0
  },
  {
    "state": "NH",
    "city": "Merrimack",
    "zip": "03054",
    "theater_name": "Apple Cinemas Merrimack",
    "chainName": "Apple Cinemas",
    "chainCode": "APPL",
    "showtime_id": 515742644,
    "date": "2025-09-14+18:30",
    "format": "Standard",
    "language": "Telugu",
    "totalSeatSold": 3,
    "occupancy": 7.14,
    "totalAvailableSeatCount": 39,
    "totalSeatCount": 42,
    "grossRevenueUSD": 42.0,
    "adultTicketPrice": 14.0
  },
  {
    "state": "MA",
    "city": "Bellingham",
    "zip": "02019",
    "theater_name": "Regal Bellingham",
    "chainName": "Regal",
    "chainCode": "REGL",
    "showtime_id": 515724661,
    "date": "2025-09-14+17:55",
    "format": "Standard",
    "language": "Telugu",
    "totalSeatSold": 24,
    "occupancy": 24.24,
    "totalAvailableSeatCount": 75,
    "totalSeatCount": 99,
    "grossRevenueUSD": 383.76,
    "adultTicketPrice": 15.99
  },
  {
    "state": "MA",
    "city": "Cambridge",
    "zip": "02138",
    "theater_name": "Apple Cinemas Cambridge",
    "chainName": "Apple Cinemas",
    "chainCode": "APPL",
    "showtime_id": 515678890,
    "date": "2025-09-14+12:40",
    "format": "Standard",
    "language": "Telugu",
    "totalSeatSold": 7,
    "occupancy": 21.21,
    "totalAvailableSeatCount": 26,
    "totalSeatCount": 33,
    "grossRevenueUSD": 84.0,
    "adultTicketPrice": 12.0
  },
  {
    "state": "MA",
    "city": "Cambridge",
    "zip": "02138",
    "theater_name": "Apple Cinemas Cambridge",
    "chainName": "Apple Cinemas",
    "chainCode": "APPL",
    "showtime_id": 515678891,
    "date": "2025-09-14+21:45",
    "format": "Standard",
    "language": "Telugu",
    "totalSeatSold": 2,
    "occupancy": 4.76,
    "totalAvailableSeatCount": 40,
    "totalSeatCount": 42,
    "grossRevenueUSD": 28.0,
    "adultTicketPrice": 14.0
  },
  {
    "state": "NJ",
    "city": "South Plainfield",
    "zip": "07080",
    "theater_name": "Regal Hadley Theatre",
    "chainName": "Regal",
    "chainCode": "REGL",
    "showtime_id": 515631338,
    "date": "2025-09-14+11:15",
    "format": "Standard",
    "language": "Telugu",
    "totalSeatSold": 19,
    "occupancy": 16.24,
    "totalAvailableSeatCount": 98,
    "totalSeatCount": 117,
    "grossRevenueUSD": 253.08,
    "adultTicketPrice": 13.32
  },
  {
    "state": "NJ",
    "city": "South Plainfield",
    "zip": "07080",
    "theater_name": "Regal Hadley Theatre",
    "chainName": "Regal",
    "chainCode": "REGL",
    "showtime_id": 515631320,
    "date": "2025-09-14+14:30",
    "format": "Standard",
    "language": "Telugu",
    "totalSeatSold": 53,
    "occupancy": 45.3,
    "totalAvailableSeatCount": 64,
    "totalSeatCount": 117,
    "grossRevenueUSD": 705.96,
    "adultTicketPrice": 13.32
  },
  {
    "state": "NJ",
    "city": "South Plainfield",
    "zip": "07080",
    "theater_name": "Regal Hadley Theatre",
    "chainName": "Regal",
    "chainCode": "REGL",
    "showtime_id": 515631319,
    "date": "2025-09-14+21:00",
    "format": "Standard",
    "language": "Telugu",
    "totalSeatSold": 31,
    "occupancy": 26.5,
    "totalAvailableSeatCount": 86,
    "totalSeatCount": 117,
    "grossRevenueUSD": 528.55,
    "adultTicketPrice": 17.05
  },
  {
    "state": "NJ",
    "city": "Secaucus",
    "zip": "07094",
    "theater_name": "Regal Secaucus ShowPlace 14",
    "chainName": "Regal",
    "chainCode": "REGL",
    "showtime_id": 515609763,
    "date": "2025-09-14+13:30",
    "format": "Standard",
    "language": "Telugu",
    "totalSeatSold": 17,
    "occupancy": 15.18,
    "totalAvailableSeatCount": 95,
    "totalSeatCount": 112,
    "grossRevenueUSD": 204.0,
    "adultTicketPrice": 12.0
  },
  {
    "state": "NJ",
    "city": "Secaucus",
    "zip": "07094",
    "theater_name": "Regal Secaucus ShowPlace 14",
    "chainName": "Regal",
    "chainCode": "REGL",
    "showtime_id": 515919639,
    "date": "2025-09-14+18:00",
    "format": "Standard",
    "language": "Telugu",
    "totalSeatSold": 9,
    "occupancy": 14.52,
    "totalAvailableSeatCount": 53,
    "totalSeatCount": 62,
    "grossRevenueUSD": 139.14,
    "adultTicketPrice": 15.46
  },
  {
    "state": "NJ",
    "city": "Secaucus",
    "zip": "07094",
    "theater_name": "Regal Secaucus ShowPlace 14",
    "chainName": "Regal",
    "chainCode": "REGL",
    "showtime_id": 515609761,
    "date": "2025-09-14+20:25",
    "format": "Standard",
    "language": "Telugu",
    "totalSeatSold": 1,
    "occupancy": 1.61,
    "totalAvailableSeatCount": 61,
    "totalSeatCount": 62,
    "grossRevenueUSD": 15.46,
    "adultTicketPrice": 15.46
  },
  {
    "state": "NJ",
    "city": "North Brunswick",
    "zip": "08902",
    "theater_name": "Regal Commerce Center & RPX",
    "chainName": "Regal",
    "chainCode": "REGL",
    "showtime_id": 515607124,
    "date": "2025-09-14+14:05",
    "format": "Standard",
    "language": "Telugu",
    "totalSeatSold": 63,
    "occupancy": 48.84,
    "totalAvailableSeatCount": 66,
    "totalSeatCount": 129,
    "grossRevenueUSD": 771.75,
    "adultTicketPrice": 12.25
  },
  {
    "state": "NJ",
    "city": "North Brunswick",
    "zip": "08902",
    "theater_name": "Regal Commerce Center & RPX",
    "chainName": "Regal",
    "chainCode": "REGL",
    "showtime_id": 515607125,
    "date": "2025-09-14+17:25",
    "format": "Standard",
    "language": "Telugu",
    "totalSeatSold": 55,
    "occupancy": 42.64,
    "totalAvailableSeatCount": 74,
    "totalSeatCount": 129,
    "grossRevenueUSD": 849.75,
    "adultTicketPrice": 15.45
  },
  {
    "state": "NJ",
    "city": "Burlington",
    "zip": "08016",
    "theater_name": "Regal Burlington",
    "chainName": "Regal",
    "chainCode": "REGL",
    "showtime_id": 515617720,
    "date": "2025-09-14+17:40",
    "format": "Standard",
    "language": "Telugu",
    "totalSeatSold": 0,
    "occupancy": 0.0,
    "totalAvailableSeatCount": 200,
    "totalSeatCount": 200,
    "grossRevenueUSD": 0.0,
    "adultTicketPrice": 14.38
  },
  {
    "state": "NJ",
    "city": "Burlington",
    "zip": "08016",
    "theater_name": "Regal Burlington",
    "chainName": "Regal",
    "chainCode": "REGL",
    "showtime_id": 515617719,
    "date": "2025-09-14+21:00",
    "format": "Standard",
    "language": "Telugu",
    "totalSeatSold": 1,
    "occupancy": 0.5,
    "totalAvailableSeatCount": 199,
    "totalSeatCount": 200,
    "grossRevenueUSD": 14.38,
    "adultTicketPrice": 14.38
  },
  {
    "state": "NJ",
    "city": "Hamilton Township",
    "zip": "08610",
    "theater_name": "Regal Independence Plaza & RPX",
    "chainName": "Regal",
    "chainCode": "REGL",
    "showtime_id": 515524995,
    "date": "2025-09-14+18:05",
    "format": "Standard",
    "language": "Telugu",
    "totalSeatSold": 10,
    "occupancy": 20.41,
    "totalAvailableSeatCount": 39,
    "totalSeatCount": 49,
    "grossRevenueUSD": 154.5,
    "adultTicketPrice": 15.45
  },
  {
    "state": "DE",
    "city": "Wilmington",
    "zip": "19804",
    "theater_name": "Cinemark Wilmington Movies 10",
    "chainName": "Cinemark Theatres",
    "chainCode": "CNMK",
    "showtime_id": 515800189,
    "date": "2025-09-14+15:45",
    "format": "Standard",
    "language": "Telugu",
    "totalSeatSold": 15,
    "occupancy": 16.3,
    "totalAvailableSeatCount": 77,
    "totalSeatCount": 92,
    "grossRevenueUSD": 101.25,
    "adultTicketPrice": 6.75
  },
  {
    "state": "DE",
    "city": "Newark",
    "zip": "19702",
    "theater_name": "Regal Peoples Plaza",
    "chainName": "Regal",
    "chainCode": "REGL",
    "showtime_id": 515495827,
    "date": "2025-09-14+11:20",
    "format": "Standard",
    "language": "Telugu",
    "totalSeatSold": 19,
    "occupancy": 57.58,
    "totalAvailableSeatCount": 14,
    "totalSeatCount": 33,
    "grossRevenueUSD": 208.81,
    "adultTicketPrice": 10.99
  },
  {
    "state": "DE",
    "city": "Newark",
    "zip": "19702",
    "theater_name": "Regal Peoples Plaza",
    "chainName": "Regal",
    "chainCode": "REGL",
    "showtime_id": 515495828,
    "date": "2025-09-14+14:40",
    "format": "Standard",
    "language": "Telugu",
    "totalSeatSold": 16,
    "occupancy": 48.48,
    "totalAvailableSeatCount": 17,
    "totalSeatCount": 33,
    "grossRevenueUSD": 175.84,
    "adultTicketPrice": 10.99
  },
  {
    "state": "DE",
    "city": "Newark",
    "zip": "19702",
    "theater_name": "Regal Peoples Plaza",
    "chainName": "Regal",
    "chainCode": "REGL",
    "showtime_id": 515495829,
    "date": "2025-09-14+17:55",
    "format": "Standard",
    "language": "Telugu",
    "totalSeatSold": 17,
    "occupancy": 51.52,
    "totalAvailableSeatCount": 16,
    "totalSeatCount": 33,
    "grossRevenueUSD": 237.83,
    "adultTicketPrice": 13.99
  },
  {
    "state": "DE",
    "city": "Newark",
    "zip": "19702",
    "theater_name": "Regal Peoples Plaza",
    "chainName": "Regal",
    "chainCode": "REGL",
    "showtime_id": 515495830,
    "date": "2025-09-14+21:20",
    "format": "Standard",
    "language": "Telugu",
    "totalSeatSold": 15,
    "occupancy": 45.45,
    "totalAvailableSeatCount": 18,
    "totalSeatCount": 33,
    "grossRevenueUSD": 209.85,
    "adultTicketPrice": 13.99
  },
  {
    "state": "NY",
    "city": "Buffalo",
    "zip": "14207",
    "theater_name": "Regal Elmwood Center",
    "chainName": "Regal",
    "chainCode": "REGL",
    "showtime_id": 515612642,
    "date": "2025-09-14+13:10",
    "format": "Standard",
    "language": "Telugu",
    "totalSeatSold": 8,
    "occupancy": 10.13,
    "totalAvailableSeatCount": 71,
    "totalSeatCount": 79,
    "grossRevenueUSD": 91.92,
    "adultTicketPrice": 11.49
  },
  {
    "state": "NY",
    "city": "Buffalo",
    "zip": "14207",
    "theater_name": "Regal Elmwood Center",
    "chainName": "Regal",
    "chainCode": "REGL",
    "showtime_id": 515612643,
    "date": "2025-09-14+20:40",
    "format": "Standard",
    "language": "Telugu",
    "totalSeatSold": 5,
    "occupancy": 6.33,
    "totalAvailableSeatCount": 74,
    "totalSeatCount": 79,
    "grossRevenueUSD": 72.45,
    "adultTicketPrice": 14.49
  },
  {
    "state": "PA",
    "city": "Bridgeville",
    "zip": "15017",
    "theater_name": "CHARTIERS VALLEY LUXURY 14 + PTX ",
    "chainName": "Phoenix Theatres",
    "chainCode": "PHNX",
    "showtime_id": 515553921,
    "date": "2025-09-14+14:30",
    "format": "Standard",
    "language": "Telugu",
    "totalSeatSold": 3,
    "occupancy": 4.76,
    "totalAvailableSeatCount": 60,
    "totalSeatCount": 63,
    "grossRevenueUSD": 36.0,
    "adultTicketPrice": 12.0
  },
  {
    "state": "PA",
    "city": "Downingtown",
    "zip": "19335",
    "theater_name": "Regal Downingtown & IMAX",
    "chainName": "Regal",
    "chainCode": "REGL",
    "showtime_id": 515356962,
    "date": "2025-09-14+11:15",
    "format": "Standard",
    "language": "Telugu",
    "totalSeatSold": 11,
    "occupancy": 14.47,
    "totalAvailableSeatCount": 65,
    "totalSeatCount": 76,
    "grossRevenueUSD": 148.39,
    "adultTicketPrice": 13.49
  },
  {
    "state": "PA",
    "city": "Downingtown",
    "zip": "19335",
    "theater_name": "Regal Downingtown & IMAX",
    "chainName": "Regal",
    "chainCode": "REGL",
    "showtime_id": 515356963,
    "date": "2025-09-14+14:40",
    "format": "Standard",
    "language": "Telugu",
    "totalSeatSold": 49,
    "occupancy": 64.47,
    "totalAvailableSeatCount": 27,
    "totalSeatCount": 76,
    "grossRevenueUSD": 661.01,
    "adultTicketPrice": 13.49
  },
  {
    "state": "PA",
    "city": "Downingtown",
    "zip": "19335",
    "theater_name": "Regal Downingtown & IMAX",
    "chainName": "Regal",
    "chainCode": "REGL",
    "showtime_id": 515356965,
    "date": "2025-09-14+18:00",
    "format": "Standard",
    "language": "Telugu",
    "totalSeatSold": 8,
    "occupancy": 10.53,
    "totalAvailableSeatCount": 68,
    "totalSeatCount": 76,
    "grossRevenueUSD": 135.92,
    "adultTicketPrice": 16.99
  },
  {
    "state": "PA",
    "city": "Downingtown",
    "zip": "19335",
    "theater_name": "Regal Downingtown & IMAX",
    "chainName": "Regal",
    "chainCode": "REGL",
    "showtime_id": 515879888,
    "date": "2025-09-14+18:45",
    "format": "Standard",
    "language": "Telugu",
    "totalSeatSold": 6,
    "occupancy": 12.24,
    "totalAvailableSeatCount": 43,
    "totalSeatCount": 49,
    "grossRevenueUSD": 101.94,
    "adultTicketPrice": 16.99
  },
  {
    "state": "PA",
    "city": "Downingtown",
    "zip": "19335",
    "theater_name": "Regal Downingtown & IMAX",
    "chainName": "Regal",
    "chainCode": "REGL",
    "showtime_id": 515356967,
    "date": "2025-09-14+21:20",
    "format": "Standard",
    "language": "Telugu",
    "totalSeatSold": 7,
    "occupancy": 9.21,
    "totalAvailableSeatCount": 69,
    "totalSeatCount": 76,
    "grossRevenueUSD": 118.93,
    "adultTicketPrice": 16.99
  },
  {
    "state": "PA",
    "city": "Oaks",
    "zip": "19456",
    "theater_name": "Oaks Center Cinema",
    "chainName": "Veezi Theaters",
    "chainCode": "VZ",
    "showtime_id": 515514457,
    "date": "2025-09-14+22:00",
    "format": "Standard",
    "language": "Telugu",
    "error": {
      "status": 400
    }
  },
  {
    "state": "VA",
    "city": "Ashburn",
    "zip": "20148",
    "theater_name": "Regal Fox 4DX & IMAX",
    "chainName": "Regal",
    "chainCode": "REGL",
    "showtime_id": 515660971,
    "date": "2025-09-14+11:40",
    "format": "Standard",
    "language": "Telugu",
    "totalSeatSold": 8,
    "occupancy": 3.51,
    "totalAvailableSeatCount": 220,
    "totalSeatCount": 228,
    "grossRevenueUSD": 99.92,
    "adultTicketPrice": 12.49
  },
  {
    "state": "VA",
    "city": "Ashburn",
    "zip": "20148",
    "theater_name": "Regal Fox 4DX & IMAX",
    "chainName": "Regal",
    "chainCode": "REGL",
    "showtime_id": 515660972,
    "date": "2025-09-14+14:55",
    "format": "Standard",
    "language": "Telugu",
    "totalSeatSold": 24,
    "occupancy": 10.53,
    "totalAvailableSeatCount": 204,
    "totalSeatCount": 228,
    "grossRevenueUSD": 299.76,
    "adultTicketPrice": 12.49
  },
  {
    "state": "VA",
    "city": "Ashburn",
    "zip": "20148",
    "theater_name": "Regal Fox 4DX & IMAX",
    "chainName": "Regal",
    "chainCode": "REGL",
    "showtime_id": 515660973,
    "date": "2025-09-14+18:15",
    "format": "Standard",
    "language": "Telugu",
    "totalSeatSold": 23,
    "occupancy": 10.09,
    "totalAvailableSeatCount": 205,
    "totalSeatCount": 228,
    "grossRevenueUSD": 367.77,
    "adultTicketPrice": 15.99
  },
  {
    "state": "VA",
    "city": "Ashburn",
    "zip": "20148",
    "theater_name": "Regal Fox 4DX & IMAX",
    "chainName": "Regal",
    "chainCode": "REGL",
    "showtime_id": 515660928,
    "date": "2025-09-14+21:50",
    "format": "Standard",
    "language": "Telugu",
    "totalSeatSold": 0,
    "occupancy": 0.0,
    "totalAvailableSeatCount": 299,
    "totalSeatCount": 299,
    "grossRevenueUSD": 0.0,
    "adultTicketPrice": 15.99
  },
  {
    "state": "VA",
    "city": "Richmond",
    "zip": "23233",
    "theater_name": "Regal Short Pump",
    "chainName": "Regal",
    "chainCode": "REGL",
    "showtime_id": 515724919,
    "date": "2025-09-14+12:35",
    "format": "Standard",
    "language": "Telugu",
    "totalSeatSold": 79,
    "occupancy": 73.83,
    "totalAvailableSeatCount": 28,
    "totalSeatCount": 107,
    "grossRevenueUSD": 947.21,
    "adultTicketPrice": 11.99
  },
  {
    "state": "NC",
    "city": "Cary",
    "zip": "27519",
    "theater_name": "Hooky Entertainment Cary",
    "chainName": "Hooky Entertainment",
    "chainCode": "HOOK",
    "showtime_id": 515519023,
    "date": "2025-09-14+14:30",
    "format": "Standard",
    "language": "Unknown",
    "totalSeatSold": 65,
    "occupancy": 77.38,
    "totalAvailableSeatCount": 19,
    "totalSeatCount": 84,
    "grossRevenueUSD": 1184.95,
    "adultTicketPrice": 18.23
  },
  {
    "state": "NC",
    "city": "Cary",
    "zip": "27518",
    "theater_name": "Regal Crossroads & IMAX - Cary",
    "chainName": "Regal",
    "chainCode": "REGL",
    "showtime_id": 515426064,
    "date": "2025-09-14+19:55",
    "format": "Standard",
    "language": "Telugu",
    "totalSeatSold": 37,
    "occupancy": 74.0,
    "totalAvailableSeatCount": 13,
    "totalSeatCount": 50,
    "grossRevenueUSD": 594.59,
    "adultTicketPrice": 16.07
  },
  {
    "state": "NC",
    "city": "Charlotte",
    "zip": "28273",
    "theater_name": "Ayrsley Grand Cinemas",
    "chainName": "Southeast Cinemas",
    "chainCode": "SEC",
    "showtime_id": 515942528,
    "date": "2025-09-14+18:00",
    "format": "Standard",
    "language": "Unknown",
    "totalSeatSold": 4,
    "occupancy": 8.33,
    "totalAvailableSeatCount": 44,
    "totalSeatCount": 48,
    "grossRevenueUSD": 48.0,
    "adultTicketPrice": 12.0
  },
  {
    "state": "GA",
    "city": "Duluth",
    "zip": "30097",
    "theater_name": "Regal Medlock Crossing & RPX",
    "chainName": "Regal",
    "chainCode": "REGL",
    "showtime_id": 515789827,
    "date": "2025-09-14+18:50",
    "format": "Standard",
    "language": "Telugu",
    "totalSeatSold": 84,
    "occupancy": 88.42,
    "totalAvailableSeatCount": 11,
    "totalSeatCount": 95,
    "grossRevenueUSD": 1538.04,
    "adultTicketPrice": 18.31
  },
  {
    "state": "GA",
    "city": "Duluth",
    "zip": "30097",
    "theater_name": "Regal Medlock Crossing & RPX",
    "chainName": "Regal",
    "chainCode": "REGL",
    "showtime_id": 515789829,
    "date": "2025-09-14+22:10",
    "format": "Standard",
    "language": "Telugu",
    "totalSeatSold": 63,
    "occupancy": 66.32,
    "totalAvailableSeatCount": 32,
    "totalSeatCount": 95,
    "grossRevenueUSD": 1153.53,
    "adultTicketPrice": 18.31
  },
  {
    "state": "GA",
    "city": "Roswell",
    "zip": "30076",
    "theater_name": "Aurora Cineplex",
    "chainName": "RTSIND",
    "chainCode": "RTSIND",
    "showtime_id": 515635827,
    "date": "2025-09-14+10:15",
    "format": "Standard",
    "language": "Telugu",
    "totalSeatSold": 1,
    "occupancy": 1.67,
    "totalAvailableSeatCount": 59,
    "totalSeatCount": 60,
    "grossRevenueUSD": 7.5,
    "adultTicketPrice": 7.5
  },
  {
    "state": "GA",
    "city": "Roswell",
    "zip": "30076",
    "theater_name": "Aurora Cineplex",
    "chainName": "RTSIND",
    "chainCode": "RTSIND",
    "showtime_id": 515635828,
    "date": "2025-09-14+13:10",
    "format": "Standard",
    "language": "Telugu",
    "totalSeatSold": 4,
    "occupancy": 6.67,
    "totalAvailableSeatCount": 56,
    "totalSeatCount": 60,
    "grossRevenueUSD": 34.0,
    "adultTicketPrice": 8.5
  },
  {
    "state": "GA",
    "city": "Roswell",
    "zip": "30076",
    "theater_name": "Aurora Cineplex",
    "chainName": "RTSIND",
    "chainCode": "RTSIND",
    "showtime_id": 515635829,
    "date": "2025-09-14+16:00",
    "format": "Standard",
    "language": "Telugu",
    "totalSeatSold": 23,
    "occupancy": 38.33,
    "totalAvailableSeatCount": 37,
    "totalSeatCount": 60,
    "grossRevenueUSD": 195.5,
    "adultTicketPrice": 8.5
  },
  {
    "state": "GA",
    "city": "Roswell",
    "zip": "30076",
    "theater_name": "Aurora Cineplex",
    "chainName": "RTSIND",
    "chainCode": "RTSIND",
    "showtime_id": 515635830,
    "date": "2025-09-14+18:45",
    "format": "Standard",
    "language": "Telugu",
    "totalSeatSold": 15,
    "occupancy": 25.0,
    "totalAvailableSeatCount": 45,
    "totalSeatCount": 60,
    "grossRevenueUSD": 150.0,
    "adultTicketPrice": 10.0
  },
  {
    "state": "FL",
    "city": "Jacksonville",
    "zip": "32256",
    "theater_name": "Regal Avenues 4DX & RPX",
    "chainName": "Regal",
    "chainCode": "REGL",
    "showtime_id": 515599501,
    "date": "2025-09-14+18:10",
    "format": "Standard",
    "language": "Telugu",
    "totalSeatSold": 8,
    "occupancy": 9.09,
    "totalAvailableSeatCount": 80,
    "totalSeatCount": 88,
    "grossRevenueUSD": 116.0,
    "adultTicketPrice": 14.5
  },
  {
    "state": "FL",
    "city": "Jacksonville",
    "zip": "32216",
    "theater_name": "Cinemark Tinseltown Jacksonville and XD",
    "chainName": "Cinemark Theatres",
    "chainCode": "CNMK",
    "showtime_id": 515763721,
    "date": "2025-09-14+21:20",
    "format": "Standard",
    "language": "Telugu",
    "totalSeatSold": 23,
    "occupancy": 26.74,
    "totalAvailableSeatCount": 63,
    "totalSeatCount": 86,
    "grossRevenueUSD": 296.7,
    "adultTicketPrice": 12.9
  },
  {
    "state": "FL",
    "city": "Gainesville",
    "zip": "32607",
    "theater_name": "Regal Royal Park",
    "chainName": "Regal",
    "chainCode": "REGL",
    "showtime_id": 515610089,
    "date": "2025-09-14+11:55",
    "format": "Standard",
    "language": "Telugu",
    "totalSeatSold": 12,
    "occupancy": 12.5,
    "totalAvailableSeatCount": 84,
    "totalSeatCount": 96,
    "grossRevenueUSD": 135.36,
    "adultTicketPrice": 11.28
  },
  {
    "state": "FL",
    "city": "Gainesville",
    "zip": "32607",
    "theater_name": "Regal Royal Park",
    "chainName": "Regal",
    "chainCode": "REGL",
    "showtime_id": 515610117,
    "date": "2025-09-14+18:15",
    "format": "Standard",
    "language": "Telugu",
    "totalSeatSold": 21,
    "occupancy": 21.88,
    "totalAvailableSeatCount": 75,
    "totalSeatCount": 96,
    "grossRevenueUSD": 304.5,
    "adultTicketPrice": 14.5
  },
  {
    "state": "FL",
    "city": "Orlando",
    "zip": "32819",
    "theater_name": "Cinemark Orlando and XD",
    "chainName": "Cinemark Theatres",
    "chainCode": "CNMK",
    "showtime_id": 515845335,
    "date": "2025-09-14+12:35",
    "format": "Standard",
    "language": "Telugu",
    "totalSeatSold": 2,
    "occupancy": 3.03,
    "totalAvailableSeatCount": 64,
    "totalSeatCount": 66,
    "grossRevenueUSD": 19.16,
    "adultTicketPrice": 9.58
  },
  {
    "state": "FL",
    "city": "Orlando",
    "zip": "32819",
    "theater_name": "Cinemark Orlando and XD",
    "chainName": "Cinemark Theatres",
    "chainCode": "CNMK",
    "showtime_id": 515845336,
    "date": "2025-09-14+15:45",
    "format": "Standard",
    "language": "Telugu",
    "totalSeatSold": 7,
    "occupancy": 10.61,
    "totalAvailableSeatCount": 59,
    "totalSeatCount": 66,
    "grossRevenueUSD": 67.06,
    "adultTicketPrice": 9.58
  },
  {
    "state": "FL",
    "city": "Orlando",
    "zip": "32819",
    "theater_name": "Cinemark Orlando and XD",
    "chainName": "Cinemark Theatres",
    "chainCode": "CNMK",
    "showtime_id": 515845337,
    "date": "2025-09-14+18:50",
    "format": "Standard",
    "language": "Telugu",
    "totalSeatSold": 0,
    "occupancy": 0.0,
    "totalAvailableSeatCount": 66,
    "totalSeatCount": 66,
    "grossRevenueUSD": 0.0,
    "adultTicketPrice": 11.98
  },
  {
    "state": "FL",
    "city": "Orlando",
    "zip": "32819",
    "theater_name": "Cinemark Orlando and XD",
    "chainName": "Cinemark Theatres",
    "chainCode": "CNMK",
    "showtime_id": 515845338,
    "date": "2025-09-14+21:55",
    "format": "Standard",
    "language": "Telugu",
    "totalSeatSold": 0,
    "occupancy": 0.0,
    "totalAvailableSeatCount": 66,
    "totalSeatCount": 66,
    "grossRevenueUSD": 0.0,
    "adultTicketPrice": 11.98
  },
  {
    "state": "FL",
    "city": "Orlando",
    "zip": "32819",
    "theater_name": "Regal Pointe Orlando 4DX & IMAX",
    "chainName": "Regal",
    "chainCode": "REGL",
    "showtime_id": 515552932,
    "date": "2025-09-14+11:25",
    "format": "Standard",
    "language": "Telugu",
    "totalSeatSold": 0,
    "occupancy": 0.0,
    "totalAvailableSeatCount": 31,
    "totalSeatCount": 31,
    "grossRevenueUSD": 0.0,
    "adultTicketPrice": 13.83
  },
  {
    "state": "FL",
    "city": "Orlando",
    "zip": "32819",
    "theater_name": "Regal Pointe Orlando 4DX & IMAX",
    "chainName": "Regal",
    "chainCode": "REGL",
    "showtime_id": 515552930,
    "date": "2025-09-14+14:45",
    "format": "Standard",
    "language": "Telugu",
    "totalSeatSold": 5,
    "occupancy": 16.13,
    "totalAvailableSeatCount": 26,
    "totalSeatCount": 31,
    "grossRevenueUSD": 69.15,
    "adultTicketPrice": 13.83
  },
  {
    "state": "FL",
    "city": "Orlando",
    "zip": "32819",
    "theater_name": "Regal Pointe Orlando 4DX & IMAX",
    "chainName": "Regal",
    "chainCode": "REGL",
    "showtime_id": 515552931,
    "date": "2025-09-14+18:45",
    "format": "Standard",
    "language": "Telugu",
    "totalSeatSold": 1,
    "occupancy": 3.23,
    "totalAvailableSeatCount": 30,
    "totalSeatCount": 31,
    "grossRevenueUSD": 17.56,
    "adultTicketPrice": 17.56
  },
  {
    "state": "FL",
    "city": "Davie",
    "zip": "33331",
    "theater_name": "Cinemark Paradise 24 and XD",
    "chainName": "Cinemark Theatres",
    "chainCode": "CNMK",
    "showtime_id": 515796883,
    "date": "2025-09-14+12:55",
    "format": "Standard",
    "language": "Telugu",
    "totalSeatSold": 33,
    "occupancy": 73.33,
    "totalAvailableSeatCount": 12,
    "totalSeatCount": 45,
    "grossRevenueUSD": 308.88,
    "adultTicketPrice": 9.36
  },
  {
    "state": "FL",
    "city": "Davie",
    "zip": "33331",
    "theater_name": "Cinemark Paradise 24 and XD",
    "chainName": "Cinemark Theatres",
    "chainCode": "CNMK",
    "showtime_id": 515796884,
    "date": "2025-09-14+22:50",
    "format": "Standard",
    "language": "Telugu",
    "totalSeatSold": 0,
    "occupancy": 0.0,
    "totalAvailableSeatCount": 45,
    "totalSeatCount": 45,
    "grossRevenueUSD": 0.0,
    "adultTicketPrice": 11.5
  },
  {
    "state": "AL",
    "city": "Birmingham",
    "zip": "35235",
    "theater_name": "Regal Trussville",
    "chainName": "Regal",
    "chainCode": "REGL",
    "showtime_id": 515821367,
    "date": "2025-09-14+12:20",
    "format": "Standard",
    "language": "Telugu",
    "totalSeatSold": 0,
    "occupancy": 0.0,
    "totalAvailableSeatCount": 191,
    "totalSeatCount": 191,
    "grossRevenueUSD": 0.0,
    "adultTicketPrice": 10.99
  },
  {
    "state": "AL",
    "city": "Birmingham",
    "zip": "35235",
    "theater_name": "Regal Trussville",
    "chainName": "Regal",
    "chainCode": "REGL",
    "showtime_id": 515821368,
    "date": "2025-09-14+18:45",
    "format": "Standard",
    "language": "Telugu",
    "totalSeatSold": 0,
    "occupancy": 0.0,
    "totalAvailableSeatCount": 191,
    "totalSeatCount": 191,
    "grossRevenueUSD": 0.0,
    "adultTicketPrice": 14.29
  },
  {
    "state": "TN",
    "city": "Nashville",
    "zip": "37204",
    "theater_name": "Regal Hollywood ScreenX, 4DX & RPX \u2013 Nashville",
    "chainName": "Regal",
    "chainCode": "REGL",
    "showtime_id": 515692958,
    "date": "2025-09-14+13:55",
    "format": "Standard",
    "language": "Telugu",
    "totalSeatSold": 15,
    "occupancy": 8.82,
    "totalAvailableSeatCount": 155,
    "totalSeatCount": 170,
    "grossRevenueUSD": 205.5,
    "adultTicketPrice": 13.7
  },
  {
    "state": "TN",
    "city": "Nashville",
    "zip": "37204",
    "theater_name": "Regal Hollywood ScreenX, 4DX & RPX \u2013 Nashville",
    "chainName": "Regal",
    "chainCode": "REGL",
    "showtime_id": 515692957,
    "date": "2025-09-14+17:15",
    "format": "Standard",
    "language": "Telugu",
    "totalSeatSold": 13,
    "occupancy": 7.65,
    "totalAvailableSeatCount": 157,
    "totalSeatCount": 170,
    "grossRevenueUSD": 228.15,
    "adultTicketPrice": 17.55
  },
  {
    "state": "TN",
    "city": "Nashville",
    "zip": "37204",
    "theater_name": "Regal Hollywood ScreenX, 4DX & RPX \u2013 Nashville",
    "chainName": "Regal",
    "chainCode": "REGL",
    "showtime_id": 515692956,
    "date": "2025-09-14+20:45",
    "format": "Standard",
    "language": "Telugu",
    "totalSeatSold": 1,
    "occupancy": 0.59,
    "totalAvailableSeatCount": 169,
    "totalSeatCount": 170,
    "grossRevenueUSD": 17.55,
    "adultTicketPrice": 17.55
  },
  {
    "state": "TN",
    "city": "Memphis",
    "zip": "38133",
    "theater_name": "Malco Wolfchase Cinema Grill",
    "chainName": "Malco Theatres 2",
    "chainCode": "MALCO",
    "showtime_id": 515690955,
    "date": "2025-09-14+13:10",
    "format": "Standard",
    "language": "Telugu",
    "error": {
      "status": 400
    }
  },
  {
    "state": "TN",
    "city": "Memphis",
    "zip": "38133",
    "theater_name": "Malco Wolfchase Cinema Grill",
    "chainName": "Malco Theatres 2",
    "chainCode": "MALCO",
    "showtime_id": 515690956,
    "date": "2025-09-14+16:00",
    "format": "Standard",
    "language": "Telugu",
    "error": {
      "status": 400
    }
  },
  {
    "state": "TN",
    "city": "Memphis",
    "zip": "38133",
    "theater_name": "Malco Wolfchase Cinema Grill",
    "chainName": "Malco Theatres 2",
    "chainCode": "MALCO",
    "showtime_id": 515690957,
    "date": "2025-09-14+19:10",
    "format": "Standard",
    "language": "Telugu",
    "error": {
      "status": 400
    }
  },
  {
    "state": "KY",
    "city": "Louisville",
    "zip": "40241",
    "theater_name": "Cinemark Tinseltown Louisville and XD",
    "chainName": "Cinemark Theatres",
    "chainCode": "CNMK",
    "showtime_id": 515844600,
    "date": "2025-09-14+21:40",
    "format": "Standard",
    "language": "Telugu",
    "totalSeatSold": 8,
    "occupancy": 19.51,
    "totalAvailableSeatCount": 33,
    "totalSeatCount": 41,
    "grossRevenueUSD": 101.76,
    "adultTicketPrice": 12.72
  },
  {
    "state": "OH",
    "city": "Milford",
    "zip": "45150",
    "theater_name": "Cinemark Milford 16",
    "chainName": "Cinemark Theatres",
    "chainCode": "CNMK",
    "showtime_id": 515621674,
    "date": "2025-09-14+12:25",
    "format": "Standard",
    "language": "Telugu",
    "totalSeatSold": 0,
    "occupancy": 0.0,
    "totalAvailableSeatCount": 234,
    "totalSeatCount": 234,
    "grossRevenueUSD": 0.0,
    "adultTicketPrice": 6.95
  },
  {
    "state": "OH",
    "city": "Milford",
    "zip": "45150",
    "theater_name": "Cinemark Milford 16",
    "chainName": "Cinemark Theatres",
    "chainCode": "CNMK",
    "showtime_id": 515621675,
    "date": "2025-09-14+15:35",
    "format": "Standard",
    "language": "Telugu",
    "totalSeatSold": 0,
    "occupancy": 0.0,
    "totalAvailableSeatCount": 234,
    "totalSeatCount": 234,
    "grossRevenueUSD": 0.0,
    "adultTicketPrice": 6.95
  },
  {
    "state": "OH",
    "city": "Milford",
    "zip": "45150",
    "theater_name": "Cinemark Milford 16",
    "chainName": "Cinemark Theatres",
    "chainCode": "CNMK",
    "showtime_id": 515621676,
    "date": "2025-09-14+18:45",
    "format": "Standard",
    "language": "Telugu",
    "totalSeatSold": 0,
    "occupancy": 0.0,
    "totalAvailableSeatCount": 234,
    "totalSeatCount": 234,
    "grossRevenueUSD": 0.0,
    "adultTicketPrice": 9.53
  },
  {
    "state": "OH",
    "city": "Milford",
    "zip": "45150",
    "theater_name": "Cinemark Milford 16",
    "chainName": "Cinemark Theatres",
    "chainCode": "CNMK",
    "showtime_id": 515621677,
    "date": "2025-09-14+21:55",
    "format": "Standard",
    "language": "Telugu",
    "totalSeatSold": 0,
    "occupancy": 0.0,
    "totalAvailableSeatCount": 234,
    "totalSeatCount": 234,
    "grossRevenueUSD": 0.0,
    "adultTicketPrice": 9.53
  },
  {
    "state": "OH",
    "city": "Columbus",
    "zip": "43240",
    "theater_name": "Cinemark Polaris 18 and XD",
    "chainName": "Cinemark Theatres",
    "chainCode": "CNMK",
    "showtime_id": 515429657,
    "date": "2025-09-14+15:50",
    "format": "Standard",
    "language": "Telugu",
    "totalSeatSold": 21,
    "occupancy": 42.0,
    "totalAvailableSeatCount": 29,
    "totalSeatCount": 50,
    "grossRevenueUSD": 183.75,
    "adultTicketPrice": 8.75
  },
  {
    "state": "OH",
    "city": "Columbus",
    "zip": "43240",
    "theater_name": "Cinemark Polaris 18 and XD",
    "chainName": "Cinemark Theatres",
    "chainCode": "CNMK",
    "showtime_id": 515429658,
    "date": "2025-09-14+19:55",
    "format": "Standard",
    "language": "Telugu",
    "totalSeatSold": 8,
    "occupancy": 12.7,
    "totalAvailableSeatCount": 55,
    "totalSeatCount": 63,
    "grossRevenueUSD": 90.0,
    "adultTicketPrice": 11.25
  },
  {
    "state": "OH",
    "city": "Columbus",
    "zip": "43240",
    "theater_name": "Cinemark Polaris 18 and XD",
    "chainName": "Cinemark Theatres",
    "chainCode": "CNMK",
    "showtime_id": 515429659,
    "date": "2025-09-14+23:00",
    "format": "Standard",
    "language": "Telugu",
    "totalSeatSold": 0,
    "occupancy": 0.0,
    "totalAvailableSeatCount": 63,
    "totalSeatCount": 63,
    "grossRevenueUSD": 0.0,
    "adultTicketPrice": 11.25
  },
  {
    "state": "OH",
    "city": "Columbus",
    "zip": "43212",
    "theater_name": "Lennox Town Center 24",
    "chainName": "Phoenix Theatres",
    "chainCode": "PHNX",
    "showtime_id": 515513849,
    "date": "2025-09-14+11:30",
    "format": "Standard",
    "language": "Telugu",
    "totalSeatSold": 0,
    "occupancy": 0.0,
    "totalAvailableSeatCount": 97,
    "totalSeatCount": 97,
    "grossRevenueUSD": 0.0,
    "adultTicketPrice": 12.96
  },
  {
    "state": "OH",
    "city": "Columbus",
    "zip": "43212",
    "theater_name": "Lennox Town Center 24",
    "chainName": "Phoenix Theatres",
    "chainCode": "PHNX",
    "showtime_id": 515513850,
    "date": "2025-09-14+14:45",
    "format": "Standard",
    "language": "Telugu",
    "totalSeatSold": 0,
    "occupancy": 0.0,
    "totalAvailableSeatCount": 97,
    "totalSeatCount": 97,
    "grossRevenueUSD": 0.0,
    "adultTicketPrice": 12.96
  },
  {
    "state": "OH",
    "city": "Columbus",
    "zip": "43212",
    "theater_name": "Lennox Town Center 24",
    "chainName": "Phoenix Theatres",
    "chainCode": "PHNX",
    "showtime_id": 515513851,
    "date": "2025-09-14+18:00",
    "format": "Standard",
    "language": "Telugu",
    "totalSeatSold": 0,
    "occupancy": 0.0,
    "totalAvailableSeatCount": 97,
    "totalSeatCount": 97,
    "grossRevenueUSD": 0.0,
    "adultTicketPrice": 12.96
  },
  {
    "state": "OH",
    "city": "Columbus",
    "zip": "43212",
    "theater_name": "Lennox Town Center 24",
    "chainName": "Phoenix Theatres",
    "chainCode": "PHNX",
    "showtime_id": 515513852,
    "date": "2025-09-14+21:15",
    "format": "Standard",
    "language": "Telugu",
    "totalSeatSold": 0,
    "occupancy": 0.0,
    "totalAvailableSeatCount": 97,
    "totalSeatCount": 97,
    "grossRevenueUSD": 0.0,
    "adultTicketPrice": 12.96
  },
  {
    "state": "OH",
    "city": "Toledo",
    "zip": "43623",
    "theater_name": "Cinemark Franklin Park 16 and XD",
    "chainName": "Cinemark Theatres",
    "chainCode": "CNMK",
    "showtime_id": 515731354,
    "date": "2025-09-14+19:30",
    "format": "Standard",
    "language": "Telugu",
    "totalSeatSold": 0,
    "occupancy": 0.0,
    "totalAvailableSeatCount": 172,
    "totalSeatCount": 172,
    "grossRevenueUSD": 0.0,
    "adultTicketPrice": 11.5
  },
  {
    "state": "MI",
    "city": "Ypsilanti",
    "zip": "48197",
    "theater_name": "Ann Arbor 20 + IMAX",
    "chainName": "Cinemark Theatres",
    "chainCode": "CNMK",
    "showtime_id": 515688861,
    "date": "2025-09-14+18:15",
    "format": "Standard",
    "language": "Telugu",
    "totalSeatSold": 16,
    "occupancy": 25.81,
    "totalAvailableSeatCount": 46,
    "totalSeatCount": 62,
    "grossRevenueUSD": 180.0,
    "adultTicketPrice": 11.25
  },
  {
    "state": "MI",
    "city": "Ypsilanti",
    "zip": "48197",
    "theater_name": "Ann Arbor 20 + IMAX",
    "chainName": "Cinemark Theatres",
    "chainCode": "CNMK",
    "showtime_id": 515688862,
    "date": "2025-09-14+22:00",
    "format": "Standard",
    "language": "Telugu",
    "totalSeatSold": 0,
    "occupancy": 0.0,
    "totalAvailableSeatCount": 117,
    "totalSeatCount": 117,
    "grossRevenueUSD": 0.0,
    "adultTicketPrice": 11.25
  },
  {
    "state": "MI",
    "city": "Westland",
    "zip": "48185",
    "theater_name": "MJR Westland Cinema",
    "chainName": "MJR Theatres",
    "chainCode": "MJRT",
    "showtime_id": 515293310,
    "date": "2025-09-14+11:10",
    "format": "Standard",
    "language": "English",
    "totalSeatSold": 9,
    "occupancy": 11.54,
    "totalAvailableSeatCount": 69,
    "totalSeatCount": 78,
    "grossRevenueUSD": 60.75,
    "adultTicketPrice": 6.75
  },
  {
    "state": "OH",
    "city": "Valley View",
    "zip": "44125",
    "theater_name": "Cinemark Valley View and XD",
    "chainName": "Cinemark Theatres",
    "chainCode": "CNMK",
    "showtime_id": 515644051,
    "date": "2025-09-14+15:45",
    "format": "Standard",
    "language": "Telugu",
    "totalSeatSold": 16,
    "occupancy": 29.09,
    "totalAvailableSeatCount": 39,
    "totalSeatCount": 55,
    "grossRevenueUSD": 151.2,
    "adultTicketPrice": 9.45
  },
  {
    "state": "OH",
    "city": "Valley View",
    "zip": "44125",
    "theater_name": "Cinemark Valley View and XD",
    "chainName": "Cinemark Theatres",
    "chainCode": "CNMK",
    "showtime_id": 515644052,
    "date": "2025-09-14+22:30",
    "format": "Standard",
    "language": "Telugu",
    "totalSeatSold": 0,
    "occupancy": 0.0,
    "totalAvailableSeatCount": 55,
    "totalSeatCount": 55,
    "grossRevenueUSD": 0.0,
    "adultTicketPrice": 13.13
  },
  {
    "state": "OH",
    "city": "West Carrollton",
    "zip": "45449",
    "theater_name": "Cinemark Dayton South 16 and XD",
    "chainName": "Cinemark Theatres",
    "chainCode": "CNMK",
    "showtime_id": 515414592,
    "date": "2025-09-14+09:35",
    "format": "Standard",
    "language": "Telugu",
    "totalSeatSold": 0,
    "occupancy": 0.0,
    "totalAvailableSeatCount": 63,
    "totalSeatCount": 63,
    "grossRevenueUSD": 0.0,
    "adultTicketPrice": 9.5
  },
  {
    "state": "OH",
    "city": "West Carrollton",
    "zip": "45449",
    "theater_name": "Cinemark Dayton South 16 and XD",
    "chainName": "Cinemark Theatres",
    "chainCode": "CNMK",
    "showtime_id": 515414593,
    "date": "2025-09-14+12:40",
    "format": "Standard",
    "language": "Telugu",
    "totalSeatSold": 5,
    "occupancy": 7.94,
    "totalAvailableSeatCount": 58,
    "totalSeatCount": 63,
    "grossRevenueUSD": 47.5,
    "adultTicketPrice": 9.5
  },
  {
    "state": "OH",
    "city": "West Carrollton",
    "zip": "45449",
    "theater_name": "Cinemark Dayton South 16 and XD",
    "chainName": "Cinemark Theatres",
    "chainCode": "CNMK",
    "showtime_id": 515928632,
    "date": "2025-09-14+22:10",
    "format": "Standard",
    "language": "Telugu",
    "totalSeatSold": 0,
    "occupancy": 0.0,
    "totalAvailableSeatCount": 63,
    "totalSeatCount": 63,
    "grossRevenueUSD": 0.0,
    "adultTicketPrice": 13.0
  },
  {
    "state": "MI",
    "city": "Troy",
    "zip": "48083",
    "theater_name": "MJR Troy Cinema",
    "chainName": "MJR Theatres",
    "chainCode": "MJRT",
    "showtime_id": 515296341,
    "date": "2025-09-14+11:00",
    "format": "Standard",
    "language": "English",
    "totalSeatSold": 4,
    "occupancy": 2.74,
    "totalAvailableSeatCount": 142,
    "totalSeatCount": 146,
    "grossRevenueUSD": 28.0,
    "adultTicketPrice": 7.0
  },
  {
    "state": "MI",
    "city": "Walled Lake",
    "zip": "48390",
    "theater_name": "Regal UA Commerce Township",
    "chainName": "Regal",
    "chainCode": "REGL",
    "showtime_id": 515535785,
    "date": "2025-09-14+13:25",
    "format": "Standard",
    "language": "Telugu",
    "totalSeatSold": 7,
    "occupancy": 2.72,
    "totalAvailableSeatCount": 250,
    "totalSeatCount": 257,
    "grossRevenueUSD": 59.43,
    "adultTicketPrice": 8.49
  },
  {
    "state": "MI",
    "city": "Walled Lake",
    "zip": "48390",
    "theater_name": "Regal UA Commerce Township",
    "chainName": "Regal",
    "chainCode": "REGL",
    "showtime_id": 515535790,
    "date": "2025-09-14+16:20",
    "format": "Standard",
    "language": "Telugu",
    "totalSeatSold": 4,
    "occupancy": 1.56,
    "totalAvailableSeatCount": 253,
    "totalSeatCount": 257,
    "grossRevenueUSD": 43.96,
    "adultTicketPrice": 10.99
  },
  {
    "state": "MI",
    "city": "Walled Lake",
    "zip": "48390",
    "theater_name": "Regal UA Commerce Township",
    "chainName": "Regal",
    "chainCode": "REGL",
    "showtime_id": 515535786,
    "date": "2025-09-14+19:25",
    "format": "Standard",
    "language": "Telugu",
    "totalSeatSold": 7,
    "occupancy": 2.72,
    "totalAvailableSeatCount": 250,
    "totalSeatCount": 257,
    "grossRevenueUSD": 76.93,
    "adultTicketPrice": 10.99
  },
  {
    "state": "SD",
    "city": "Sioux Falls",
    "zip": "57106",
    "theater_name": "Cinemark Century Sioux Falls 14 and XD",
    "chainName": "Cinemark Theatres",
    "chainCode": "CNMK",
    "showtime_id": 515805212,
    "date": "2025-09-14+21:05",
    "format": "Standard",
    "language": "Telugu",
    "totalSeatSold": 0,
    "occupancy": 0.0,
    "totalAvailableSeatCount": 103,
    "totalSeatCount": 103,
    "grossRevenueUSD": 0.0,
    "adultTicketPrice": 9.11
  },
  {
    "state": "IL",
    "city": "Deer Park",
    "zip": "60010",
    "theater_name": "Cinemark Century Deer Park 16",
    "chainName": "Cinemark Theatres",
    "chainCode": "CNMK",
    "showtime_id": 515728905,
    "date": "2025-09-14+12:45",
    "format": "Standard",
    "language": "Telugu",
    "totalSeatSold": 3,
    "occupancy": 2.36,
    "totalAvailableSeatCount": 124,
    "totalSeatCount": 127,
    "grossRevenueUSD": 25.74,
    "adultTicketPrice": 8.58
  },
  {
    "state": "IL",
    "city": "Deer Park",
    "zip": "60010",
    "theater_name": "Cinemark Century Deer Park 16",
    "chainName": "Cinemark Theatres",
    "chainCode": "CNMK",
    "showtime_id": 515728906,
    "date": "2025-09-14+15:50",
    "format": "Standard",
    "language": "Telugu",
    "totalSeatSold": 0,
    "occupancy": 0.0,
    "totalAvailableSeatCount": 127,
    "totalSeatCount": 127,
    "grossRevenueUSD": 0.0,
    "adultTicketPrice": 10.66
  },
  {
    "state": "IL",
    "city": "Deer Park",
    "zip": "60010",
    "theater_name": "Cinemark Century Deer Park 16",
    "chainName": "Cinemark Theatres",
    "chainCode": "CNMK",
    "showtime_id": 515728907,
    "date": "2025-09-14+19:00",
    "format": "Standard",
    "language": "Telugu",
    "totalSeatSold": 0,
    "occupancy": 0.0,
    "totalAvailableSeatCount": 127,
    "totalSeatCount": 127,
    "grossRevenueUSD": 0.0,
    "adultTicketPrice": 10.66
  },
  {
    "state": "IL",
    "city": "Niles",
    "zip": "60714",
    "theater_name": "Cin\u00e9 Lounge at Niles",
    "chainName": "RTSIND",
    "chainCode": "RTSIND",
    "showtime_id": 515809065,
    "date": "2025-09-14+16:15",
    "format": "Standard",
    "language": "Telugu",
    "totalSeatSold": 1,
    "occupancy": 0.89,
    "totalAvailableSeatCount": 111,
    "totalSeatCount": 112,
    "grossRevenueUSD": 13.95,
    "adultTicketPrice": 13.95
  },
  {
    "state": "IL",
    "city": "Niles",
    "zip": "60714",
    "theater_name": "Cin\u00e9 Lounge at Niles",
    "chainName": "RTSIND",
    "chainCode": "RTSIND",
    "showtime_id": 515809058,
    "date": "2025-09-14+19:00",
    "format": "Standard",
    "language": "Telugu",
    "totalSeatSold": 2,
    "occupancy": 1.79,
    "totalAvailableSeatCount": 110,
    "totalSeatCount": 112,
    "grossRevenueUSD": 27.9,
    "adultTicketPrice": 13.95
  },
  {
    "state": "IL",
    "city": "Niles",
    "zip": "60714",
    "theater_name": "Cin\u00e9 Lounge at Niles",
    "chainName": "RTSIND",
    "chainCode": "RTSIND",
    "showtime_id": 515809054,
    "date": "2025-09-14+21:40",
    "format": "Standard",
    "language": "Telugu",
    "totalSeatSold": 0,
    "occupancy": 0.0,
    "totalAvailableSeatCount": 112,
    "totalSeatCount": 112,
    "grossRevenueUSD": 0.0,
    "adultTicketPrice": 13.95
  },
  {
    "state": "MN",
    "city": "Saint Louis Park",
    "zip": "55416",
    "theater_name": "Marcus West End Cinema",
    "chainName": "Marcus Theatres",
    "chainCode": "MRCS",
    "showtime_id": 515395094,
    "date": "2025-09-14+12:40",
    "format": "Standard",
    "language": "Telugu",
    "totalSeatSold": 20,
    "occupancy": 16.67,
    "totalAvailableSeatCount": 100,
    "totalSeatCount": 120,
    "grossRevenueUSD": 180.0,
    "adultTicketPrice": 9.0
  },
  {
    "state": "IL",
    "city": "North Aurora",
    "zip": "60542",
    "theater_name": "Cinemark Tinseltown USA Aurora",
    "chainName": "Cinemark Theatres",
    "chainCode": "CNMK",
    "showtime_id": 515396265,
    "date": "2025-09-14+10:30",
    "format": "Standard",
    "language": "Telugu",
    "totalSeatSold": 0,
    "occupancy": 0.0,
    "totalAvailableSeatCount": 121,
    "totalSeatCount": 121,
    "grossRevenueUSD": 0.0,
    "adultTicketPrice": 6.18
  },
  {
    "state": "IL",
    "city": "North Aurora",
    "zip": "60542",
    "theater_name": "Cinemark Tinseltown USA Aurora",
    "chainName": "Cinemark Theatres",
    "chainCode": "CNMK",
    "showtime_id": 515396266,
    "date": "2025-09-14+13:35",
    "format": "Standard",
    "language": "Telugu",
    "totalSeatSold": 0,
    "occupancy": 0.0,
    "totalAvailableSeatCount": 121,
    "totalSeatCount": 121,
    "grossRevenueUSD": 0.0,
    "adultTicketPrice": 6.18
  },
  {
    "state": "IL",
    "city": "North Aurora",
    "zip": "60542",
    "theater_name": "Cinemark Tinseltown USA Aurora",
    "chainName": "Cinemark Theatres",
    "chainCode": "CNMK",
    "showtime_id": 515396267,
    "date": "2025-09-14+16:40",
    "format": "Standard",
    "language": "Telugu",
    "totalSeatSold": 3,
    "occupancy": 2.48,
    "totalAvailableSeatCount": 118,
    "totalSeatCount": 121,
    "grossRevenueUSD": 25.5,
    "adultTicketPrice": 8.5
  },
  {
    "state": "IL",
    "city": "North Aurora",
    "zip": "60542",
    "theater_name": "Cinemark Tinseltown USA Aurora",
    "chainName": "Cinemark Theatres",
    "chainCode": "CNMK",
    "showtime_id": 515396268,
    "date": "2025-09-14+19:45",
    "format": "Standard",
    "language": "Telugu",
    "totalSeatSold": 0,
    "occupancy": 0.0,
    "totalAvailableSeatCount": 121,
    "totalSeatCount": 121,
    "grossRevenueUSD": 0.0,
    "adultTicketPrice": 8.5
  },
  {
    "state": "IL",
    "city": "Warrenville",
    "zip": "60555",
    "theater_name": "Phoenix Theatres Cantera Warrenville 17 + PTX",
    "chainName": "Phoenix Theatres",
    "chainCode": "PHNX",
    "showtime_id": 515434749,
    "date": "2025-09-14+12:00",
    "format": "Standard",
    "language": "Telugu",
    "totalSeatSold": 0,
    "occupancy": 0.0,
    "totalAvailableSeatCount": 43,
    "totalSeatCount": 43,
    "grossRevenueUSD": 0.0,
    "adultTicketPrice": 12.6
  },
  {
    "state": "IL",
    "city": "Warrenville",
    "zip": "60555",
    "theater_name": "Phoenix Theatres Cantera Warrenville 17 + PTX",
    "chainName": "Phoenix Theatres",
    "chainCode": "PHNX",
    "showtime_id": 515434750,
    "date": "2025-09-14+15:30",
    "format": "Standard",
    "language": "Telugu",
    "totalSeatSold": 0,
    "occupancy": 0.0,
    "totalAvailableSeatCount": 43,
    "totalSeatCount": 43,
    "grossRevenueUSD": 0.0,
    "adultTicketPrice": 12.6
  },
  {
    "state": "IL",
    "city": "Warrenville",
    "zip": "60555",
    "theater_name": "Phoenix Theatres Cantera Warrenville 17 + PTX",
    "chainName": "Phoenix Theatres",
    "chainCode": "PHNX",
    "showtime_id": 515434751,
    "date": "2025-09-14+18:40",
    "format": "Standard",
    "language": "Telugu",
    "totalSeatSold": 0,
    "occupancy": 0.0,
    "totalAvailableSeatCount": 43,
    "totalSeatCount": 43,
    "grossRevenueUSD": 0.0,
    "adultTicketPrice": 12.6
  },
  {
    "state": "IL",
    "city": "Warrenville",
    "zip": "60555",
    "theater_name": "Phoenix Theatres Cantera Warrenville 17 + PTX",
    "chainName": "Phoenix Theatres",
    "chainCode": "PHNX",
    "showtime_id": 515434752,
    "date": "2025-09-14+21:50",
    "format": "Standard",
    "language": "Telugu",
    "totalSeatSold": 0,
    "occupancy": 0.0,
    "totalAvailableSeatCount": 43,
    "totalSeatCount": 43,
    "grossRevenueUSD": 0.0,
    "adultTicketPrice": 12.6
  },
  {
    "state": "IL",
    "city": "Savoy",
    "zip": "61874",
    "theater_name": "Phoenix Theatres Savoy 16 + IMAX",
    "chainName": "Phoenix Theatres",
    "chainCode": "PHNX",
    "showtime_id": 515385331,
    "date": "2025-09-14+14:45",
    "format": "Standard",
    "language": "Telugu",
    "totalSeatSold": 4,
    "occupancy": 3.92,
    "totalAvailableSeatCount": 98,
    "totalSeatCount": 102,
    "grossRevenueUSD": 48.0,
    "adultTicketPrice": 12.0
  },
  {
    "state": "MO",
    "city": "Saint Peters",
    "zip": "63376",
    "theater_name": "Marcus Mid Rivers Cinema",
    "chainName": "Marcus Theatres",
    "chainCode": "MRCS",
    "showtime_id": 515301426,
    "date": "2025-09-14+17:50",
    "format": "Standard",
    "language": "Telugu",
    "totalSeatSold": 16,
    "occupancy": 26.23,
    "totalAvailableSeatCount": 45,
    "totalSeatCount": 61,
    "grossRevenueUSD": 235.36,
    "adultTicketPrice": 14.71
  },
  {
    "state": "MO",
    "city": "Saint Peters",
    "zip": "63376",
    "theater_name": "Marcus Mid Rivers Cinema",
    "chainName": "Marcus Theatres",
    "chainCode": "MRCS",
    "showtime_id": 515301425,
    "date": "2025-09-14+21:00",
    "format": "Standard",
    "language": "Telugu",
    "totalSeatSold": 4,
    "occupancy": 6.56,
    "totalAvailableSeatCount": 57,
    "totalSeatCount": 61,
    "grossRevenueUSD": 58.84,
    "adultTicketPrice": 14.71
  },
  {
    "state": "MO",
    "city": "Chesterfield",
    "zip": "63005",
    "theater_name": "Marcus Chesterfield Cinema",
    "chainName": "Marcus Theatres",
    "chainCode": "MRCS",
    "showtime_id": 515606137,
    "date": "2025-09-14+15:30",
    "format": "Standard",
    "language": "Telugu",
    "totalSeatSold": 19,
    "occupancy": 43.18,
    "totalAvailableSeatCount": 25,
    "totalSeatCount": 44,
    "grossRevenueUSD": 196.27,
    "adultTicketPrice": 10.33
  },
  {
    "state": "KS",
    "city": "Merriam",
    "zip": "66202",
    "theater_name": "Cinemark Merriam and XD",
    "chainName": "Cinemark Theatres",
    "chainCode": "CNMK",
    "showtime_id": 515951041,
    "date": "2025-09-14+21:00",
    "format": "Standard",
    "language": "Telugu",
    "totalSeatSold": 0,
    "occupancy": 0.0,
    "totalAvailableSeatCount": 124,
    "totalSeatCount": 124,
    "grossRevenueUSD": 0.0,
    "adultTicketPrice": 9.31
  },
  {
    "state": "NE",
    "city": "Omaha",
    "zip": "68118",
    "theater_name": "Marcus Village Pointe Cinema",
    "chainName": "Marcus Theatres",
    "chainCode": "MRCS",
    "showtime_id": 515439896,
    "date": "2025-09-14+21:00",
    "format": "Standard",
    "language": "Telugu",
    "totalSeatSold": 0,
    "occupancy": 0.0,
    "totalAvailableSeatCount": 79,
    "totalSeatCount": 79,
    "grossRevenueUSD": 0.0,
    "adultTicketPrice": 12.84
  },
  {
    "state": "AR",
    "city": "Little Rock",
    "zip": "72210",
    "theater_name": "Cinemark Colonel Glenn and XD",
    "chainName": "Cinemark Theatres",
    "chainCode": "CNMK",
    "showtime_id": 515607238,
    "date": "2025-09-14+21:30",
    "format": "Standard",
    "language": "Telugu",
    "totalSeatSold": 1,
    "occupancy": 1.25,
    "totalAvailableSeatCount": 79,
    "totalSeatCount": 80,
    "grossRevenueUSD": 12.76,
    "adultTicketPrice": 12.76
  },
  {
    "state": "TX",
    "city": "Plano",
    "zip": "75025",
    "theater_name": "Cinemark Legacy and XD",
    "chainName": "Cinemark Theatres",
    "chainCode": "CNMK",
    "showtime_id": 515656776,
    "date": "2025-09-14+12:30",
    "format": "Standard",
    "language": "Telugu",
    "totalSeatSold": 43,
    "occupancy": 44.33,
    "totalAvailableSeatCount": 54,
    "totalSeatCount": 97,
    "grossRevenueUSD": 488.91,
    "adultTicketPrice": 11.37
  },
  {
    "state": "TX",
    "city": "Plano",
    "zip": "75025",
    "theater_name": "Cinemark Legacy and XD",
    "chainName": "Cinemark Theatres",
    "chainCode": "CNMK",
    "showtime_id": 515938699,
    "date": "2025-09-14+12:40",
    "format": "Standard",
    "language": "Telugu",
    "totalSeatSold": 22,
    "occupancy": 27.85,
    "totalAvailableSeatCount": 57,
    "totalSeatCount": 79,
    "grossRevenueUSD": 250.14,
    "adultTicketPrice": 11.37
  },
  {
    "state": "TX",
    "city": "Plano",
    "zip": "75025",
    "theater_name": "Cinemark Legacy and XD",
    "chainName": "Cinemark Theatres",
    "chainCode": "CNMK",
    "showtime_id": 515656777,
    "date": "2025-09-14+16:20",
    "format": "Standard",
    "language": "Telugu",
    "totalSeatSold": 36,
    "occupancy": 67.92,
    "totalAvailableSeatCount": 17,
    "totalSeatCount": 53,
    "grossRevenueUSD": 496.8,
    "adultTicketPrice": 13.8
  },
  {
    "state": "TX",
    "city": "Plano",
    "zip": "75025",
    "theater_name": "Cinemark Legacy and XD",
    "chainName": "Cinemark Theatres",
    "chainCode": "CNMK",
    "showtime_id": 515656778,
    "date": "2025-09-14+18:40",
    "format": "Standard",
    "language": "Telugu",
    "totalSeatSold": 23,
    "occupancy": 38.33,
    "totalAvailableSeatCount": 37,
    "totalSeatCount": 60,
    "grossRevenueUSD": 317.4,
    "adultTicketPrice": 13.8
  },
  {
    "state": "TX",
    "city": "Plano",
    "zip": "75025",
    "theater_name": "Cinemark Legacy and XD",
    "chainName": "Cinemark Theatres",
    "chainCode": "CNMK",
    "showtime_id": 515916007,
    "date": "2025-09-14+20:00",
    "format": "Standard",
    "language": "Telugu",
    "totalSeatSold": 7,
    "occupancy": 10.29,
    "totalAvailableSeatCount": 61,
    "totalSeatCount": 68,
    "grossRevenueUSD": 96.6,
    "adultTicketPrice": 13.8
  },
  {
    "state": "TX",
    "city": "Plano",
    "zip": "75025",
    "theater_name": "Cinemark Legacy and XD",
    "chainName": "Cinemark Theatres",
    "chainCode": "CNMK",
    "showtime_id": 515656779,
    "date": "2025-09-14+22:30",
    "format": "Standard",
    "language": "Telugu",
    "totalSeatSold": 0,
    "occupancy": 0.0,
    "totalAvailableSeatCount": 97,
    "totalSeatCount": 97,
    "grossRevenueUSD": 0.0,
    "adultTicketPrice": 13.8
  },
  {
    "state": "TX",
    "city": "Plano",
    "zip": "75093",
    "theater_name": "Studio Movie Grill Plano",
    "chainName": "Studio Movie Grill",
    "chainCode": "SMG",
    "showtime_id": 515527994,
    "date": "2025-09-14+14:30",
    "format": "Standard",
    "language": "Telugu",
    "totalSeatSold": 6,
    "occupancy": 8.22,
    "totalAvailableSeatCount": 67,
    "totalSeatCount": 73,
    "grossRevenueUSD": 45.48,
    "adultTicketPrice": 7.58
  },
  {
    "state": "TX",
    "city": "Allen",
    "zip": "75013",
    "theater_name": "Cinemark Allen 16 and XD",
    "chainName": "Cinemark Theatres",
    "chainCode": "CNMK",
    "showtime_id": 515729415,
    "date": "2025-09-14+23:00",
    "format": "Standard",
    "language": "Telugu",
    "totalSeatSold": 0,
    "occupancy": 0.0,
    "totalAvailableSeatCount": 75,
    "totalSeatCount": 75,
    "grossRevenueUSD": 0.0,
    "adultTicketPrice": 13.53
  },
  {
    "state": "TX",
    "city": "Plano",
    "zip": "75093",
    "theater_name": "Cinemark West Plano and XD",
    "chainName": "Cinemark Theatres",
    "chainCode": "CNMK",
    "showtime_id": 515597514,
    "date": "2025-09-14+20:35",
    "format": "Standard",
    "language": "Telugu",
    "totalSeatSold": 6,
    "occupancy": 8.11,
    "totalAvailableSeatCount": 68,
    "totalSeatCount": 74,
    "grossRevenueUSD": 84.42,
    "adultTicketPrice": 14.07
  },
  {
    "state": "TX",
    "city": "Plano",
    "zip": "75093",
    "theater_name": "Cinemark West Plano and XD",
    "chainName": "Cinemark Theatres",
    "chainCode": "CNMK",
    "showtime_id": 515597515,
    "date": "2025-09-14+23:30",
    "format": "Standard",
    "language": "Telugu",
    "totalSeatSold": 0,
    "occupancy": 0.0,
    "totalAvailableSeatCount": 74,
    "totalSeatCount": 74,
    "grossRevenueUSD": 0.0,
    "adultTicketPrice": 14.07
  },
  {
    "state": "TX",
    "city": "The Colony",
    "zip": "75056",
    "theater_name": "Galaxy Grandscape",
    "chainName": "Galaxy Theatres",
    "chainCode": "GLXY",
    "showtime_id": 515471744,
    "date": "2025-09-14+18:00",
    "format": "Standard",
    "language": "Telugu",
    "totalSeatSold": 17,
    "occupancy": 25.37,
    "totalAvailableSeatCount": 50,
    "totalSeatCount": 67,
    "grossRevenueUSD": 229.5,
    "adultTicketPrice": 13.5
  },
  {
    "state": "TX",
    "city": "The Colony",
    "zip": "75056",
    "theater_name": "Galaxy Grandscape",
    "chainName": "Galaxy Theatres",
    "chainCode": "GLXY",
    "showtime_id": 515471745,
    "date": "2025-09-14+21:15",
    "format": "Standard",
    "language": "Telugu",
    "totalSeatSold": 0,
    "occupancy": 0.0,
    "totalAvailableSeatCount": 67,
    "totalSeatCount": 67,
    "grossRevenueUSD": 0.0,
    "adultTicketPrice": 13.5
  },
  {
    "state": "TX",
    "city": "Frisco",
    "zip": "75033",
    "theater_name": "CUT! by Cinemark Frisco - Dine-in Theatre, Kitchen",
    "chainName": "Cinemark Theatres",
    "chainCode": "CNMK",
    "showtime_id": 515562635,
    "date": "2025-09-14+18:00",
    "format": "Standard",
    "language": "Telugu",
    "totalSeatSold": 48,
    "occupancy": 56.47,
    "totalAvailableSeatCount": 37,
    "totalSeatCount": 85,
    "grossRevenueUSD": 675.36,
    "adultTicketPrice": 14.07
  },
  {
    "state": "TX",
    "city": "Frisco",
    "zip": "75033",
    "theater_name": "CUT! by Cinemark Frisco - Dine-in Theatre, Kitchen",
    "chainName": "Cinemark Theatres",
    "chainCode": "CNMK",
    "showtime_id": 515929062,
    "date": "2025-09-14+18:45",
    "format": "Standard",
    "language": "Telugu",
    "totalSeatSold": 44,
    "occupancy": 45.36,
    "totalAvailableSeatCount": 53,
    "totalSeatCount": 97,
    "grossRevenueUSD": 619.08,
    "adultTicketPrice": 14.07
  },
  {
    "state": "TX",
    "city": "Frisco",
    "zip": "75033",
    "theater_name": "CUT! by Cinemark Frisco - Dine-in Theatre, Kitchen",
    "chainName": "Cinemark Theatres",
    "chainCode": "CNMK",
    "showtime_id": 515940724,
    "date": "2025-09-14+19:30",
    "format": "Standard",
    "language": "Telugu",
    "totalSeatSold": 28,
    "occupancy": 46.67,
    "totalAvailableSeatCount": 32,
    "totalSeatCount": 60,
    "grossRevenueUSD": 393.96,
    "adultTicketPrice": 14.07
  },
  {
    "state": "TX",
    "city": "Dallas",
    "zip": "75243",
    "theater_name": "Studio Movie Grill Spring Valley",
    "chainName": "Studio Movie Grill",
    "chainCode": "SMG",
    "showtime_id": 515335376,
    "date": "2025-09-14+14:45",
    "format": "Standard",
    "language": "Telugu",
    "totalSeatSold": 2,
    "occupancy": 3.33,
    "totalAvailableSeatCount": 58,
    "totalSeatCount": 60,
    "grossRevenueUSD": 15.16,
    "adultTicketPrice": 7.58
  },
  {
    "state": "TX",
    "city": "Dallas",
    "zip": "75243",
    "theater_name": "Studio Movie Grill Spring Valley",
    "chainName": "Studio Movie Grill",
    "chainCode": "SMG",
    "showtime_id": 515335374,
    "date": "2025-09-14+21:45",
    "format": "Standard",
    "language": "Telugu",
    "totalSeatSold": 0,
    "occupancy": 0.0,
    "totalAvailableSeatCount": 60,
    "totalSeatCount": 60,
    "grossRevenueUSD": 0.0,
    "adultTicketPrice": 10.83
  },
  {
    "state": "TX",
    "city": "Lewisville",
    "zip": "75067",
    "theater_name": "Cinemark Lewisville and XD",
    "chainName": "Cinemark Theatres",
    "chainCode": "CNMK",
    "showtime_id": 515943644,
    "date": "2025-09-14+09:20",
    "format": "Standard",
    "language": "Telugu",
    "totalSeatSold": 0,
    "occupancy": 0.0,
    "totalAvailableSeatCount": 79,
    "totalSeatCount": 79,
    "grossRevenueUSD": 0.0,
    "adultTicketPrice": 7.58
  },
  {
    "state": "TX",
    "city": "Lewisville",
    "zip": "75067",
    "theater_name": "Cinemark Lewisville and XD",
    "chainName": "Cinemark Theatres",
    "chainCode": "CNMK",
    "showtime_id": 515623890,
    "date": "2025-09-14+10:25",
    "format": "Standard",
    "language": "Telugu",
    "totalSeatSold": 27,
    "occupancy": 33.75,
    "totalAvailableSeatCount": 53,
    "totalSeatCount": 80,
    "grossRevenueUSD": 204.66,
    "adultTicketPrice": 7.58
  },
  {
    "state": "TX",
    "city": "Lewisville",
    "zip": "75067",
    "theater_name": "Cinemark Lewisville and XD",
    "chainName": "Cinemark Theatres",
    "chainCode": "CNMK",
    "showtime_id": 515623889,
    "date": "2025-09-14+13:25",
    "format": "Standard",
    "language": "Telugu",
    "totalSeatSold": 43,
    "occupancy": 53.75,
    "totalAvailableSeatCount": 37,
    "totalSeatCount": 80,
    "grossRevenueUSD": 325.94,
    "adultTicketPrice": 7.58
  },
  {
    "state": "TX",
    "city": "Lewisville",
    "zip": "75067",
    "theater_name": "Cinemark Lewisville and XD",
    "chainName": "Cinemark Theatres",
    "chainCode": "CNMK",
    "showtime_id": 515623888,
    "date": "2025-09-14+16:25",
    "format": "Standard",
    "language": "Telugu",
    "totalSeatSold": 44,
    "occupancy": 55.0,
    "totalAvailableSeatCount": 36,
    "totalSeatCount": 80,
    "grossRevenueUSD": 440.44,
    "adultTicketPrice": 10.01
  },
  {
    "state": "TX",
    "city": "Lewisville",
    "zip": "75067",
    "theater_name": "Cinemark Lewisville and XD",
    "chainName": "Cinemark Theatres",
    "chainCode": "CNMK",
    "showtime_id": 515623886,
    "date": "2025-09-14+19:35",
    "format": "Standard",
    "language": "Telugu",
    "totalSeatSold": 27,
    "occupancy": 33.75,
    "totalAvailableSeatCount": 53,
    "totalSeatCount": 80,
    "grossRevenueUSD": 270.27,
    "adultTicketPrice": 10.01
  },
  {
    "state": "TX",
    "city": "Lewisville",
    "zip": "75067",
    "theater_name": "Cinemark Lewisville and XD",
    "chainName": "Cinemark Theatres",
    "chainCode": "CNMK",
    "showtime_id": 515623887,
    "date": "2025-09-14+22:30",
    "format": "Standard",
    "language": "Telugu",
    "totalSeatSold": 2,
    "occupancy": 2.5,
    "totalAvailableSeatCount": 78,
    "totalSeatCount": 80,
    "grossRevenueUSD": 20.02,
    "adultTicketPrice": 10.01
  },
  {
    "state": "TX",
    "city": "Dallas",
    "zip": "75234",
    "theater_name": "Cinemark Dallas XD and IMAX",
    "chainName": "Cinemark Theatres",
    "chainCode": "CNMK",
    "showtime_id": 515437289,
    "date": "2025-09-14+17:35",
    "format": "Standard",
    "language": "Telugu",
    "totalSeatSold": 25,
    "occupancy": 35.71,
    "totalAvailableSeatCount": 45,
    "totalSeatCount": 70,
    "grossRevenueUSD": 351.75,
    "adultTicketPrice": 14.07
  },
  {
    "state": "TX",
    "city": "Dallas",
    "zip": "75234",
    "theater_name": "Cinemark Dallas XD and IMAX",
    "chainName": "Cinemark Theatres",
    "chainCode": "CNMK",
    "showtime_id": 515437290,
    "date": "2025-09-14+20:25",
    "format": "Standard",
    "language": "Telugu",
    "totalSeatSold": 11,
    "occupancy": 15.71,
    "totalAvailableSeatCount": 59,
    "totalSeatCount": 70,
    "grossRevenueUSD": 154.77,
    "adultTicketPrice": 14.07
  },
  {
    "state": "TX",
    "city": "Grapevine",
    "zip": "76051",
    "theater_name": "Cinemark Tinseltown Grapevine and XD",
    "chainName": "Cinemark Theatres",
    "chainCode": "CNMK",
    "showtime_id": 515702662,
    "date": "2025-09-14+23:25",
    "format": "Standard",
    "language": "Telugu",
    "totalSeatSold": 3,
    "occupancy": 5.26,
    "totalAvailableSeatCount": 54,
    "totalSeatCount": 57,
    "grossRevenueUSD": 32.49,
    "adultTicketPrice": 10.83
  },
  {
    "state": "TX",
    "city": "Denton",
    "zip": "76210",
    "theater_name": "Cinemark Denton 14",
    "chainName": "Cinemark Theatres",
    "chainCode": "CNMK",
    "showtime_id": 515744837,
    "date": "2025-09-14+19:35",
    "format": "Standard",
    "language": "Telugu",
    "totalSeatSold": 18,
    "occupancy": 39.13,
    "totalAvailableSeatCount": 28,
    "totalSeatCount": 46,
    "grossRevenueUSD": 209.52,
    "adultTicketPrice": 11.64
  },
  {
    "state": "TX",
    "city": "Denton",
    "zip": "76210",
    "theater_name": "Cinemark Denton 14",
    "chainName": "Cinemark Theatres",
    "chainCode": "CNMK",
    "showtime_id": 515744838,
    "date": "2025-09-14+22:25",
    "format": "Standard",
    "language": "Telugu",
    "totalSeatSold": 0,
    "occupancy": 0.0,
    "totalAvailableSeatCount": 95,
    "totalSeatCount": 95,
    "grossRevenueUSD": 0.0,
    "adultTicketPrice": 11.64
  },
  {
    "state": "TX",
    "city": "Pflugerville",
    "zip": "78660",
    "theater_name": "Cinemark Pflugerville 20 and XD",
    "chainName": "Cinemark Theatres",
    "chainCode": "CNMK",
    "showtime_id": 515656697,
    "date": "2025-09-14+09:30",
    "format": "Standard",
    "language": "Telugu",
    "totalSeatSold": 5,
    "occupancy": 3.82,
    "totalAvailableSeatCount": 126,
    "totalSeatCount": 131,
    "grossRevenueUSD": 59.55,
    "adultTicketPrice": 11.91
  },
  {
    "state": "TX",
    "city": "Pflugerville",
    "zip": "78660",
    "theater_name": "Cinemark Pflugerville 20 and XD",
    "chainName": "Cinemark Theatres",
    "chainCode": "CNMK",
    "showtime_id": 515656698,
    "date": "2025-09-14+12:25",
    "format": "Standard",
    "language": "Telugu",
    "totalSeatSold": 43,
    "occupancy": 32.82,
    "totalAvailableSeatCount": 88,
    "totalSeatCount": 131,
    "grossRevenueUSD": 512.13,
    "adultTicketPrice": 11.91
  },
  {
    "state": "TX",
    "city": "Pflugerville",
    "zip": "78660",
    "theater_name": "Cinemark Pflugerville 20 and XD",
    "chainName": "Cinemark Theatres",
    "chainCode": "CNMK",
    "showtime_id": 515656699,
    "date": "2025-09-14+15:20",
    "format": "Standard",
    "language": "Telugu",
    "totalSeatSold": 85,
    "occupancy": 64.89,
    "totalAvailableSeatCount": 46,
    "totalSeatCount": 131,
    "grossRevenueUSD": 1012.35,
    "adultTicketPrice": 11.91
  },
  {
    "state": "TX",
    "city": "Pflugerville",
    "zip": "78660",
    "theater_name": "Cinemark Pflugerville 20 and XD",
    "chainName": "Cinemark Theatres",
    "chainCode": "CNMK",
    "showtime_id": 515942012,
    "date": "2025-09-14+16:00",
    "format": "Standard",
    "language": "Telugu",
    "totalSeatSold": 67,
    "occupancy": 50.0,
    "totalAvailableSeatCount": 67,
    "totalSeatCount": 134,
    "grossRevenueUSD": 960.78,
    "adultTicketPrice": 14.34
  },
  {
    "state": "TX",
    "city": "Houston",
    "zip": "77040",
    "theater_name": "Cinemark Tinseltown Houston 290 and XD",
    "chainName": "Cinemark Theatres",
    "chainCode": "CNMK",
    "showtime_id": 515642627,
    "date": "2025-09-14+09:40",
    "format": "Standard",
    "language": "Telugu",
    "totalSeatSold": 2,
    "occupancy": 2.04,
    "totalAvailableSeatCount": 96,
    "totalSeatCount": 98,
    "grossRevenueUSD": 16.78,
    "adultTicketPrice": 8.39
  },
  {
    "state": "TX",
    "city": "Houston",
    "zip": "77040",
    "theater_name": "Cinemark Tinseltown Houston 290 and XD",
    "chainName": "Cinemark Theatres",
    "chainCode": "CNMK",
    "showtime_id": 515642626,
    "date": "2025-09-14+12:45",
    "format": "Standard",
    "language": "Telugu",
    "totalSeatSold": 0,
    "occupancy": 0.0,
    "totalAvailableSeatCount": 98,
    "totalSeatCount": 98,
    "grossRevenueUSD": 0.0,
    "adultTicketPrice": 8.39
  },
  {
    "state": "TX",
    "city": "Houston",
    "zip": "77040",
    "theater_name": "Cinemark Tinseltown Houston 290 and XD",
    "chainName": "Cinemark Theatres",
    "chainCode": "CNMK",
    "showtime_id": 515642624,
    "date": "2025-09-14+15:50",
    "format": "Standard",
    "language": "Telugu",
    "totalSeatSold": 22,
    "occupancy": 22.45,
    "totalAvailableSeatCount": 76,
    "totalSeatCount": 98,
    "grossRevenueUSD": 184.58,
    "adultTicketPrice": 8.39
  },
  {
    "state": "TX",
    "city": "Houston",
    "zip": "77040",
    "theater_name": "Cinemark Tinseltown Houston 290 and XD",
    "chainName": "Cinemark Theatres",
    "chainCode": "CNMK",
    "showtime_id": 515642625,
    "date": "2025-09-14+19:10",
    "format": "Standard",
    "language": "Telugu",
    "totalSeatSold": 0,
    "occupancy": 0.0,
    "totalAvailableSeatCount": 98,
    "totalSeatCount": 98,
    "grossRevenueUSD": 0.0,
    "adultTicketPrice": 10.28
  },
  {
    "state": "TX",
    "city": "San Antonio",
    "zip": "78229",
    "theater_name": "Cinemark Movies 16",
    "chainName": "Cinemark Theatres",
    "chainCode": "CNMK",
    "showtime_id": 515676021,
    "date": "2025-09-14+12:50",
    "format": "Standard",
    "language": "Telugu",
    "totalSeatSold": 25,
    "occupancy": 36.76,
    "totalAvailableSeatCount": 43,
    "totalSeatCount": 68,
    "grossRevenueUSD": 189.5,
    "adultTicketPrice": 7.58
  },
  {
    "state": "TX",
    "city": "San Antonio",
    "zip": "78229",
    "theater_name": "Cinemark Movies 16",
    "chainName": "Cinemark Theatres",
    "chainCode": "CNMK",
    "showtime_id": 515676022,
    "date": "2025-09-14+15:55",
    "format": "Standard",
    "language": "Telugu",
    "totalSeatSold": 28,
    "occupancy": 41.18,
    "totalAvailableSeatCount": 40,
    "totalSeatCount": 68,
    "grossRevenueUSD": 212.24,
    "adultTicketPrice": 7.58
  },
  {
    "state": "TX",
    "city": "San Antonio",
    "zip": "78229",
    "theater_name": "Cinemark Movies 16",
    "chainName": "Cinemark Theatres",
    "chainCode": "CNMK",
    "showtime_id": 515676023,
    "date": "2025-09-14+19:00",
    "format": "Standard",
    "language": "Telugu",
    "totalSeatSold": 0,
    "occupancy": 0.0,
    "totalAvailableSeatCount": 68,
    "totalSeatCount": 68,
    "grossRevenueUSD": 0.0,
    "adultTicketPrice": 10.28
  },
  {
    "state": "TX",
    "city": "San Antonio",
    "zip": "78229",
    "theater_name": "Cinemark Movies 16",
    "chainName": "Cinemark Theatres",
    "chainCode": "CNMK",
    "showtime_id": 515676024,
    "date": "2025-09-14+22:05",
    "format": "Standard",
    "language": "Telugu",
    "totalSeatSold": 0,
    "occupancy": 0.0,
    "totalAvailableSeatCount": 68,
    "totalSeatCount": 68,
    "grossRevenueUSD": 0.0,
    "adultTicketPrice": 10.28
  },
  {
    "state": "CO",
    "city": "Aurora",
    "zip": "80012",
    "theater_name": "Cinemark Century Aurora and XD",
    "chainName": "Cinemark Theatres",
    "chainCode": "CNMK",
    "showtime_id": 515787487,
    "date": "2025-09-14+22:00",
    "format": "Standard",
    "language": "Telugu",
    "totalSeatSold": 32,
    "occupancy": 53.33,
    "totalAvailableSeatCount": 28,
    "totalSeatCount": 60,
    "grossRevenueUSD": 315.52,
    "adultTicketPrice": 9.86
  },
  {
    "state": "CO",
    "city": "Denver",
    "zip": "80238",
    "theater_name": "Harkins Northfield 18",
    "chainName": "Harkins Theatres",
    "chainCode": "HRKN",
    "showtime_id": 515821131,
    "date": "2025-09-14+21:15",
    "format": "Standard",
    "language": "Telugu",
    "totalSeatSold": 4,
    "occupancy": 5.88,
    "totalAvailableSeatCount": 64,
    "totalSeatCount": 68,
    "grossRevenueUSD": 59.0,
    "adultTicketPrice": 14.75
  },
  {
    "state": "UT",
    "city": "West Jordan",
    "zip": "84084",
    "theater_name": "Cinemark Jordan Landing 24 and XD",
    "chainName": "Cinemark Theatres",
    "chainCode": "CNMK",
    "showtime_id": 515749630,
    "date": "2025-09-14+09:40",
    "format": "Standard",
    "language": "Telugu",
    "totalSeatSold": 0,
    "occupancy": 0.0,
    "totalAvailableSeatCount": 63,
    "totalSeatCount": 63,
    "grossRevenueUSD": 0.0,
    "adultTicketPrice": 10.21
  },
  {
    "state": "UT",
    "city": "West Jordan",
    "zip": "84084",
    "theater_name": "Cinemark Jordan Landing 24 and XD",
    "chainName": "Cinemark Theatres",
    "chainCode": "CNMK",
    "showtime_id": 515749631,
    "date": "2025-09-14+12:45",
    "format": "Standard",
    "language": "Telugu",
    "totalSeatSold": 2,
    "occupancy": 3.17,
    "totalAvailableSeatCount": 61,
    "totalSeatCount": 63,
    "grossRevenueUSD": 20.42,
    "adultTicketPrice": 10.21
  },
  {
    "state": "UT",
    "city": "West Jordan",
    "zip": "84084",
    "theater_name": "Cinemark Jordan Landing 24 and XD",
    "chainName": "Cinemark Theatres",
    "chainCode": "CNMK",
    "showtime_id": 515749632,
    "date": "2025-09-14+19:35",
    "format": "Standard",
    "language": "Telugu",
    "totalSeatSold": 2,
    "occupancy": 3.17,
    "totalAvailableSeatCount": 61,
    "totalSeatCount": 63,
    "grossRevenueUSD": 25.26,
    "adultTicketPrice": 12.63
  },
  {
    "state": "AZ",
    "city": "Avondale",
    "zip": "85392",
    "theater_name": "Harkins Gateway Pavilions 18",
    "chainName": "Harkins Theatres",
    "chainCode": "HRKN",
    "showtime_id": 515764102,
    "date": "2025-09-14+20:20",
    "format": "Standard",
    "language": "Telugu",
    "totalSeatSold": 4,
    "occupancy": 1.9,
    "totalAvailableSeatCount": 207,
    "totalSeatCount": 211,
    "grossRevenueUSD": 49.0,
    "adultTicketPrice": 12.25
  },
  {
    "state": "AZ",
    "city": "Mesa",
    "zip": "85201",
    "theater_name": "Cinemark Mesa 16",
    "chainName": "Cinemark Theatres",
    "chainCode": "CNMK",
    "showtime_id": 515580470,
    "date": "2025-09-14+09:30",
    "format": "Standard",
    "language": "Telugu",
    "totalSeatSold": 37,
    "occupancy": 52.11,
    "totalAvailableSeatCount": 34,
    "totalSeatCount": 71,
    "grossRevenueUSD": 340.77,
    "adultTicketPrice": 9.21
  },
  {
    "state": "AZ",
    "city": "Mesa",
    "zip": "85201",
    "theater_name": "Cinemark Mesa 16",
    "chainName": "Cinemark Theatres",
    "chainCode": "CNMK",
    "showtime_id": 515580471,
    "date": "2025-09-14+15:55",
    "format": "Standard",
    "language": "Telugu",
    "totalSeatSold": 50,
    "occupancy": 70.42,
    "totalAvailableSeatCount": 21,
    "totalSeatCount": 71,
    "grossRevenueUSD": 460.5,
    "adultTicketPrice": 9.21
  },
  {
    "state": "AZ",
    "city": "Mesa",
    "zip": "85201",
    "theater_name": "Cinemark Mesa 16",
    "chainName": "Cinemark Theatres",
    "chainCode": "CNMK",
    "showtime_id": 515891005,
    "date": "2025-09-14+16:05",
    "format": "Standard",
    "language": "Telugu",
    "totalSeatSold": 33,
    "occupancy": 60.0,
    "totalAvailableSeatCount": 22,
    "totalSeatCount": 55,
    "grossRevenueUSD": 384.12,
    "adultTicketPrice": 11.64
  },
  {
    "state": "CA",
    "city": "Los Angeles",
    "zip": "90045",
    "theater_name": "Cinemark Howard Hughes Los Angeles and XD",
    "chainName": "Cinemark Theatres",
    "chainCode": "CNMK",
    "showtime_id": 515801352,
    "date": "2025-09-14+22:55",
    "format": "Standard",
    "language": "Telugu",
    "totalSeatSold": 3,
    "occupancy": 2.38,
    "totalAvailableSeatCount": 123,
    "totalSeatCount": 126,
    "grossRevenueUSD": 39.0,
    "adultTicketPrice": 13.0
  },
  {
    "state": "CA",
    "city": "Orange",
    "zip": "92867",
    "theater_name": "Cinemark Century Orange and XD",
    "chainName": "Cinemark Theatres",
    "chainCode": "CNMK",
    "showtime_id": 515678135,
    "date": "2025-09-14+17:00",
    "format": "Standard",
    "language": "Telugu",
    "totalSeatSold": 20,
    "occupancy": 34.48,
    "totalAvailableSeatCount": 38,
    "totalSeatCount": 58,
    "grossRevenueUSD": 245.0,
    "adultTicketPrice": 12.25
  },
  {
    "state": "CA",
    "city": "Orange",
    "zip": "92867",
    "theater_name": "Cinemark Century Orange and XD",
    "chainName": "Cinemark Theatres",
    "chainCode": "CNMK",
    "showtime_id": 515678136,
    "date": "2025-09-14+20:05",
    "format": "Standard",
    "language": "Telugu",
    "totalSeatSold": 2,
    "occupancy": 3.45,
    "totalAvailableSeatCount": 56,
    "totalSeatCount": 58,
    "grossRevenueUSD": 24.5,
    "adultTicketPrice": 12.25
  },
  {
    "state": "CA",
    "city": "Milpitas",
    "zip": "95035",
    "theater_name": "Cinemark Century Great Mall 20 XD and ScreenX",
    "chainName": "Cinemark Theatres",
    "chainCode": "CNMK",
    "showtime_id": 515467878,
    "date": "2025-09-14+13:35",
    "format": "Standard",
    "language": "Telugu",
    "totalSeatSold": 28,
    "occupancy": 62.22,
    "totalAvailableSeatCount": 17,
    "totalSeatCount": 45,
    "grossRevenueUSD": 343.0,
    "adultTicketPrice": 12.25
  },
  {
    "state": "CA",
    "city": "Milpitas",
    "zip": "95035",
    "theater_name": "Cinemark Century Great Mall 20 XD and ScreenX",
    "chainName": "Cinemark Theatres",
    "chainCode": "CNMK",
    "showtime_id": 515467879,
    "date": "2025-09-14+22:20",
    "format": "Standard",
    "language": "Telugu",
    "totalSeatSold": 0,
    "occupancy": 0.0,
    "totalAvailableSeatCount": 45,
    "totalSeatCount": 45,
    "grossRevenueUSD": 0.0,
    "adultTicketPrice": 15.5
  },
  {
    "state": "CA",
    "city": "Fremont",
    "zip": "94538",
    "theater_name": "Cin\u00e9 Lounge Fremont 7",
    "chainName": "RTSIND",
    "chainCode": "RTSIND",
    "showtime_id": 515871996,
    "date": "2025-09-14+13:30",
    "format": "Standard",
    "language": "Telugu",
    "totalSeatSold": 15,
    "occupancy": 28.85,
    "totalAvailableSeatCount": 37,
    "totalSeatCount": 52,
    "grossRevenueUSD": 202.5,
    "adultTicketPrice": 13.5
  },
  {
    "state": "CA",
    "city": "Fremont",
    "zip": "94538",
    "theater_name": "Cin\u00e9 Lounge Fremont 7",
    "chainName": "RTSIND",
    "chainCode": "RTSIND",
    "showtime_id": 515871997,
    "date": "2025-09-14+20:00",
    "format": "Standard",
    "language": "Telugu",
    "totalSeatSold": 2,
    "occupancy": 4.08,
    "totalAvailableSeatCount": 47,
    "totalSeatCount": 49,
    "grossRevenueUSD": 29.0,
    "adultTicketPrice": 14.5
  },
  {
    "state": "CA",
    "city": "Fremont",
    "zip": "94538",
    "theater_name": "Cin\u00e9 Lounge Fremont 7",
    "chainName": "RTSIND",
    "chainCode": "RTSIND",
    "showtime_id": 515936316,
    "date": "2025-09-14+21:30",
    "format": "Standard",
    "language": "Telugu",
    "totalSeatSold": 0,
    "occupancy": 0.0,
    "totalAvailableSeatCount": 78,
    "totalSeatCount": 78,
    "grossRevenueUSD": 0.0,
    "adultTicketPrice": 14.5
  },
  {
    "state": "CA",
    "city": "Union City",
    "zip": "94587",
    "theater_name": "Cinemark Century Union Landing 25 and XD",
    "chainName": "Cinemark Theatres",
    "chainCode": "CNMK",
    "showtime_id": 515414889,
    "date": "2025-09-14+13:15",
    "format": "Standard",
    "language": "Telugu",
    "totalSeatSold": 29,
    "occupancy": 25.22,
    "totalAvailableSeatCount": 86,
    "totalSeatCount": 115,
    "grossRevenueUSD": 362.5,
    "adultTicketPrice": 12.5
  },
  {
    "state": "CA",
    "city": "Union City",
    "zip": "94587",
    "theater_name": "Cinemark Century Union Landing 25 and XD",
    "chainName": "Cinemark Theatres",
    "chainCode": "CNMK",
    "showtime_id": 515414890,
    "date": "2025-09-14+19:40",
    "format": "Standard",
    "language": "Telugu",
    "totalSeatSold": 11,
    "occupancy": 9.57,
    "totalAvailableSeatCount": 104,
    "totalSeatCount": 115,
    "grossRevenueUSD": 167.75,
    "adultTicketPrice": 15.25
  },
  {
    "state": "CA",
    "city": "Dublin",
    "zip": "94568",
    "theater_name": "Regal Hacienda Crossings ScreenX, IMAX & RPX",
    "chainName": "Regal",
    "chainCode": "REGL",
    "showtime_id": 515915043,
    "date": "2025-09-14+10:20",
    "format": "Standard",
    "language": "Telugu",
    "totalSeatSold": 4,
    "occupancy": 2.21,
    "totalAvailableSeatCount": 177,
    "totalSeatCount": 181,
    "grossRevenueUSD": 55.96,
    "adultTicketPrice": 13.99
  },
  {
    "state": "CA",
    "city": "Dublin",
    "zip": "94568",
    "theater_name": "Regal Hacienda Crossings ScreenX, IMAX & RPX",
    "chainName": "Regal",
    "chainCode": "REGL",
    "showtime_id": 515791146,
    "date": "2025-09-14+13:45",
    "format": "Standard",
    "language": "Telugu",
    "totalSeatSold": 42,
    "occupancy": 23.2,
    "totalAvailableSeatCount": 139,
    "totalSeatCount": 181,
    "grossRevenueUSD": 587.58,
    "adultTicketPrice": 13.99
  },
  {
    "state": "CA",
    "city": "Dublin",
    "zip": "94568",
    "theater_name": "Regal Hacienda Crossings ScreenX, IMAX & RPX",
    "chainName": "Regal",
    "chainCode": "REGL",
    "showtime_id": 515791142,
    "date": "2025-09-14+17:00",
    "format": "Standard",
    "language": "Telugu",
    "totalSeatSold": 34,
    "occupancy": 18.78,
    "totalAvailableSeatCount": 147,
    "totalSeatCount": 181,
    "grossRevenueUSD": 611.66,
    "adultTicketPrice": 17.99
  },
  {
    "state": "CA",
    "city": "Dublin",
    "zip": "94568",
    "theater_name": "Regal Hacienda Crossings ScreenX, IMAX & RPX",
    "chainName": "Regal",
    "chainCode": "REGL",
    "showtime_id": 515791145,
    "date": "2025-09-14+20:30",
    "format": "Standard",
    "language": "Telugu",
    "totalSeatSold": 0,
    "occupancy": 0.0,
    "totalAvailableSeatCount": 181,
    "totalSeatCount": 181,
    "grossRevenueUSD": 0.0,
    "adultTicketPrice": 17.99
  },
  {
    "state": "CA",
    "city": "San Francisco",
    "zip": "94109",
    "theater_name": "Apple Cinemas Van Ness",
    "chainName": "Apple Cinemas",
    "chainCode": "APPL",
    "showtime_id": 515693954,
    "date": "2025-09-14+11:00",
    "format": "Standard",
    "language": "Telugu",
    "totalSeatSold": 14,
    "occupancy": 17.95,
    "totalAvailableSeatCount": 64,
    "totalSeatCount": 78,
    "grossRevenueUSD": 182.0,
    "adultTicketPrice": 13.0
  },
  {
    "state": "CA",
    "city": "Folsom",
    "zip": "95630",
    "theater_name": "Cinemark Century Folsom 14",
    "chainName": "Cinemark Theatres",
    "chainCode": "CNMK",
    "showtime_id": 515758377,
    "date": "2025-09-14+10:20",
    "format": "Standard",
    "language": "Telugu",
    "totalSeatSold": 0,
    "occupancy": 0.0,
    "totalAvailableSeatCount": 113,
    "totalSeatCount": 113,
    "grossRevenueUSD": 0.0,
    "adultTicketPrice": 7.75
  },
  {
    "state": "CA",
    "city": "Folsom",
    "zip": "95630",
    "theater_name": "Cinemark Century Folsom 14",
    "chainName": "Cinemark Theatres",
    "chainCode": "CNMK",
    "showtime_id": 515758378,
    "date": "2025-09-14+16:45",
    "format": "Standard",
    "language": "Telugu",
    "totalSeatSold": 5,
    "occupancy": 4.42,
    "totalAvailableSeatCount": 108,
    "totalSeatCount": 113,
    "grossRevenueUSD": 45.0,
    "adultTicketPrice": 9.0
  },
  {
    "state": "OR",
    "city": "Beaverton",
    "zip": "97005",
    "theater_name": "Cinemark Cedar Hills 16",
    "chainName": "Cinemark Theatres",
    "chainCode": "CNMK",
    "showtime_id": 515581467,
    "date": "2025-09-14+21:30",
    "format": "Standard",
    "language": "Telugu",
    "totalSeatSold": 26,
    "occupancy": 45.61,
    "totalAvailableSeatCount": 31,
    "totalSeatCount": 57,
    "grossRevenueUSD": 344.5,
    "adultTicketPrice": 13.25
  },
  {
    "state": "WA",
    "city": "Bellevue",
    "zip": "98004",
    "theater_name": "Cinemark Lincoln Square",
    "chainName": "Cinemark Theatres",
    "chainCode": "CNMK",
    "showtime_id": 515396931,
    "date": "2025-09-14+13:05",
    "format": "Standard",
    "language": "Telugu",
    "totalSeatSold": 32,
    "occupancy": 8.7,
    "totalAvailableSeatCount": 336,
    "totalSeatCount": 368,
    "grossRevenueUSD": 403.84,
    "adultTicketPrice": 12.62
  },
  {
    "state": "WA",
    "city": "Bellevue",
    "zip": "98004",
    "theater_name": "Cinemark Lincoln Square",
    "chainName": "Cinemark Theatres",
    "chainCode": "CNMK",
    "showtime_id": 515396928,
    "date": "2025-09-14+16:00",
    "format": "Standard",
    "language": "Telugu",
    "totalSeatSold": 30,
    "occupancy": 8.15,
    "totalAvailableSeatCount": 338,
    "totalSeatCount": 368,
    "grossRevenueUSD": 463.5,
    "adultTicketPrice": 15.45
  },
  {
    "state": "WA",
    "city": "Bellevue",
    "zip": "98004",
    "theater_name": "Cinemark Lincoln Square",
    "chainName": "Cinemark Theatres",
    "chainCode": "CNMK",
    "showtime_id": 515396929,
    "date": "2025-09-14+19:20",
    "format": "Standard",
    "language": "Telugu",
    "totalSeatSold": 8,
    "occupancy": 6.25,
    "totalAvailableSeatCount": 120,
    "totalSeatCount": 128,
    "grossRevenueUSD": 123.6,
    "adultTicketPrice": 15.45
  },
  {
    "state": "WA",
    "city": "Bellevue",
    "zip": "98004",
    "theater_name": "Cinemark Lincoln Square",
    "chainName": "Cinemark Theatres",
    "chainCode": "CNMK",
    "showtime_id": 515396930,
    "date": "2025-09-14+22:30",
    "format": "Standard",
    "language": "Telugu",
    "totalSeatSold": 0,
    "occupancy": 0.0,
    "totalAvailableSeatCount": 368,
    "totalSeatCount": 368,
    "grossRevenueUSD": 0.0,
    "adultTicketPrice": 15.45
  },
  {
    "state": "WA",
    "city": "Seattle",
    "zip": "98101",
    "theater_name": "Regal Meridian & 4DX",
    "chainName": "Regal",
    "chainCode": "REGL",
    "showtime_id": 515706791,
    "date": "2025-09-14+16:10",
    "format": "Standard",
    "language": "Telugu",
    "totalSeatSold": 26,
    "occupancy": 55.32,
    "totalAvailableSeatCount": 21,
    "totalSeatCount": 47,
    "grossRevenueUSD": 477.36,
    "adultTicketPrice": 18.36
  },
  {
    "state": "WA",
    "city": "Seattle",
    "zip": "98101",
    "theater_name": "Regal Meridian & 4DX",
    "chainName": "Regal",
    "chainCode": "REGL",
    "showtime_id": 515706779,
    "date": "2025-09-14+22:05",
    "format": "Standard",
    "language": "Telugu",
    "totalSeatSold": 5,
    "occupancy": 10.0,
    "totalAvailableSeatCount": 45,
    "totalSeatCount": 50,
    "grossRevenueUSD": 91.8,
    "adultTicketPrice": 18.36
  },
  {
    "state": "WA",
    "city": "Monroe",
    "zip": "98272",
    "theater_name": "Galaxy Monroe",
    "chainName": "Galaxy Theatres",
    "chainCode": "GLXY",
    "showtime_id": 515426904,
    "date": "2025-09-14+20:30",
    "format": "Standard",
    "language": "Telugu",
    "error": {
      "status": 400
    }
  },
  {
    "state": "GA",
    "city": "Duluth",
    "zip": "30097",
    "theater_name": "Regal Medlock Crossing & RPX",
    "chainName": "Regal",
    "chainCode": "REGL",
    "showtime_id": 515952256,
    "date": "2025-09-14+12:05",
    "format": "Standard",
    "language": "Telugu",
    "totalSeatSold": 3,
    "occupancy": 3.16,
    "totalAvailableSeatCount": 92,
    "totalSeatCount": 95,
    "grossRevenueUSD": 43.62,
    "adultTicketPrice": 14.54
  },
  {
    "state": "GA",
    "city": "Duluth",
    "zip": "30097",
    "theater_name": "Regal Medlock Crossing & RPX",
    "chainName": "Regal",
    "chainCode": "REGL",
    "showtime_id": 515952257,
    "date": "2025-09-14+15:35",
    "format": "Standard",
    "language": "Telugu",
    "totalSeatSold": 69,
    "occupancy": 72.63,
    "totalAvailableSeatCount": 26,
    "totalSeatCount": 95,
    "grossRevenueUSD": 1003.26,
    "adultTicketPrice": 14.54
  },
  {
    "state": "GA",
    "city": "Duluth",
    "zip": "30097",
    "theater_name": "Regal Medlock Crossing & RPX",
    "chainName": "Regal",
    "chainCode": "REGL",
    "showtime_id": 515952254,
    "date": "2025-09-14+18:25",
    "format": "Standard",
    "language": "Telugu",
    "totalSeatSold": 123,
    "occupancy": 66.13,
    "totalAvailableSeatCount": 63,
    "totalSeatCount": 186,
    "grossRevenueUSD": 2252.13,
    "adultTicketPrice": 18.31
  },
  {
    "state": "GA",
    "city": "Duluth",
    "zip": "30097",
    "theater_name": "Regal Medlock Crossing & RPX",
    "chainName": "Regal",
    "chainCode": "REGL",
    "showtime_id": 515952255,
    "date": "2025-09-14+21:45",
    "format": "Standard",
    "language": "Telugu",
    "totalSeatSold": 24,
    "occupancy": 12.9,
    "totalAvailableSeatCount": 162,
    "totalSeatCount": 186,
    "grossRevenueUSD": 439.44,
    "adultTicketPrice": 18.31
  }
]