{
  "last_updated": "2025-09-20 12:02:31 AM",
  "errors": [
    {
      "state": "NY",
      "city": "Albany",
      "zip": "12203",
      "theater_name": "Regal Crossgates & IMAX",
      "chainName": "Regal",
      "chainCode": "REGL",
      "showtime_id": 516648552,
      "date": "2025-09-19+12:00",
      "format": "Standard",
      "language": "Telugu",
      "error": {
        "status": 403
      }
    },
    {
      "state": "MA",
      "city": "Bellingham",
      "zip": "02019",
      "theater_name": "Regal Bellingham",
      "chainName": "Regal",
      "chainCode": "REGL",
      "showtime_id": 516380891,
      "date": "2025-09-19+14:45",
      "format": "Standard",
      "language": "Telugu",
      "error": {
        "status": 403
      }
    },
    {
      "state": "NJ",
      "city": "South Plainfield",
      "zip": "07080",
      "theater_name": "Regal Hadley Theatre",
      "chainName": "Regal",
      "chainCode": "REGL",
      "showtime_id": 516455178,
      "date": "2025-09-19+12:50",
      "format": "Standard",
      "language": "Telugu",
      "error": {
        "status": 403
      }
    },
    {
      "state": "NJ",
      "city": "South Plainfield",
      "zip": "07080",
      "theater_name": "Regal Hadley Theatre",
      "chainName": "Regal",
      "chainCode": "REGL",
      "showtime_id": 516455173,
      "date": "2025-09-19+15:50",
      "format": "Standard",
      "language": "Telugu",
      "error": {
        "status": 403
      }
    },
    {
      "state": "NJ",
      "city": "North Brunswick",
      "zip": "08902",
      "theater_name": "Regal Commerce Center & RPX",
      "chainName": "Regal",
      "chainCode": "REGL",
      "showtime_id": 516389085,
      "date": "2025-09-19+12:00",
      "format": "Standard",
      "language": "Telugu",
      "error": {
        "status": 403
      }
    },
    {
      "state": "NJ",
      "city": "North Brunswick",
      "zip": "08902",
      "theater_name": "Regal Commerce Center & RPX",
      "chainName": "Regal",
      "chainCode": "REGL",
      "showtime_id": 516389094,
      "date": "2025-09-19+15:00",
      "format": "Standard",
      "language": "Telugu",
      "error": {
        "status": 403
      }
    },
    {
      "state": "NJ",
      "city": "North Brunswick",
      "zip": "08902",
      "theater_name": "Regal Commerce Center & RPX",
      "chainName": "Regal",
      "chainCode": "REGL",
      "showtime_id": 516389095,
      "date": "2025-09-19+18:30",
      "format": "Standard",
      "language": "Telugu",
      "error": {
        "status": 403
      }
    },
    {
      "state": "NJ",
      "city": "North Brunswick",
      "zip": "08902",
      "theater_name": "Regal Commerce Center & RPX",
      "chainName": "Regal",
      "chainCode": "REGL",
      "showtime_id": 516389096,
      "date": "2025-09-19+21:45",
      "format": "Standard",
      "language": "Telugu",
      "error": {
        "status": 403
      }
    },
    {
      "state": "NJ",
      "city": "Secaucus",
      "zip": "07094",
      "theater_name": "Regal Secaucus ShowPlace 14",
      "chainName": "Regal",
      "chainCode": "REGL",
      "showtime_id": 516367795,
      "date": "2025-09-19+14:00",
      "format": "Standard",
      "language": "Telugu",
      "error": {
        "status": 403
      }
    },
    {
      "state": "NJ",
      "city": "Secaucus",
      "zip": "07094",
      "theater_name": "Regal Secaucus ShowPlace 14",
      "chainName": "Regal",
      "chainCode": "REGL",
      "showtime_id": 516367796,
      "date": "2025-09-19+20:20",
      "format": "Standard",
      "language": "Telugu",
      "error": {
        "status": 403
      }
    },
    {
      "state": "NJ",
      "city": "Somerdale",
      "zip": "08083",
      "theater_name": "Cinemark Somerdale 16 and XD",
      "chainName": "Cinemark Theatres",
      "chainCode": "CNMK",
      "showtime_id": 516079127,
      "date": "2025-09-19+12:15",
      "format": "Standard",
      "language": "Telugu",
      "error": {
        "status": 403
      }
    },
    {
      "state": "NJ",
      "city": "Somerdale",
      "zip": "08083",
      "theater_name": "Cinemark Somerdale 16 and XD",
      "chainName": "Cinemark Theatres",
      "chainCode": "CNMK",
      "showtime_id": 516079128,
      "date": "2025-09-19+22:55",
      "format": "Standard",
      "language": "Telugu",
      "error": {
        "status": 403
      }
    },
    {
      "state": "DE",
      "city": "Wilmington",
      "zip": "19804",
      "theater_name": "Cinemark Wilmington Movies 10",
      "chainName": "Cinemark Theatres",
      "chainCode": "CNMK",
      "showtime_id": 516414312,
      "date": "2025-09-19+15:10",
      "format": "Standard",
      "language": "Telugu",
      "error": {
        "status": 403
      }
    },
    {
      "state": "DE",
      "city": "Wilmington",
      "zip": "19804",
      "theater_name": "Cinemark Wilmington Movies 10",
      "chainName": "Cinemark Theatres",
      "chainCode": "CNMK",
      "showtime_id": 516414311,
      "date": "2025-09-19+21:30",
      "format": "Standard",
      "language": "Telugu",
      "error": {
        "status": 403
      }
    },
    {
      "state": "DE",
      "city": "Newark",
      "zip": "19702",
      "theater_name": "Regal Peoples Plaza",
      "chainName": "Regal",
      "chainCode": "REGL",
      "showtime_id": 516292048,
      "date": "2025-09-19+15:10",
      "format": "Standard",
      "language": "Telugu",
      "error": {
        "status": 403
      }
    },
    {
      "state": "DE",
      "city": "Newark",
      "zip": "19702",
      "theater_name": "Regal Peoples Plaza",
      "chainName": "Regal",
      "chainCode": "REGL",
      "showtime_id": 516292049,
      "date": "2025-09-19+18:35",
      "format": "Standard",
      "language": "Telugu",
      "error": {
        "status": 403
      }
    },
    {
      "state": "DE",
      "city": "Newark",
      "zip": "19702",
      "theater_name": "Regal Peoples Plaza",
      "chainName": "Regal",
      "chainCode": "REGL",
      "showtime_id": 516292050,
      "date": "2025-09-19+22:00",
      "format": "Standard",
      "language": "Telugu",
      "error": {
        "status": 403
      }
    },
    {
      "state": "NY",
      "city": "Buffalo",
      "zip": "14207",
      "theater_name": "Regal Elmwood Center",
      "chainName": "Regal",
      "chainCode": "REGL",
      "showtime_id": 516452412,
      "date": "2025-09-19+17:50",
      "format": "Standard",
      "language": "Telugu",
      "error": {
        "status": 403
      }
    },
    {
      "state": "MD",
      "city": "Columbia",
      "zip": "21046",
      "theater_name": "Phoenix Theatres Columbia Snowden 14 + ScreenX",
      "chainName": "Phoenix Theatres",
      "chainCode": "PHNX",
      "showtime_id": 516530401,
      "date": "2025-09-19+15:00",
      "format": "Standard",
      "language": "Telugu",
      "error": {
        "status": 403
      }
    },
    {
      "state": "PA",
      "city": "Downingtown",
      "zip": "19335",
      "theater_name": "Regal Downingtown & IMAX",
      "chainName": "Regal",
      "chainCode": "REGL",
      "showtime_id": 516093917,
      "date": "2025-09-19+11:35",
      "format": "Standard",
      "language": "Telugu",
      "error": {
        "status": 403
      }
    },
    {
      "state": "PA",
      "city": "Downingtown",
      "zip": "19335",
      "theater_name": "Regal Downingtown & IMAX",
      "chainName": "Regal",
      "chainCode": "REGL",
      "showtime_id": 516093918,
      "date": "2025-09-19+14:50",
      "format": "Standard",
      "language": "Telugu",
      "error": {
        "status": 403
      }
    },
    {
      "state": "PA",
      "city": "Downingtown",
      "zip": "19335",
      "theater_name": "Regal Downingtown & IMAX",
      "chainName": "Regal",
      "chainCode": "REGL",
      "showtime_id": 516093919,
      "date": "2025-09-19+18:00",
      "format": "Standard",
      "language": "Telugu",
      "error": {
        "status": 403
      }
    },
    {
      "state": "PA",
      "city": "Downingtown",
      "zip": "19335",
      "theater_name": "Regal Downingtown & IMAX",
      "chainName": "Regal",
      "chainCode": "REGL",
      "showtime_id": 516093920,
      "date": "2025-09-19+21:10",
      "format": "Standard",
      "language": "Telugu",
      "error": {
        "status": 403
      }
    },
    {
      "state": "VA",
      "city": "Ashburn",
      "zip": "20148",
      "theater_name": "Regal Fox 4DX & IMAX",
      "chainName": "Regal",
      "chainCode": "REGL",
      "showtime_id": 516179785,
      "date": "2025-09-19+11:45",
      "format": "Standard",
      "language": "Telugu",
      "error": {
        "status": 403
      }
    },
    {
      "state": "VA",
      "city": "Ashburn",
      "zip": "20148",
      "theater_name": "Regal Fox 4DX & IMAX",
      "chainName": "Regal",
      "chainCode": "REGL",
      "showtime_id": 516179783,
      "date": "2025-09-19+18:35",
      "format": "Standard",
      "language": "Telugu",
      "error": {
        "status": 403
      }
    },
    {
      "state": "VA",
      "city": "Richmond",
      "zip": "23233",
      "theater_name": "Regal Short Pump",
      "chainName": "Regal",
      "chainCode": "REGL",
      "showtime_id": 516460178,
      "date": "2025-09-19+13:00",
      "format": "Standard",
      "language": "Telugu",
      "error": {
        "status": 403
      }
    },
    {
      "state": "NC",
      "city": "Morrisville",
      "zip": "27560",
      "theater_name": "B&B Theatres Morrisville Park West 14",
      "chainName": "B&B Theaters",
      "chainCode": "BNBT",
      "showtime_id": 516097761,
      "date": "2025-09-19+18:30",
      "format": "Standard",
      "language": "Telugu",
      "error": {
        "status": 403
      }
    },
    {
      "state": "NC",
      "city": "Morrisville",
      "zip": "27560",
      "theater_name": "B&B Theatres Morrisville Park West 14",
      "chainName": "B&B Theaters",
      "chainCode": "BNBT",
      "showtime_id": 516097764,
      "date": "2025-09-19+21:45",
      "format": "Standard",
      "language": "Telugu",
      "error": {
        "status": 403
      }
    },
    {
      "state": "NC",
      "city": "Cary",
      "zip": "27518",
      "theater_name": "Regal Crossroads & IMAX - Cary",
      "chainName": "Regal",
      "chainCode": "REGL",
      "showtime_id": 516213579,
      "date": "2025-09-19+13:15",
      "format": "Standard",
      "language": "Telugu",
      "error": {
        "status": 403
      }
    },
    {
      "state": "GA",
      "city": "Roswell",
      "zip": "30076",
      "theater_name": "Aurora Cineplex",
      "chainName": "RTSIND",
      "chainCode": "RTSIND",
      "showtime_id": 516621544,
      "date": "2025-09-19+13:45",
      "format": "Standard",
      "language": "Telugu",
      "error": {
        "status": 403
      }
    },
    {
      "state": "GA",
      "city": "Roswell",
      "zip": "30076",
      "theater_name": "Aurora Cineplex",
      "chainName": "RTSIND",
      "chainCode": "RTSIND",
      "showtime_id": 516621545,
      "date": "2025-09-19+16:30",
      "format": "Standard",
      "language": "Telugu",
      "error": {
        "status": 403
      }
    },
    {
      "state": "GA",
      "city": "Duluth",
      "zip": "30097",
      "theater_name": "Regal Medlock Crossing & RPX",
      "chainName": "Regal",
      "chainCode": "REGL",
      "showtime_id": 516586028,
      "date": "2025-09-19+18:10",
      "format": "Standard",
      "language": "Telugu",
      "error": {
        "status": 403
      }
    },
    {
      "state": "GA",
      "city": "Duluth",
      "zip": "30097",
      "theater_name": "Regal Medlock Crossing & RPX",
      "chainName": "Regal",
      "chainCode": "REGL",
      "showtime_id": 516586027,
      "date": "2025-09-19+21:35",
      "format": "Standard",
      "language": "Telugu",
      "error": {
        "status": 403
      }
    },
    {
      "state": "FL",
      "city": "Gainesville",
      "zip": "32607",
      "theater_name": "Regal Royal Park",
      "chainName": "Regal",
      "chainCode": "REGL",
      "showtime_id": 516359237,
      "date": "2025-09-19+17:50",
      "format": "Standard",
      "language": "Telugu",
      "error": {
        "status": 403
      }
    },
    {
      "state": "FL",
      "city": "Orlando",
      "zip": "32819",
      "theater_name": "Cinemark Orlando and XD",
      "chainName": "Cinemark Theatres",
      "chainCode": "CNMK",
      "showtime_id": 516387266,
      "date": "2025-09-19+15:20",
      "format": "Standard",
      "language": "Telugu",
      "error": {
        "status": 403
      }
    },
    {
      "state": "FL",
      "city": "Orlando",
      "zip": "32819",
      "theater_name": "Cinemark Orlando and XD",
      "chainName": "Cinemark Theatres",
      "chainCode": "CNMK",
      "showtime_id": 516662568,
      "date": "2025-09-19+22:05",
      "format": "Standard",
      "language": "Telugu",
      "error": {
        "status": 403
      }
    },
    {
      "state": "FL",
      "city": "Davie",
      "zip": "33331",
      "theater_name": "Cinemark Paradise 24 and XD",
      "chainName": "Cinemark Theatres",
      "chainCode": "CNMK",
      "showtime_id": 516585301,
      "date": "2025-09-19+11:05",
      "format": "Standard",
      "language": "Telugu",
      "error": {
        "status": 403
      }
    },
    {
      "state": "FL",
      "city": "Davie",
      "zip": "33331",
      "theater_name": "Cinemark Paradise 24 and XD",
      "chainName": "Cinemark Theatres",
      "chainCode": "CNMK",
      "showtime_id": 516585300,
      "date": "2025-09-19+17:45",
      "format": "Standard",
      "language": "Telugu",
      "error": {
        "status": 403
      }
    },
    {
      "state": "FL",
      "city": "Davie",
      "zip": "33331",
      "theater_name": "Cinemark Paradise 24 and XD",
      "chainName": "Cinemark Theatres",
      "chainCode": "CNMK",
      "showtime_id": 516585302,
      "date": "2025-09-19+21:45",
      "format": "Standard",
      "language": "Telugu",
      "error": {
        "status": 403
      }
    },
    {
      "state": "OH",
      "city": "Columbus",
      "zip": "43240",
      "theater_name": "Cinemark Polaris 18 and XD",
      "chainName": "Cinemark Theatres",
      "chainCode": "CNMK",
      "showtime_id": 516171923,
      "date": "2025-09-19+13:40",
      "format": "Standard",
      "language": "Telugu",
      "error": {
        "status": 403
      }
    },
    {
      "state": "OH",
      "city": "Columbus",
      "zip": "43240",
      "theater_name": "Cinemark Polaris 18 and XD",
      "chainName": "Cinemark Theatres",
      "chainCode": "CNMK",
      "showtime_id": 516171924,
      "date": "2025-09-19+16:45",
      "format": "Standard",
      "language": "Telugu",
      "error": {
        "status": 403
      }
    },
    {
      "state": "OH",
      "city": "Columbus",
      "zip": "43240",
      "theater_name": "Cinemark Polaris 18 and XD",
      "chainName": "Cinemark Theatres",
      "chainCode": "CNMK",
      "showtime_id": 516171925,
      "date": "2025-09-19+19:50",
      "format": "Standard",
      "language": "Telugu",
      "error": {
        "status": 403
      }
    },
    {
      "state": "OH",
      "city": "Columbus",
      "zip": "43240",
      "theater_name": "Cinemark Polaris 18 and XD",
      "chainName": "Cinemark Theatres",
      "chainCode": "CNMK",
      "showtime_id": 516171926,
      "date": "2025-09-19+22:55",
      "format": "Standard",
      "language": "Telugu",
      "error": {
        "status": 403
      }
    },
    {
      "state": "OH",
      "city": "Columbus",
      "zip": "43212",
      "theater_name": "Lennox Town Center 24",
      "chainName": "Phoenix Theatres",
      "chainCode": "PHNX",
      "showtime_id": 516343237,
      "date": "2025-09-19+11:00",
      "format": "Standard",
      "language": "Telugu",
      "error": {
        "status": 403
      }
    },
    {
      "state": "OH",
      "city": "Columbus",
      "zip": "43212",
      "theater_name": "Lennox Town Center 24",
      "chainName": "Phoenix Theatres",
      "chainCode": "PHNX",
      "showtime_id": 516343238,
      "date": "2025-09-19+14:30",
      "format": "Standard",
      "language": "Telugu",
      "error": {
        "status": 403
      }
    },
    {
      "state": "OH",
      "city": "Columbus",
      "zip": "43212",
      "theater_name": "Lennox Town Center 24",
      "chainName": "Phoenix Theatres",
      "chainCode": "PHNX",
      "showtime_id": 516343247,
      "date": "2025-09-19+18:15",
      "format": "Standard",
      "language": "Telugu",
      "error": {
        "status": 403
      }
    },
    {
      "state": "OH",
      "city": "Columbus",
      "zip": "43212",
      "theater_name": "Lennox Town Center 24",
      "chainName": "Phoenix Theatres",
      "chainCode": "PHNX",
      "showtime_id": 516343248,
      "date": "2025-09-19+21:30",
      "format": "Standard",
      "language": "Telugu",
      "error": {
        "status": 403
      }
    },
    {
      "state": "IN",
      "city": "Indianapolis",
      "zip": "46227",
      "theater_name": "Cinemark Greenwood Corner",
      "chainName": "Cinemark Theatres",
      "chainCode": "CNMK",
      "showtime_id": 516528037,
      "date": "2025-09-19+15:40",
      "format": "Standard",
      "language": "Telugu",
      "error": {
        "status": 403
      }
    },
    {
      "state": "IN",
      "city": "Indianapolis",
      "zip": "46227",
      "theater_name": "Cinemark Greenwood Corner",
      "chainName": "Cinemark Theatres",
      "chainCode": "CNMK",
      "showtime_id": 516528038,
      "date": "2025-09-19+21:55",
      "format": "Standard",
      "language": "Telugu",
      "error": {
        "status": 403
      }
    },
    {
      "state": "MI",
      "city": "Walled Lake",
      "zip": "48390",
      "theater_name": "Regal UA Commerce Township",
      "chainName": "Regal",
      "chainCode": "REGL",
      "showtime_id": 516275791,
      "date": "2025-09-19+15:15",
      "format": "Standard",
      "language": "Telugu",
      "error": {
        "status": 403
      }
    },
    {
      "state": "MI",
      "city": "Walled Lake",
      "zip": "48390",
      "theater_name": "Regal UA Commerce Township",
      "chainName": "Regal",
      "chainCode": "REGL",
      "showtime_id": 516275798,
      "date": "2025-09-19+18:30",
      "format": "Standard",
      "language": "Telugu",
      "error": {
        "status": 403
      }
    },
    {
      "state": "IA",
      "city": "West Des Moines",
      "zip": "50266",
      "theater_name": "Cinemark Century Jordan Creek 20 and XD",
      "chainName": "Cinemark Theatres",
      "chainCode": "CNMK",
      "showtime_id": 516408148,
      "date": "2025-09-19+23:00",
      "format": "Standard",
      "language": "Telugu",
      "error": {
        "status": 403
      }
    },
    {
      "state": "IA",
      "city": "Davenport",
      "zip": "52807",
      "theater_name": "Cinemark Davenport 18 XD and IMAX",
      "chainName": "Cinemark Theatres",
      "chainCode": "CNMK",
      "showtime_id": 516368061,
      "date": "2025-09-19+21:55",
      "format": "Standard",
      "language": "Telugu",
      "error": {
        "status": 403
      }
    },
    {
      "state": "MN",
      "city": "Saint Louis Park",
      "zip": "55416",
      "theater_name": "Marcus West End Cinema",
      "chainName": "Marcus Theatres",
      "chainCode": "MRCS",
      "showtime_id": 516092800,
      "date": "2025-09-19+21:15",
      "format": "Standard",
      "language": "Telugu",
      "error": {
        "status": 403
      }
    },
    {
      "state": "IL",
      "city": "Warrenville",
      "zip": "60555",
      "theater_name": "Phoenix Theatres Cantera Warrenville 17 + PTX",
      "chainName": "Phoenix Theatres",
      "chainCode": "PHNX",
      "showtime_id": 516424806,
      "date": "2025-09-19+14:45",
      "format": "Standard",
      "language": "Telugu",
      "error": {
        "status": 403
      }
    },
    {
      "state": "IL",
      "city": "Warrenville",
      "zip": "60555",
      "theater_name": "Phoenix Theatres Cantera Warrenville 17 + PTX",
      "chainName": "Phoenix Theatres",
      "chainCode": "PHNX",
      "showtime_id": 516424807,
      "date": "2025-09-19+18:15",
      "format": "Standard",
      "language": "Telugu",
      "error": {
        "status": 403
      }
    },
    {
      "state": "IL",
      "city": "North Aurora",
      "zip": "60542",
      "theater_name": "Cinemark Tinseltown USA Aurora",
      "chainName": "Cinemark Theatres",
      "chainCode": "CNMK",
      "showtime_id": 516271322,
      "date": "2025-09-19+13:20",
      "format": "Standard",
      "language": "Telugu",
      "error": {
        "status": 403
      }
    },
    {
      "state": "IL",
      "city": "North Aurora",
      "zip": "60542",
      "theater_name": "Cinemark Tinseltown USA Aurora",
      "chainName": "Cinemark Theatres",
      "chainCode": "CNMK",
      "showtime_id": 516271323,
      "date": "2025-09-19+16:25",
      "format": "Standard",
      "language": "Telugu",
      "error": {
        "status": 403
      }
    },
    {
      "state": "IL",
      "city": "North Aurora",
      "zip": "60542",
      "theater_name": "Cinemark Tinseltown USA Aurora",
      "chainName": "Cinemark Theatres",
      "chainCode": "CNMK",
      "showtime_id": 516271324,
      "date": "2025-09-19+19:30",
      "format": "Standard",
      "language": "Telugu",
      "error": {
        "status": 403
      }
    },
    {
      "state": "IL",
      "city": "North Aurora",
      "zip": "60542",
      "theater_name": "Cinemark Tinseltown USA Aurora",
      "chainName": "Cinemark Theatres",
      "chainCode": "CNMK",
      "showtime_id": 516271325,
      "date": "2025-09-19+22:35",
      "format": "Standard",
      "language": "Telugu",
      "error": {
        "status": 403
      }
    },
    {
      "state": "MO",
      "city": "Saint Peters",
      "zip": "63376",
      "theater_name": "Marcus Mid Rivers Cinema",
      "chainName": "Marcus Theatres",
      "chainCode": "MRCS",
      "showtime_id": 516026449,
      "date": "2025-09-19+19:50",
      "format": "Standard",
      "language": "Telugu",
      "error": {
        "status": 403
      }
    },
    {
      "state": "LA",
      "city": "Baton Rouge",
      "zip": "70810",
      "theater_name": "Cinemark Perkins Rowe and XD",
      "chainName": "Cinemark Theatres",
      "chainCode": "CNMK",
      "showtime_id": 516475016,
      "date": "2025-09-19+21:55",
      "format": "Standard",
      "language": "Telugu",
      "error": {
        "status": 403
      }
    },
    {
      "state": "TX",
      "city": "Plano",
      "zip": "75025",
      "theater_name": "Cinemark Legacy and XD",
      "chainName": "Cinemark Theatres",
      "chainCode": "CNMK",
      "showtime_id": 516449716,
      "date": "2025-09-19+13:50",
      "format": "Standard",
      "language": "Telugu",
      "error": {
        "status": 403
      }
    },
    {
      "state": "TX",
      "city": "Plano",
      "zip": "75025",
      "theater_name": "Cinemark Legacy and XD",
      "chainName": "Cinemark Theatres",
      "chainCode": "CNMK",
      "showtime_id": 516449717,
      "date": "2025-09-19+16:50",
      "format": "Standard",
      "language": "Telugu",
      "error": {
        "status": 403
      }
    },
    {
      "state": "TX",
      "city": "Plano",
      "zip": "75025",
      "theater_name": "Cinemark Legacy and XD",
      "chainName": "Cinemark Theatres",
      "chainCode": "CNMK",
      "showtime_id": 516449718,
      "date": "2025-09-19+19:50",
      "format": "Standard",
      "language": "Telugu",
      "error": {
        "status": 403
      }
    },
    {
      "state": "TX",
      "city": "Plano",
      "zip": "75025",
      "theater_name": "Cinemark Legacy and XD",
      "chainName": "Cinemark Theatres",
      "chainCode": "CNMK",
      "showtime_id": 516449719,
      "date": "2025-09-19+22:55",
      "format": "Standard",
      "language": "Telugu",
      "error": {
        "status": 403
      }
    },
    {
      "state": "TX",
      "city": "Plano",
      "zip": "75093",
      "theater_name": "Cinemark West Plano and XD",
      "chainName": "Cinemark Theatres",
      "chainCode": "CNMK",
      "showtime_id": 516086389,
      "date": "2025-09-19+12:10",
      "format": "Standard",
      "language": "Telugu",
      "error": {
        "status": 403
      }
    },
    {
      "state": "TX",
      "city": "Plano",
      "zip": "75093",
      "theater_name": "Cinemark West Plano and XD",
      "chainName": "Cinemark Theatres",
      "chainCode": "CNMK",
      "showtime_id": 516086390,
      "date": "2025-09-19+15:05",
      "format": "Standard",
      "language": "Telugu",
      "error": {
        "status": 403
      }
    },
    {
      "state": "TX",
      "city": "The Colony",
      "zip": "75056",
      "theater_name": "Galaxy Grandscape",
      "chainName": "Galaxy Theatres",
      "chainCode": "GLXY",
      "showtime_id": 516219211,
      "date": "2025-09-19+19:30",
      "format": "Standard",
      "language": "Telugu",
      "error": {
        "status": 403
      }
    },
    {
      "state": "TX",
      "city": "Frisco",
      "zip": "75033",
      "theater_name": "CUT! by Cinemark Frisco - Dine-in Theatre, Kitchen",
      "chainName": "Cinemark Theatres",
      "chainCode": "CNMK",
      "showtime_id": 516387605,
      "date": "2025-09-19+21:45",
      "format": "Standard",
      "language": "Telugu",
      "error": {
        "status": 403
      }
    },
    {
      "state": "TX",
      "city": "Grapevine",
      "zip": "76051",
      "theater_name": "Cinemark Tinseltown Grapevine and XD",
      "chainName": "Cinemark Theatres",
      "chainCode": "CNMK",
      "showtime_id": 516448632,
      "date": "2025-09-19+14:15",
      "format": "Standard",
      "language": "Telugu",
      "error": {
        "status": 403
      }
    },
    {
      "state": "TX",
      "city": "Grapevine",
      "zip": "76051",
      "theater_name": "Cinemark Tinseltown Grapevine and XD",
      "chainName": "Cinemark Theatres",
      "chainCode": "CNMK",
      "showtime_id": 516448633,
      "date": "2025-09-19+17:15",
      "format": "Standard",
      "language": "Telugu",
      "error": {
        "status": 403
      }
    },
    {
      "state": "TX",
      "city": "Grapevine",
      "zip": "76051",
      "theater_name": "Cinemark Tinseltown Grapevine and XD",
      "chainName": "Cinemark Theatres",
      "chainCode": "CNMK",
      "showtime_id": 516448634,
      "date": "2025-09-19+20:10",
      "format": "Standard",
      "language": "Telugu",
      "error": {
        "status": 403
      }
    },
    {
      "state": "TX",
      "city": "Grapevine",
      "zip": "76051",
      "theater_name": "Cinemark Tinseltown Grapevine and XD",
      "chainName": "Cinemark Theatres",
      "chainCode": "CNMK",
      "showtime_id": 516448635,
      "date": "2025-09-19+23:00",
      "format": "Standard",
      "language": "Telugu",
      "error": {
        "status": 403
      }
    },
    {
      "state": "TX",
      "city": "Lewisville",
      "zip": "75067",
      "theater_name": "Cinemark Lewisville and XD",
      "chainName": "Cinemark Theatres",
      "chainCode": "CNMK",
      "showtime_id": 516387155,
      "date": "2025-09-19+20:00",
      "format": "Standard",
      "language": "Telugu",
      "error": {
        "status": 403
      }
    },
    {
      "state": "TX",
      "city": "Lewisville",
      "zip": "75067",
      "theater_name": "Cinemark Lewisville and XD",
      "chainName": "Cinemark Theatres",
      "chainCode": "CNMK",
      "showtime_id": 516387156,
      "date": "2025-09-19+22:50",
      "format": "Standard",
      "language": "Telugu",
      "error": {
        "status": 403
      }
    },
    {
      "state": "TX",
      "city": "Denton",
      "zip": "76210",
      "theater_name": "Cinemark Denton 14",
      "chainName": "Cinemark Theatres",
      "chainCode": "CNMK",
      "showtime_id": 516520877,
      "date": "2025-09-19+14:20",
      "format": "Standard",
      "language": "Telugu",
      "error": {
        "status": 403
      }
    },
    {
      "state": "TX",
      "city": "Denton",
      "zip": "76210",
      "theater_name": "Cinemark Denton 14",
      "chainName": "Cinemark Theatres",
      "chainCode": "CNMK",
      "showtime_id": 516520878,
      "date": "2025-09-19+17:05",
      "format": "Standard",
      "language": "Telugu",
      "error": {
        "status": 403
      }
    },
    {
      "state": "TX",
      "city": "Denton",
      "zip": "76210",
      "theater_name": "Cinemark Denton 14",
      "chainName": "Cinemark Theatres",
      "chainCode": "CNMK",
      "showtime_id": 516520879,
      "date": "2025-09-19+20:00",
      "format": "Standard",
      "language": "Telugu",
      "error": {
        "status": 403
      }
    },
    {
      "state": "TX",
      "city": "Denton",
      "zip": "76210",
      "theater_name": "Cinemark Denton 14",
      "chainName": "Cinemark Theatres",
      "chainCode": "CNMK",
      "showtime_id": 516520880,
      "date": "2025-09-19+22:50",
      "format": "Standard",
      "language": "Telugu",
      "error": {
        "status": 403
      }
    },
    {
      "state": "TX",
      "city": "Dallas",
      "zip": "75234",
      "theater_name": "Cinemark Dallas XD and IMAX",
      "chainName": "Cinemark Theatres",
      "chainCode": "CNMK",
      "showtime_id": 516238367,
      "date": "2025-09-19+11:15",
      "format": "Standard",
      "language": "Telugu",
      "error": {
        "status": 403
      }
    },
    {
      "state": "TX",
      "city": "Dallas",
      "zip": "75234",
      "theater_name": "Cinemark Dallas XD and IMAX",
      "chainName": "Cinemark Theatres",
      "chainCode": "CNMK",
      "showtime_id": 516238368,
      "date": "2025-09-19+16:50",
      "format": "Standard",
      "language": "Telugu",
      "error": {
        "status": 403
      }
    },
    {
      "state": "TX",
      "city": "Dallas",
      "zip": "75234",
      "theater_name": "Cinemark Dallas XD and IMAX",
      "chainName": "Cinemark Theatres",
      "chainCode": "CNMK",
      "showtime_id": 516238369,
      "date": "2025-09-19+22:35",
      "format": "Standard",
      "language": "Telugu",
      "error": {
        "status": 403
      }
    },
    {
      "state": "TX",
      "city": "Pflugerville",
      "zip": "78660",
      "theater_name": "Cinemark Pflugerville 20 and XD",
      "chainName": "Cinemark Theatres",
      "chainCode": "CNMK",
      "showtime_id": 516563330,
      "date": "2025-09-19+14:55",
      "format": "Standard",
      "language": "Telugu",
      "error": {
        "status": 403
      }
    },
    {
      "state": "TX",
      "city": "Pflugerville",
      "zip": "78660",
      "theater_name": "Cinemark Pflugerville 20 and XD",
      "chainName": "Cinemark Theatres",
      "chainCode": "CNMK",
      "showtime_id": 516563331,
      "date": "2025-09-19+17:50",
      "format": "Standard",
      "language": "Telugu",
      "error": {
        "status": 403
      }
    },
    {
      "state": "TX",
      "city": "Pflugerville",
      "zip": "78660",
      "theater_name": "Cinemark Pflugerville 20 and XD",
      "chainName": "Cinemark Theatres",
      "chainCode": "CNMK",
      "showtime_id": 516563332,
      "date": "2025-09-19+20:45",
      "format": "Standard",
      "language": "Telugu",
      "error": {
        "status": 403
      }
    },
    {
      "state": "TX",
      "city": "Pflugerville",
      "zip": "78660",
      "theater_name": "Cinemark Pflugerville 20 and XD",
      "chainName": "Cinemark Theatres",
      "chainCode": "CNMK",
      "showtime_id": 516563333,
      "date": "2025-09-19+23:45",
      "format": "Standard",
      "language": "Telugu",
      "error": {
        "status": 403
      }
    },
    {
      "state": "TX",
      "city": "Houston",
      "zip": "77040",
      "theater_name": "Cinemark Tinseltown Houston 290 and XD",
      "chainName": "Cinemark Theatres",
      "chainCode": "CNMK",
      "showtime_id": 516476239,
      "date": "2025-09-19+21:30",
      "format": "Standard",
      "language": "Telugu",
      "error": {
        "status": 403
      }
    },
    {
      "state": "TX",
      "city": "San Antonio",
      "zip": "78229",
      "theater_name": "Cinemark Movies 16",
      "chainName": "Cinemark Theatres",
      "chainCode": "CNMK",
      "showtime_id": 516100217,
      "date": "2025-09-19+10:20",
      "format": "Standard",
      "language": "Telugu",
      "error": {
        "status": 403
      }
    },
    {
      "state": "TX",
      "city": "San Antonio",
      "zip": "78229",
      "theater_name": "Cinemark Movies 16",
      "chainName": "Cinemark Theatres",
      "chainCode": "CNMK",
      "showtime_id": 516100218,
      "date": "2025-09-19+13:25",
      "format": "Standard",
      "language": "Telugu",
      "error": {
        "status": 403
      }
    },
    {
      "state": "TX",
      "city": "San Antonio",
      "zip": "78229",
      "theater_name": "Cinemark Movies 16",
      "chainName": "Cinemark Theatres",
      "chainCode": "CNMK",
      "showtime_id": 516100219,
      "date": "2025-09-19+16:30",
      "format": "Standard",
      "language": "Telugu",
      "error": {
        "status": 403
      }
    },
    {
      "state": "TX",
      "city": "San Antonio",
      "zip": "78229",
      "theater_name": "Cinemark Movies 16",
      "chainName": "Cinemark Theatres",
      "chainCode": "CNMK",
      "showtime_id": 516100220,
      "date": "2025-09-19+19:35",
      "format": "Standard",
      "language": "Telugu",
      "error": {
        "status": 403
      }
    },
    {
      "state": "TX",
      "city": "San Antonio",
      "zip": "78229",
      "theater_name": "Cinemark Movies 16",
      "chainName": "Cinemark Theatres",
      "chainCode": "CNMK",
      "showtime_id": 516100221,
      "date": "2025-09-19+22:40",
      "format": "Standard",
      "language": "Telugu",
      "error": {
        "status": 403
      }
    },
    {
      "state": "CO",
      "city": "Aurora",
      "zip": "80012",
      "theater_name": "Cinemark Century Aurora and XD",
      "chainName": "Cinemark Theatres",
      "chainCode": "CNMK",
      "showtime_id": 516559185,
      "date": "2025-09-19+12:05",
      "format": "Standard",
      "language": "Telugu",
      "error": {
        "status": 403
      }
    },
    {
      "state": "CO",
      "city": "Aurora",
      "zip": "80012",
      "theater_name": "Cinemark Century Aurora and XD",
      "chainName": "Cinemark Theatres",
      "chainCode": "CNMK",
      "showtime_id": 516559184,
      "date": "2025-09-19+18:45",
      "format": "Standard",
      "language": "Telugu",
      "error": {
        "status": 403
      }
    },
    {
      "state": "AZ",
      "city": "Avondale",
      "zip": "85392",
      "theater_name": "Harkins Gateway Pavilions 18",
      "chainName": "Harkins Theatres",
      "chainCode": "HRKN",
      "showtime_id": 516490340,
      "date": "2025-09-19+20:15",
      "format": "Standard",
      "language": "Telugu",
      "error": {
        "status": 403
      }
    },
    {
      "state": "AZ",
      "city": "Mesa",
      "zip": "85201",
      "theater_name": "Cinemark Mesa 16",
      "chainName": "Cinemark Theatres",
      "chainCode": "CNMK",
      "showtime_id": 516415042,
      "date": "2025-09-19+14:55",
      "format": "Standard",
      "language": "Telugu",
      "error": {
        "status": 403
      }
    },
    {
      "state": "AZ",
      "city": "Mesa",
      "zip": "85201",
      "theater_name": "Cinemark Mesa 16",
      "chainName": "Cinemark Theatres",
      "chainCode": "CNMK",
      "showtime_id": 516415043,
      "date": "2025-09-19+18:00",
      "format": "Standard",
      "language": "Telugu",
      "error": {
        "status": 403
      }
    },
    {
      "state": "AZ",
      "city": "Mesa",
      "zip": "85201",
      "theater_name": "Cinemark Mesa 16",
      "chainName": "Cinemark Theatres",
      "chainCode": "CNMK",
      "showtime_id": 516415044,
      "date": "2025-09-19+21:05",
      "format": "Standard",
      "language": "Telugu",
      "error": {
        "status": 403
      }
    },
    {
      "state": "NM",
      "city": "Albuquerque",
      "zip": "87109",
      "theater_name": "Cinemark Century Rio Plex 24 and XD",
      "chainName": "Cinemark Theatres",
      "chainCode": "CNMK",
      "showtime_id": 516241889,
      "date": "2025-09-19+21:25",
      "format": "Standard",
      "language": "Telugu",
      "error": {
        "status": 403
      }
    },
    {
      "state": "NV",
      "city": "Las Vegas",
      "zip": "89103",
      "theater_name": "Cinemark Century Orleans 18 and XD",
      "chainName": "Cinemark Theatres",
      "chainCode": "CNMK",
      "showtime_id": 516584637,
      "date": "2025-09-19+18:45",
      "format": "Standard",
      "language": "Telugu",
      "error": {
        "status": 403
      }
    },
    {
      "state": "NV",
      "city": "Las Vegas",
      "zip": "89103",
      "theater_name": "Cinemark Century Orleans 18 and XD",
      "chainName": "Cinemark Theatres",
      "chainCode": "CNMK",
      "showtime_id": 516584638,
      "date": "2025-09-19+21:50",
      "format": "Standard",
      "language": "Telugu",
      "error": {
        "status": 403
      }
    },
    {
      "state": "NV",
      "city": "Reno",
      "zip": "89511",
      "theater_name": "Cinemark Century Summit Sierra",
      "chainName": "Cinemark Theatres",
      "chainCode": "CNMK",
      "showtime_id": 516384025,
      "date": "2025-09-19+10:40",
      "format": "Standard",
      "language": "Telugu",
      "error": {
        "status": 403
      }
    },
    {
      "state": "NV",
      "city": "Reno",
      "zip": "89511",
      "theater_name": "Cinemark Century Summit Sierra",
      "chainName": "Cinemark Theatres",
      "chainCode": "CNMK",
      "showtime_id": 516384027,
      "date": "2025-09-19+17:30",
      "format": "Standard",
      "language": "Telugu",
      "error": {
        "status": 403
      }
    },
    {
      "state": "CA",
      "city": "Orange",
      "zip": "92867",
      "theater_name": "Cinemark Century Orange and XD",
      "chainName": "Cinemark Theatres",
      "chainCode": "CNMK",
      "showtime_id": 516572658,
      "date": "2025-09-19+16:50",
      "format": "Standard",
      "language": "Telugu",
      "error": {
        "status": 403
      }
    },
    {
      "state": "CA",
      "city": "Orange",
      "zip": "92867",
      "theater_name": "Cinemark Century Orange and XD",
      "chainName": "Cinemark Theatres",
      "chainCode": "CNMK",
      "showtime_id": 516572659,
      "date": "2025-09-19+22:10",
      "format": "Standard",
      "language": "Telugu",
      "error": {
        "status": 403
      }
    },
    {
      "state": "CA",
      "city": "El Cajon",
      "zip": "92020",
      "theater_name": "Regal Parkway Plaza & IMAX",
      "chainName": "Regal",
      "chainCode": "REGL",
      "showtime_id": 516052401,
      "date": "2025-09-19+15:15",
      "format": "Standard",
      "language": "Telugu",
      "error": {
        "status": 403
      }
    },
    {
      "state": "CA",
      "city": "El Cajon",
      "zip": "92020",
      "theater_name": "Regal Parkway Plaza & IMAX",
      "chainName": "Regal",
      "chainCode": "REGL",
      "showtime_id": 516052403,
      "date": "2025-09-19+21:30",
      "format": "Standard",
      "language": "Telugu",
      "error": {
        "status": 403
      }
    },
    {
      "state": "CA",
      "city": "Milpitas",
      "zip": "95035",
      "theater_name": "Cinemark Century Great Mall 20 XD and ScreenX",
      "chainName": "Cinemark Theatres",
      "chainCode": "CNMK",
      "showtime_id": 516203645,
      "date": "2025-09-19+11:00",
      "format": "Standard",
      "language": "Telugu",
      "error": {
        "status": 403
      }
    },
    {
      "state": "CA",
      "city": "Milpitas",
      "zip": "95035",
      "theater_name": "Cinemark Century Great Mall 20 XD and ScreenX",
      "chainName": "Cinemark Theatres",
      "chainCode": "CNMK",
      "showtime_id": 516660850,
      "date": "2025-09-19+11:30",
      "format": "Standard",
      "language": "Telugu",
      "error": {
        "status": 403
      }
    },
    {
      "state": "CA",
      "city": "Milpitas",
      "zip": "95035",
      "theater_name": "Cinemark Century Great Mall 20 XD and ScreenX",
      "chainName": "Cinemark Theatres",
      "chainCode": "CNMK",
      "showtime_id": 516203646,
      "date": "2025-09-19+14:25",
      "format": "Standard",
      "language": "Telugu",
      "error": {
        "status": 403
      }
    },
    {
      "state": "CA",
      "city": "Milpitas",
      "zip": "95035",
      "theater_name": "Cinemark Century Great Mall 20 XD and ScreenX",
      "chainName": "Cinemark Theatres",
      "chainCode": "CNMK",
      "showtime_id": 516679365,
      "date": "2025-09-19+20:20",
      "format": "Standard",
      "language": "Telugu",
      "error": {
        "status": 403
      }
    },
    {
      "state": "CA",
      "city": "Milpitas",
      "zip": "95035",
      "theater_name": "Cinemark Century Great Mall 20 XD and ScreenX",
      "chainName": "Cinemark Theatres",
      "chainCode": "CNMK",
      "showtime_id": 516203647,
      "date": "2025-09-19+20:35",
      "format": "Standard",
      "language": "Telugu",
      "error": {
        "status": 403
      }
    },
    {
      "state": "CA",
      "city": "Milpitas",
      "zip": "95035",
      "theater_name": "Cinemark Century Great Mall 20 XD and ScreenX",
      "chainName": "Cinemark Theatres",
      "chainCode": "CNMK",
      "showtime_id": 516660848,
      "date": "2025-09-19+21:50",
      "format": "Standard",
      "language": "Telugu",
      "error": {
        "status": 403
      }
    },
    {
      "state": "CA",
      "city": "Milpitas",
      "zip": "95035",
      "theater_name": "Cinemark Century Great Mall 20 XD and ScreenX",
      "chainName": "Cinemark Theatres",
      "chainCode": "CNMK",
      "showtime_id": 516660849,
      "date": "2025-09-19+23:20",
      "format": "Standard",
      "language": "Telugu",
      "error": {
        "status": 403
      }
    },
    {
      "state": "CA",
      "city": "Fremont",
      "zip": "94538",
      "theater_name": "Ciné Lounge Fremont 7",
      "chainName": "RTSIND",
      "chainCode": "RTSIND",
      "showtime_id": 516228104,
      "date": "2025-09-19+16:50",
      "format": "Standard",
      "language": "Telugu",
      "error": {
        "status": 403
      }
    },
    {
      "state": "CA",
      "city": "Dublin",
      "zip": "94568",
      "theater_name": "Regal Hacienda Crossings ScreenX, IMAX & RPX",
      "chainName": "Regal",
      "chainCode": "REGL",
      "showtime_id": 516218222,
      "date": "2025-09-19+09:50",
      "format": "Standard",
      "language": "Telugu",
      "error": {
        "status": 403
      }
    },
    {
      "state": "CA",
      "city": "Dublin",
      "zip": "94568",
      "theater_name": "Regal Hacienda Crossings ScreenX, IMAX & RPX",
      "chainName": "Regal",
      "chainCode": "REGL",
      "showtime_id": 516218249,
      "date": "2025-09-19+17:30",
      "format": "Standard",
      "language": "Telugu",
      "error": {
        "status": 403
      }
    },
    {
      "state": "WA",
      "city": "Bellevue",
      "zip": "98004",
      "theater_name": "Cinemark Lincoln Square",
      "chainName": "Cinemark Theatres",
      "chainCode": "CNMK",
      "showtime_id": 516410337,
      "date": "2025-09-19+15:55",
      "format": "Standard",
      "language": "Telugu",
      "error": {
        "status": 403
      }
    },
    {
      "state": "WA",
      "city": "Bellevue",
      "zip": "98004",
      "theater_name": "Cinemark Lincoln Square",
      "chainName": "Cinemark Theatres",
      "chainCode": "CNMK",
      "showtime_id": 516410338,
      "date": "2025-09-19+22:30",
      "format": "Standard",
      "language": "Telugu",
      "error": {
        "status": 403
      }
    },
    {
      "state": "WA",
      "city": "Redmond",
      "zip": "98052",
      "theater_name": "Regal Bella Bottega",
      "chainName": "Regal",
      "chainCode": "REGL",
      "showtime_id": 516035418,
      "date": "2025-09-19+11:30",
      "format": "Standard",
      "language": "Telugu",
      "error": {
        "status": 403
      }
    },
    {
      "state": "WA",
      "city": "Redmond",
      "zip": "98052",
      "theater_name": "Regal Bella Bottega",
      "chainName": "Regal",
      "chainCode": "REGL",
      "showtime_id": 516035417,
      "date": "2025-09-19+14:35",
      "format": "Standard",
      "language": "Telugu",
      "error": {
        "status": 403
      }
    },
    {
      "state": "WA",
      "city": "Redmond",
      "zip": "98052",
      "theater_name": "Regal Bella Bottega",
      "chainName": "Regal",
      "chainCode": "REGL",
      "showtime_id": 516035416,
      "date": "2025-09-19+17:40",
      "format": "Standard",
      "language": "Telugu",
      "error": {
        "status": 403
      }
    },
    {
      "state": "WA",
      "city": "Redmond",
      "zip": "98052",
      "theater_name": "Regal Bella Bottega",
      "chainName": "Regal",
      "chainCode": "REGL",
      "showtime_id": 516035384,
      "date": "2025-09-19+20:40",
      "format": "Standard",
      "language": "Telugu",
      "error": {
        "status": 403
      }
    },
    {
      "state": "WA",
      "city": "Seattle",
      "zip": "98101",
      "theater_name": "Regal Meridian & 4DX",
      "chainName": "Regal",
      "chainCode": "REGL",
      "showtime_id": 516565805,
      "date": "2025-09-19+15:30",
      "format": "Standard",
      "language": "Telugu",
      "error": {
        "status": 403
      }
    },
    {
      "state": "WA",
      "city": "Seattle",
      "zip": "98101",
      "theater_name": "Regal Meridian & 4DX",
      "chainName": "Regal",
      "chainCode": "REGL",
      "showtime_id": 516565806,
      "date": "2025-09-19+18:50",
      "format": "Standard",
      "language": "Telugu",
      "error": {
        "status": 403
      }
    },
    {
      "state": "WA",
      "city": "Seattle",
      "zip": "98101",
      "theater_name": "Regal Meridian & 4DX",
      "chainName": "Regal",
      "chainCode": "REGL",
      "showtime_id": 516565807,
      "date": "2025-09-19+22:10",
      "format": "Standard",
      "language": "Telugu",
      "error": {
        "status": 403
      }
    }
  ]
}