[
  {
    "sessions": 275,
    "venues": 49,
    "sold": 7649,
    "available": 46622,
    "total": 54271,
    "gross": 235269.0,
    "max_gross": 1610267.0,
    "occupancy": 14.09,
    "name": "Demon Slayer: Kimetsu no Yaiba- Infinity Castle (Japanese, Eng Sub)",
    "summary": "The three-part cinematic movie represents the final arc and culmination of the hugely popular award-winning anime shonen series. ",
    "duration": 155,
    "releaseDate": "2025-09-11T00:00:00",
    "posterImage": "mx/posters/au/demon-slayer-kimetsu-no-yaiba-infinity-castle-subbed-ce798f8d.jpg",
    "id": "HO00010233"
  },
  {
    "sessions": 67,
    "venues": 48,
    "sold": 937,
    "available": 10211,
    "total": 11148,
    "gross": 25294.5,
    "max_gross": 305134.0,
    "occupancy": 8.41,
    "name": "Demon Slayer: Kimetsu no Yaiba- Infinity Castle (English)",
    "summary": "The three-part cinematic movie represents the final arc and culmination of the hugely popular award-winning anime shonen series. ",
    "duration": 155,
    "releaseDate": "2025-09-11T00:00:00",
    "posterImage": "mx/posters/au/demon-slayer-kimetsu-no-yaiba-infinity-castle-dubbed-0827b096.jpg",
    "id": "HO00010246"
  },
  {
    "sessions": 42,
    "venues": 27,
    "sold": 331,
    "available": 6079,
    "total": 6410,
    "gross": 8421.0,
    "max_gross": 162280.0,
    "occupancy": 5.16,
    "name": "Downton Abbey: The Grand Finale",
    "summary": "Experience the beloved Crawley family\u2019s final chapter in Downton Abbey: The Grand Finale.",
    "duration": 123,
    "releaseDate": "2025-09-11T00:00:00",
    "posterImage": "mx/posters/au/downton-abbey-the-grand-finale-c4fd18a1.jpg",
    "id": "HO00009618"
  },
  {
    "sessions": 111,
    "venues": 49,
    "sold": 3949,
    "available": 18846,
    "total": 22795,
    "gross": 109263.0,
    "max_gross": 622741.75,
    "occupancy": 17.32,
    "name": "The Conjuring: Last Rites",
    "summary": "The Conjuring: Last Rites delivers another thrilling chapter of the iconic Conjuring cinematic universe, based on real events. ",
    "duration": 135,
    "releaseDate": "2025-09-04T00:00:00",
    "posterImage": "mx/posters/au/the-conjuring-last-rites-efeea4c3.jpg",
    "id": "HO00008335"
  },
  {
    "sessions": 38,
    "venues": 34,
    "sold": 320,
    "available": 5253,
    "total": 5573,
    "gross": 7890.0,
    "max_gross": 135374.0,
    "occupancy": 5.74,
    "name": "The Naked Gun",
    "summary": "Follows the misadventures of Detective Frank Drebin's son, Frank Drebin jr.",
    "duration": 85,
    "releaseDate": "2025-08-21T00:00:00",
    "posterImage": "mx/posters/au/the-naked-gun-d92e182e.jpg",
    "id": "HO00009351"
  },
  {
    "sessions": 7,
    "venues": 5,
    "sold": 131,
    "available": 1400,
    "total": 1531,
    "gross": 3078.0,
    "max_gross": 34550.0,
    "occupancy": 8.56,
    "name": "Leaving Mom (Vietnamese, Eng Sub)",
    "summary": "A poor street barber in Vietnam decides to seek help from his brother as he struggles to care for his dementia-stricken mother while his own health deteriorates.",
    "duration": 114,
    "releaseDate": "2025-09-11T00:00:00",
    "posterImage": "mx/posters/au/leaving-mom-39b71840.jpg",
    "id": "HO00010537"
  },
  {
    "sessions": 1,
    "venues": 1,
    "sold": 41,
    "available": 111,
    "total": 152,
    "gross": 1066.0,
    "max_gross": 3952.0,
    "occupancy": 26.97,
    "name": "Sketch",
    "summary": "\nA young girl\u2019s monster drawings come to life after falling into a strange pond, unleashing chaos. Her family must reunite to save their town before it's too late",
    "duration": 92,
    "releaseDate": "2025-09-11T00:00:00",
    "posterImage": "mx/posters/au/sketch-3e2c54b3.jpg",
    "id": "HO00010330"
  },
  {
    "sessions": 17,
    "venues": 17,
    "sold": 84,
    "available": 2483,
    "total": 2567,
    "gross": 2013.0,
    "max_gross": 63315.0,
    "occupancy": 3.27,
    "name": "The Fantastic Four: First Steps",
    "summary": "One of Marvel's most iconic families makes it to the big screen: the Fantastic Four.",
    "duration": 114,
    "releaseDate": "2025-07-24T00:00:00",
    "posterImage": "mx/posters/au/the-fantastic-four-first-steps-78e4edfe.jpg",
    "id": "HO00007688"
  },
  {
    "sessions": 19,
    "venues": 19,
    "sold": 50,
    "available": 2749,
    "total": 2799,
    "gross": 1261.5,
    "max_gross": 68013.5,
    "occupancy": 1.79,
    "name": "Caught Stealing",
    "summary": "Burned-out ex-baseball player Hank Thompson unexpectedly finds himself embroiled in a dangerous struggle for survival amidst the criminal underbelly of 1990s NYC...",
    "duration": 107,
    "releaseDate": "2025-08-28T00:00:00",
    "posterImage": "mx/posters/au/caught-stealing-9f22c0f1.jpg",
    "id": "HO00010166"
  },
  {
    "sessions": 58,
    "venues": 43,
    "sold": 543,
    "available": 9172,
    "total": 9715,
    "gross": 13403.810000000001,
    "max_gross": 233664.72,
    "occupancy": 5.59,
    "name": "The Long Walk",
    "summary": "A group of teenage boys compete in an annual contest known as \"The Long Walk,\" where they must maintain a certain walking speed or get shot.",
    "duration": 107,
    "releaseDate": "2025-09-11T00:00:00",
    "posterImage": "mx/posters/au/the-long-walk-6010993c.jpg",
    "id": "HO00010397"
  },
  {
    "sessions": 32,
    "venues": 28,
    "sold": 316,
    "available": 5171,
    "total": 5487,
    "gross": 7963.0,
    "max_gross": 135806.0,
    "occupancy": 5.76,
    "name": "The Roses",
    "summary": "Ivy and Theo, the picture-perfect couple who have successful careers, great kids, and an enviable sex life. But underneath the fa\u00e7ade of the perfect family is a tinderbox of competition and resentments.",
    "duration": 105,
    "releaseDate": "2025-09-04T00:00:00",
    "posterImage": "mx/posters/au/the-roses-d11faaef.jpg",
    "id": "HO00010303"
  },
  {
    "sessions": 16,
    "venues": 16,
    "sold": 13,
    "available": 2708,
    "total": 2721,
    "gross": 311.0,
    "max_gross": 62903.5,
    "occupancy": 0.48,
    "name": "Fight or Flight",
    "summary": "A mercenary takes on the job of tracking down a target on a plane but must protect her when they're surrounded by people trying to kill both of them.",
    "duration": 102,
    "releaseDate": "2025-09-04T00:00:00",
    "posterImage": "mx/posters/au/fight-or-flight-8a8ecb9e.jpg",
    "id": "HO00010301"
  },
  {
    "sessions": 12,
    "venues": 11,
    "sold": 47,
    "available": 1481,
    "total": 1528,
    "gross": 1189.5,
    "max_gross": 37226.0,
    "occupancy": 3.08,
    "name": "Splitsville",
    "summary": "When Ashley asks for a divorce, the good-natured Carey runs to his friends, Julie and Paul, for support. ",
    "duration": 100,
    "releaseDate": "2025-09-11T00:00:00",
    "posterImage": "mx/posters/au/splitsville-087ccef9.jpg",
    "id": "HO00010471"
  },
  {
    "sessions": 8,
    "venues": 8,
    "sold": 25,
    "available": 889,
    "total": 914,
    "gross": 659.0,
    "max_gross": 23320.5,
    "occupancy": 2.74,
    "id": "HO00008333"
  },
  {
    "sessions": 33,
    "venues": 31,
    "sold": 244,
    "available": 5132,
    "total": 5376,
    "gross": 6186.5,
    "max_gross": 134929.0,
    "occupancy": 4.54,
    "name": "Weapons",
    "summary": "When all but one child from the same class mysteriously vanish on the same night at exactly the same time, a community is left questioning who or what is behind their disappearance.",
    "duration": 128,
    "releaseDate": "2025-08-07T00:00:00",
    "posterImage": "mx/posters/au/weapons-4dd66fe3.jpg",
    "id": "HO00009498"
  },
  {
    "sessions": 8,
    "venues": 7,
    "sold": 526,
    "available": 1081,
    "total": 1607,
    "gross": 13045.0,
    "max_gross": 37190.0,
    "occupancy": 32.73,
    "name": "Little Hearts (Telugu, Eng Sub)",
    "summary": "Akhil, when failed in EAMCET exam, is forced into long-term coaching after heartbreak teaches him the difference between true and shallow love.",
    "duration": 138,
    "releaseDate": "2025-09-11T00:00:00",
    "posterImage": "mx/posters/au/little-hearts-fc503b06.jpg",
    "id": "HO00010707"
  },
  {
    "sessions": 21,
    "venues": 20,
    "sold": 323,
    "available": 2728,
    "total": 3051,
    "gross": 7766.0,
    "max_gross": 71224.0,
    "occupancy": 10.59,
    "name": "Lokah Chapter 1: Chandra (Malayalam, Eng Sub)",
    "summary": "Extraordinary events unfold when an aimless trio of friends encounter their new neighbour \u2014 a mysterious young woman with a haunting past. A darkly comic fantasy thriller",
    "duration": 161,
    "releaseDate": "2025-08-28T00:00:00",
    "posterImage": "mx/posters/au/lokah-chapter-one-chandra-44a864c0.jpg",
    "id": "HO00010678"
  },
  {
    "sessions": 5,
    "venues": 5,
    "sold": 46,
    "available": 494,
    "total": 540,
    "gross": 1190.0,
    "max_gross": 14225.0,
    "occupancy": 8.52,
    "name": "F1 The Movie",
    "summary": "A Formula One driver comes out of retirement to mentor and team with a younger driver.",
    "duration": 155,
    "releaseDate": "2025-06-26T00:00:00",
    "posterImage": "mx/posters/au/f1-intl-one-sheet-teaser-update-aus-digital-hires.jpg",
    "id": "HO00009611"
  },
  {
    "sessions": 1,
    "venues": 1,
    "sold": 0,
    "available": 60,
    "total": 60,
    "gross": 0.0,
    "max_gross": 1560.0,
    "occupancy": 0.0,
    "name": "The Toxic Avenger",
    "summary": "A horrible toxic accident transforms downtrodden janitor, Winston Gooze into a new evolution of hero: The Toxic Avenger.",
    "duration": 102,
    "releaseDate": "2025-08-28T00:00:00",
    "posterImage": "mx/posters/au/the-toxic-avenger-6de04df4.jpg",
    "id": "HO00010460"
  },
  {
    "sessions": 4,
    "venues": 4,
    "sold": 17,
    "available": 580,
    "total": 597,
    "gross": 436.0,
    "max_gross": 15207.5,
    "occupancy": 2.85,
    "name": "Jurassic World: Rebirth",
    "summary": "Five years after Jurassic World Dominion, an expedition braves isolated equatorial regions to extract DNA from three massive prehistoric creatures.",
    "duration": 133,
    "releaseDate": "2025-07-03T00:00:00",
    "posterImage": "mx/posters/au/jw4-intl-one-sheet-t-rex-montage-sj-aus-digital-hires.jpg",
    "id": "HO00008377"
  },
  {
    "sessions": 13,
    "venues": 13,
    "sold": 109,
    "available": 1813,
    "total": 1922,
    "gross": 2650.5,
    "max_gross": 45639.0,
    "occupancy": 5.67,
    "name": "Freakier Friday",
    "summary": "Anna Coleman and her mother Tess are in another predicament when they swap bodies with Anna's daughter. Now it's up to the three to reverse the body swap.",
    "duration": 111,
    "releaseDate": "2025-08-07T00:00:00",
    "posterImage": "mx/posters/au/freakier-friday-c2fb18eb.jpg",
    "id": "HO00009718"
  },
  {
    "sessions": 2,
    "venues": 2,
    "sold": 32,
    "available": 642,
    "total": 674,
    "gross": 656.0,
    "max_gross": 12772.0,
    "occupancy": 4.75,
    "name": "Lokah Chapter One: Chandra (Telugu, Eng Sub)",
    "summary": "Extraordinary events unfold when an aimless trio of friends encounter their new neighbour \u2014 a mysterious young woman with a haunting past. A darkly comic fantasy thriller",
    "duration": 161,
    "releaseDate": "2025-08-28T00:00:00",
    "posterImage": "mx/posters/au/lokah-chapter-one-chandra-44a864c0.jpg",
    "id": "HO00010706"
  },
  {
    "sessions": 5,
    "venues": 5,
    "sold": 79,
    "available": 528,
    "total": 607,
    "gross": 1966.0,
    "max_gross": 15389.0,
    "occupancy": 13.01,
    "name": "The Shadow's Edge (Mandarin, Eng Sub)",
    "summary": "A crew of criminal prodigies disappears with billions, evading capture by outsmarting the formidable \u201cSky Eye\u201d surveillance system. ",
    "duration": 141,
    "releaseDate": "2025-08-21T00:00:00",
    "posterImage": "mx/posters/au/the-shadows-edge-62acc0e2.jpg",
    "id": "HO00010653"
  },
  {
    "sessions": 4,
    "venues": 4,
    "sold": 55,
    "available": 344,
    "total": 399,
    "gross": 1407.0,
    "max_gross": 9969.0,
    "occupancy": 13.78,
    "name": "Param Sundari (Hindi, Eng Sub)",
    "summary": "In Kerala's picturesque backwaters, a North Indian and South Indian find unexpected love. Their cultural differences spark a hilarious and chaotic romance, full of twists and turns.",
    "duration": 146,
    "releaseDate": "2025-08-29T00:00:00",
    "posterImage": "mx/posters/au/param-sundari-5b26e02a.jpg",
    "id": "HO00010412"
  },
  {
    "sessions": 3,
    "venues": 3,
    "sold": 58,
    "available": 366,
    "total": 424,
    "gross": 1483.0,
    "max_gross": 10780.0,
    "occupancy": 13.68,
    "name": "Madharaasi (Tamil, Eng Sub)",
    "summary": "Madharasi is an upcoming Indian Tamil-language action thriller film written and directed by AR Murugadoss.",
    "duration": 178,
    "releaseDate": "2025-09-05T00:00:00",
    "posterImage": "mx/posters/au/madharaasi-5f64fc1f.jpg",
    "id": "HO00010548"
  },
  {
    "sessions": 1,
    "venues": 1,
    "sold": 1,
    "available": 183,
    "total": 184,
    "gross": 13.33,
    "max_gross": 2452.72,
    "occupancy": 0.54,
    "name": "Kangaroo Island",
    "summary": "When Lou returns home to ruggedly beautiful Kangaroo Island at the request of her father, years of family secrets resurface in this beautiful, emotionally rewarding film.",
    "duration": 113,
    "releaseDate": "2025-08-21T00:00:00",
    "posterImage": "mx/posters/au/kangaroo-island-f543b218.jpg",
    "id": "HO00010383"
  },
  {
    "sessions": 1,
    "venues": 1,
    "sold": 13,
    "available": 127,
    "total": 140,
    "gross": 247.0,
    "max_gross": 2660.0,
    "occupancy": 9.29,
    "name": "Hridayapoorvam (Malayalam, Eng Sub)",
    "summary": "Hridayapoorvam (transl.\u2009Heartily) is an upcoming Indian Malayalam-language family drama film directed by Sathyan Anthikad from a screenplay by Sonu T. P.",
    "duration": 162,
    "releaseDate": "2025-08-28T00:00:00",
    "posterImage": "mx/posters/au/hridayapoorvam-4bbace09.jpg",
    "id": "HO00010607"
  },
  {
    "sessions": 1,
    "venues": 1,
    "sold": 7,
    "available": 125,
    "total": 132,
    "gross": 182.0,
    "max_gross": 3432.0,
    "occupancy": 5.3,
    "name": "Nobody 2",
    "summary": "Bob Odenkirk returns as Hutch Mansell, a seemingly ordinary suburban dad and former assassin who is once again drawn into the violent world he tried to leave behind.",
    "duration": 90,
    "releaseDate": "2025-08-14T00:00:00",
    "posterImage": "mx/posters/au/nobody-2-98a9f52a.jpg",
    "id": "HO00009610"
  },
  {
    "sessions": 1,
    "venues": 1,
    "sold": 22,
    "available": 69,
    "total": 91,
    "gross": 572.0,
    "max_gross": 2366.0,
    "occupancy": 24.18,
    "name": "Dead To Rights (Mandarin, Eng Sub)",
    "summary": "In the Nanjing Massacre of 1937, in order to save his life, postman A Chang pretended to be a photo developer in a photo studio and developed photos for the Japanese army",
    "duration": 137,
    "releaseDate": "2025-08-07T00:00:00",
    "posterImage": "mx/posters/au/dead-to-rights-473b8713.jpg",
    "id": "HO00010539"
  },
  {
    "sessions": 1,
    "venues": 1,
    "sold": 47,
    "available": 73,
    "total": 120,
    "gross": 1316.0,
    "max_gross": 3360.0,
    "occupancy": 39.17,
    "name": "The Bengal Files (Hindi, Eng Sub)",
    "summary": "A Kashmiri Pandit CBI officer investigates a journalist\u2019s disappearance in Bengal, haunted by his mother\u2019s genocide. ",
    "duration": 212,
    "releaseDate": "2025-09-05T00:00:00",
    "posterImage": "mx/posters/au/the-bengal-files-96c2dd8e.jpg",
    "id": "HO00010642"
  },
  {
    "sessions": 1,
    "venues": 1,
    "sold": 28,
    "available": 152,
    "total": 180,
    "gross": 784.0,
    "max_gross": 5040.0,
    "occupancy": 15.56,
    "name": "Baaghi 4 (Hindi, Eng Sub)",
    "summary": "At his lowest, Ronny survives a deadly train crash he never intended to live through. ",
    "duration": 166,
    "releaseDate": "2025-09-05T00:00:00",
    "posterImage": "mx/posters/au/baaghi-4-c324e2d7.jpg",
    "id": "HO00010415"
  }
]