[
  {
    "id": 428077,
    "cinemaId": "WETHER",
    "movieId": "HO00010550",
    "date": "2025-09-25T18:30:00",
    "typeId": "STANDARD",
    "screenName": "Cinema 03",
    "operator": "WET",
    "total": 120,
    "sold": 9,
    "available": 111,
    "occupancy": 7.5,
    "max_gross": 3120.0,
    "total_gross": 234.0,
    "price": 26.0,
    "error": false,
    "last_error": "HTTP 403"
  },
  {
    "id": 497611,
    "cinemaId": "CAROUS",
    "movieId": "HO00010550",
    "date": "2025-09-25T18:30:00",
    "typeId": "STANDARD",
    "screenName": "Cinema 06",
    "operator": "CAR",
    "total": 160,
    "sold": 60,
    "available": 100,
    "occupancy": 37.5,
    "max_gross": 3840.0,
    "total_gross": 1440.0,
    "price": 24.0,
    "error": false,
    "last_error": "HTTP 403"
  },
  {
    "id": 407446,
    "cinemaId": "NORTHL",
    "movieId": "HO00010550",
    "date": "2025-09-25T18:30:00",
    "typeId": "STANDARD",
    "screenName": "Cinema 09",
    "operator": "NOR",
    "total": 144,
    "sold": 6,
    "available": 138,
    "occupancy": 4.17,
    "max_gross": 3744.0,
    "total_gross": 156.0,
    "price": 26.0,
    "error": false,
    "last_error": "HTTP 403"
  },
  {
    "id": 361464,
    "cinemaId": "VGDCIN",
    "movieId": "HO00009403",
    "date": "2025-09-25T14:00:00",
    "typeId": "STANDARD",
    "screenName": "Cinema 05",
    "operator": "VGD",
    "total": 90,
    "sold": 12,
    "available": 78,
    "occupancy": 13.33,
    "max_gross": 2340.0,
    "total_gross": 312.0,
    "price": 26.0,
    "error": false,
    "last_error": "HTTP 403"
  },
  {
    "id": 292263,
    "cinemaId": "CWFFLD",
    "movieId": "HO00010550",
    "date": "2025-09-25T18:30:00",
    "typeId": "STANDARD",
    "screenName": "Cinema 06",
    "operator": "CWF",
    "total": 190,
    "sold": 15,
    "available": 175,
    "occupancy": 7.89,
    "max_gross": 4940.0,
    "total_gross": 390.0,
    "price": 26.0,
    "error": false,
    "last_error": "HTTP 403"
  },
  {
    "id": 376372,
    "cinemaId": "TTPLZA",
    "movieId": "HO00010550",
    "date": "2025-09-25T18:30:00",
    "typeId": "STANDARD",
    "screenName": "Cinema 07",
    "operator": "TTP",
    "total": 160,
    "sold": 20,
    "available": 140,
    "occupancy": 12.5,
    "max_gross": 3840.0,
    "total_gross": 480.0,
    "price": 24.0,
    "error": false,
    "last_error": "HTTP 403"
  },
  {
    "id": 281273,
    "cinemaId": "NWDCIN",
    "movieId": "HO00010550",
    "date": "2025-09-25T18:30:00",
    "typeId": "STANDARD",
    "screenName": "Cinema 09",
    "operator": "NWD",
    "total": 189,
    "sold": 7,
    "available": 182,
    "occupancy": 3.7,
    "max_gross": 4536.0,
    "total_gross": 168.0,
    "price": 24.0,
    "error": false,
    "last_error": "HTTP 403"
  },
  {
    "id": 434830,
    "cinemaId": "BROADW",
    "movieId": "HO00009267",
    "date": "2025-09-25T18:00:00",
    "typeId": "STANDARD",
    "screenName": "Cinema 08",
    "operator": "BRO",
    "total": 112,
    "sold": 0,
    "available": 112,
    "occupancy": 0.0,
    "max_gross": 3080.0,
    "total_gross": 0.0,
    "price": 27.5,
    "error": false,
    "last_error": "HTTP 403"
  },
  {
    "id": 434840,
    "cinemaId": "BROADW",
    "movieId": "HO00010550",
    "date": "2025-09-25T18:30:00",
    "typeId": "STANDARD",
    "screenName": "Cinema 03",
    "operator": "BRO",
    "total": 119,
    "sold": 5,
    "available": 114,
    "occupancy": 4.2,
    "max_gross": 3272.5,
    "total_gross": 137.5,
    "price": 27.5,
    "error": false,
    "last_error": "HTTP 403"
  },
  {
    "id": 370802,
    "cinemaId": "MCECIN",
    "movieId": "HO00010550",
    "date": "2025-09-25T18:30:00",
    "typeId": "STANDARD",
    "screenName": "Cinema 08",
    "operator": "MCE",
    "total": 152,
    "sold": 77,
    "available": 75,
    "occupancy": 50.66,
    "max_gross": 3952.0,
    "total_gross": 2002.0,
    "price": 26.0,
    "error": false,
    "last_error": "HTTP 403"
  },
  {
    "id": 344120,
    "cinemaId": "BELCON",
    "movieId": "HO00010550",
    "date": "2025-09-25T18:30:00",
    "typeId": "STANDARD",
    "screenName": "Cinema 03",
    "operator": "BEL",
    "total": 104,
    "sold": 29,
    "available": 75,
    "occupancy": 27.88,
    "max_gross": 2652.0,
    "total_gross": 739.5,
    "price": 25.5,
    "error": false,
    "last_error": "HTTP 403"
  },
  {
    "id": 310353,
    "cinemaId": "CHDSTN",
    "movieId": "HO00010550",
    "date": "2025-09-25T18:30:00",
    "typeId": "STANDARD",
    "screenName": "Cinema 10",
    "operator": "CDS",
    "total": 200,
    "sold": 43,
    "available": 157,
    "occupancy": 21.5,
    "max_gross": 5200.0,
    "total_gross": 1118.0,
    "price": 26.0,
    "error": false,
    "last_error": "HTTP 403"
  },
  {
    "id": 371947,
    "cinemaId": "MCECIN",
    "movieId": "HO00010550",
    "date": "2025-09-25T16:00:00",
    "typeId": "STANDARD",
    "screenName": "Cinema 08",
    "operator": "MCE",
    "total": 152,
    "sold": 11,
    "available": 141,
    "occupancy": 7.24,
    "max_gross": 3952.0,
    "total_gross": 286.0,
    "price": 26.0,
    "error": false,
    "last_error": "HTTP 403"
  },
  {
    "id": 500347,
    "cinemaId": "CAROUS",
    "movieId": "HO00010550",
    "date": "2025-09-25T19:00:00",
    "typeId": "STANDARD",
    "screenName": "Cinema 07",
    "operator": "CAR",
    "total": 160,
    "sold": 7,
    "available": 153,
    "occupancy": 4.38,
    "max_gross": 3840.0,
    "total_gross": 168.0,
    "price": 24.0,
    "error": false,
    "last_error": "HTTP 403"
  },
  {
    "id": 213202,
    "cinemaId": "FHLCIN",
    "movieId": "HO00010652",
    "date": "2025-09-25T20:30:00",
    "typeId": "STANDARD",
    "screenName": "Cinema 03",
    "operator": "FHL",
    "total": 144,
    "sold": 38,
    "available": 106,
    "occupancy": 26.39,
    "max_gross": 2808.0,
    "total_gross": 741.0,
    "price": 19.5,
    "error": false,
    "last_error": "'utf-8' codec can't decode byte 0xb5 in position 1: invalid start byte"
  },
  {
    "id": 359138,
    "cinemaId": "PENRTH",
    "movieId": "HO00010652",
    "date": "2025-09-25T21:15:00",
    "typeId": "XTREME",
    "screenName": "Xtremescreen 09",
    "operator": "PEN",
    "total": 476,
    "sold": 12,
    "available": 464,
    "occupancy": 2.52,
    "max_gross": 14280.0,
    "total_gross": 360.0,
    "price": 30.0,
    "error": false
  },
  {
    "id": 500724,
    "cinemaId": "CAROUS",
    "movieId": "HO00010652",
    "date": "2025-09-25T21:15:00",
    "typeId": "XTREME",
    "screenName": "Xtreme 01",
    "operator": "CAR",
    "total": 326,
    "sold": 107,
    "available": 219,
    "occupancy": 32.82,
    "max_gross": 10106.0,
    "total_gross": 3317.0,
    "price": 31.0,
    "error": false
  },
  {
    "id": 422046,
    "cinemaId": "EASTLN",
    "movieId": "HO00010652",
    "date": "2025-09-25T20:45:00",
    "typeId": "XTREME",
    "screenName": "Xtremescreen 07",
    "operator": "EAS",
    "total": 202,
    "sold": 49,
    "available": 153,
    "occupancy": 24.26,
    "max_gross": 6666.0,
    "total_gross": 1617.0,
    "price": 33.0,
    "error": false
  },
  {
    "id": 517683,
    "cinemaId": "HIGPNT",
    "movieId": "HO00010652",
    "date": "2025-09-25T21:15:00",
    "typeId": "XTREME",
    "screenName": "Xtremescreen 06",
    "operator": "HIG",
    "total": 316,
    "sold": 172,
    "available": 144,
    "occupancy": 54.43,
    "max_gross": 10428.0,
    "total_gross": 5676.0,
    "price": 33.0,
    "error": false
  },
  {
    "id": 378330,
    "cinemaId": "TTPLZA",
    "movieId": "HO00010652",
    "date": "2025-09-25T21:15:00",
    "typeId": "XTREME",
    "screenName": "Xtremescreen 01",
    "operator": "TTP",
    "total": 267,
    "sold": 64,
    "available": 203,
    "occupancy": 23.97,
    "max_gross": 8277.0,
    "total_gross": 1984.0,
    "price": 31.0,
    "error": false
  },
  {
    "id": 429527,
    "cinemaId": "WETHER",
    "movieId": "HO00010652",
    "date": "2025-09-25T21:15:00",
    "typeId": "XTREME",
    "screenName": "Xtremescreen 05",
    "operator": "WET",
    "total": 204,
    "sold": 88,
    "available": 116,
    "occupancy": 43.14,
    "max_gross": 6732.0,
    "total_gross": 2904.0,
    "price": 33.0,
    "error": false
  },
  {
    "id": 245555,
    "cinemaId": "BMWCIN",
    "movieId": "HO00010652",
    "date": "2025-09-25T21:00:00",
    "typeId": "XTREME",
    "screenName": "Xtremescreen 01",
    "operator": "BMW",
    "total": 134,
    "sold": 54,
    "available": 80,
    "occupancy": 40.3,
    "max_gross": 3886.0,
    "total_gross": 1566.0,
    "price": 29.0,
    "error": false
  },
  {
    "id": 334487,
    "cinemaId": "WODENP",
    "movieId": "HO00010652",
    "date": "2025-09-25T21:15:00",
    "typeId": "XTREME",
    "screenName": "Xtremescreen 04",
    "operator": "WOD",
    "total": 161,
    "sold": 71,
    "available": 90,
    "occupancy": 44.1,
    "max_gross": 5071.5,
    "total_gross": 2236.5,
    "price": 31.5,
    "error": false
  },
  {
    "id": 73518,
    "cinemaId": "ARNCIN",
    "movieId": "HO00010652",
    "date": "2025-09-25T20:50:00",
    "typeId": "XTREME",
    "screenName": "Xtremescreen 01",
    "operator": "ARN",
    "total": 684,
    "sold": 17,
    "available": 667,
    "occupancy": 2.49,
    "max_gross": 12996.0,
    "total_gross": 323.0,
    "price": 19.0,
    "error": false,
    "last_error": "'utf-8' codec can't decode byte 0xb5 in position 1: invalid start byte"
  },
  {
    "id": 262247,
    "cinemaId": "REDCLF",
    "movieId": "HO00010652",
    "date": "2025-09-25T21:00:00",
    "typeId": "XTREME",
    "screenName": "Xtremescreen 05",
    "operator": "RED",
    "total": 138,
    "sold": 33,
    "available": 105,
    "occupancy": 23.91,
    "max_gross": 3933.0,
    "total_gross": 940.5,
    "price": 28.5,
    "error": false
  },
  {
    "id": 318556,
    "cinemaId": "MTDRTT",
    "movieId": "HO00010652",
    "date": "2025-09-25T21:30:00",
    "typeId": "XTREME",
    "screenName": "Xtremescreen 03",
    "operator": "MTD",
    "total": 198,
    "sold": 15,
    "available": 183,
    "occupancy": 7.58,
    "max_gross": 6336.0,
    "total_gross": 480.0,
    "price": 32.0,
    "error": false,
    "last_error": "'utf-8' codec can't decode byte 0xb5 in position 1: invalid start byte"
  },
  {
    "id": 248861,
    "cinemaId": "SUNBNK",
    "movieId": "HO00010652",
    "date": "2025-09-25T21:30:00",
    "typeId": "XTREME",
    "screenName": "Xtremescreen 7",
    "operator": "SUN",
    "total": 130,
    "sold": 41,
    "available": 89,
    "occupancy": 31.54,
    "max_gross": 3770.0,
    "total_gross": 1189.0,
    "price": 29.0,
    "error": false
  },
  {
    "id": 331086,
    "cinemaId": "BANKTN",
    "movieId": "HO00010652",
    "date": "2025-09-25T21:00:00",
    "typeId": "STANDARD",
    "screenName": "Cinema 03",
    "operator": "BAN",
    "total": 170,
    "sold": 6,
    "available": 164,
    "occupancy": 3.53,
    "max_gross": 4590.0,
    "total_gross": 162.0,
    "price": 27.0,
    "error": false
  },
  {
    "id": 313530,
    "cinemaId": "CHDSTN",
    "movieId": "HO00010652",
    "date": "2025-09-25T21:15:00",
    "typeId": "XTREME",
    "screenName": "Xtremescreen 01",
    "operator": "CDS",
    "total": 278,
    "sold": 137,
    "available": 141,
    "occupancy": 49.28,
    "max_gross": 9174.0,
    "total_gross": 4521.0,
    "price": 33.0,
    "error": false,
    "last_error": "'utf-8' codec can't decode byte 0xb5 in position 1: invalid start byte"
  },
  {
    "id": 409483,
    "cinemaId": "NORTHL",
    "movieId": "HO00010652",
    "date": "2025-09-25T21:15:00",
    "typeId": "XTREME",
    "screenName": "Xtremescreen 10",
    "operator": "NOR",
    "total": 232,
    "sold": 81,
    "available": 151,
    "occupancy": 34.91,
    "max_gross": 7656.0,
    "total_gross": 2673.0,
    "price": 33.0,
    "error": false,
    "last_error": "'utf-8' codec can't decode byte 0xb5 in position 1: invalid start byte"
  },
  {
    "id": 286792,
    "cinemaId": "SLYCIN",
    "movieId": "HO00010652",
    "date": "2025-09-25T20:30:00",
    "typeId": "XTREME",
    "screenName": "Xtremescreen 08",
    "operator": "SLY",
    "total": 184,
    "sold": 67,
    "available": 117,
    "occupancy": 36.41,
    "max_gross": 4232.0,
    "total_gross": 1541.0,
    "price": 23.0,
    "error": false
  },
  {
    "id": 141394,
    "cinemaId": "DOCCIN",
    "movieId": "HO00010652",
    "date": "2025-09-25T21:15:00",
    "typeId": "XTREME",
    "screenName": "Xtremescreen 01",
    "operator": "DOC",
    "total": 408,
    "sold": 221,
    "available": 187,
    "occupancy": 54.17,
    "max_gross": 13464.0,
    "total_gross": 7293.0,
    "price": 33.0,
    "error": false
  },
  {
    "id": 346397,
    "cinemaId": "BELCON",
    "movieId": "HO00010652",
    "date": "2025-09-25T21:15:00",
    "typeId": "XTREME",
    "screenName": "Xtremescreen 05",
    "operator": "BEL",
    "total": 160,
    "sold": 73,
    "available": 87,
    "occupancy": 45.62,
    "max_gross": 5040.0,
    "total_gross": 2299.5,
    "price": 31.5,
    "error": false
  },
  {
    "id": 41806,
    "cinemaId": "WARCIN",
    "movieId": "HO00010652",
    "date": "2025-09-25T21:00:00",
    "typeId": "XTREME",
    "screenName": "Xtremescreen 09",
    "operator": "WAR",
    "total": 330,
    "sold": 6,
    "available": 324,
    "occupancy": 1.82,
    "max_gross": 9900.0,
    "total_gross": 180.0,
    "price": 30.0,
    "error": false
  },
  {
    "id": 78699,
    "cinemaId": "KYPCIN",
    "movieId": "HO00010652",
    "date": "2025-09-25T21:15:00",
    "typeId": "XTREME",
    "screenName": "Xtremescreen 01",
    "operator": "KYP",
    "total": 432,
    "sold": 63,
    "available": 369,
    "occupancy": 14.58,
    "max_gross": 14256.0,
    "total_gross": 2079.0,
    "price": 33.0,
    "error": false
  },
  {
    "id": 274720,
    "cinemaId": "TAYLOR",
    "movieId": "HO00010652",
    "date": "2025-09-25T21:15:00",
    "typeId": "XTREME",
    "screenName": "Xtremescreen 03",
    "operator": "TAY",
    "total": 252,
    "sold": 106,
    "available": 146,
    "occupancy": 42.06,
    "max_gross": 8316.0,
    "total_gross": 3498.0,
    "price": 33.0,
    "error": false
  },
  {
    "id": 272951,
    "cinemaId": "SOUTHL",
    "movieId": "HO00010652",
    "date": "2025-09-25T20:45:00",
    "typeId": "STANDARD",
    "screenName": "Cinema 01",
    "operator": "SOU",
    "total": 210,
    "sold": 17,
    "available": 193,
    "occupancy": 8.1,
    "max_gross": 5670.0,
    "total_gross": 459.0,
    "price": 27.0,
    "error": false
  },
  {
    "id": 358627,
    "cinemaId": "WESCIN",
    "movieId": "HO00010652",
    "date": "2025-09-25T21:15:00",
    "typeId": "XTREME",
    "screenName": "Xtremescreen 05",
    "operator": "WES",
    "total": 408,
    "sold": 195,
    "available": 213,
    "occupancy": 47.79,
    "max_gross": 13464.0,
    "total_gross": 6435.0,
    "price": 33.0,
    "error": false
  },
  {
    "id": 43468,
    "cinemaId": "MIDCIN",
    "movieId": "HO00010652",
    "date": "2025-09-25T21:15:00",
    "typeId": "XTREME",
    "screenName": "Xtremescreen 03",
    "operator": "MID",
    "total": 200,
    "sold": 13,
    "available": 187,
    "occupancy": 6.5,
    "max_gross": 5700.0,
    "total_gross": 370.5,
    "price": 28.5,
    "error": false
  },
  {
    "id": 358981,
    "cinemaId": "WESCIN",
    "movieId": "HO00010652",
    "date": "2025-09-25T17:45:00",
    "typeId": "XTREME",
    "screenName": "Xtremescreen 05",
    "operator": "WES",
    "total": 408,
    "sold": 186,
    "available": 222,
    "occupancy": 45.59,
    "max_gross": 13464.0,
    "total_gross": 6138.0,
    "price": 33.0,
    "error": false
  },
  {
    "id": 358980,
    "cinemaId": "WESCIN",
    "movieId": "HO00010652",
    "date": "2025-09-25T21:10:00",
    "typeId": "STANDARD",
    "screenName": "Cinema 06",
    "operator": "WES",
    "total": 242,
    "sold": 93,
    "available": 149,
    "occupancy": 38.43,
    "max_gross": 6776.0,
    "total_gross": 2604.0,
    "price": 28.0,
    "error": false
  },
  {
    "id": 358979,
    "cinemaId": "WESCIN",
    "movieId": "HO00010652",
    "date": "2025-09-25T21:30:00",
    "typeId": "XTREME",
    "screenName": "Xtremescreen 01",
    "operator": "WES",
    "total": 264,
    "sold": 111,
    "available": 153,
    "occupancy": 42.05,
    "max_gross": 8712.0,
    "total_gross": 3663.0,
    "price": 33.0,
    "error": false
  },
  {
    "id": 429973,
    "cinemaId": "WETHER",
    "movieId": "HO00010652",
    "date": "2025-09-25T18:00:00",
    "typeId": "XTREME",
    "screenName": "Xtremescreen 12",
    "operator": "WET",
    "total": 202,
    "sold": 22,
    "available": 180,
    "occupancy": 10.89,
    "max_gross": 6666.0,
    "total_gross": 726.0,
    "price": 33.0,
    "error": false
  },
  {
    "id": 346747,
    "cinemaId": "BELCON",
    "movieId": "HO00010652",
    "date": "2025-09-25T21:00:00",
    "typeId": "STANDARD",
    "screenName": "Cinema 03",
    "operator": "BEL",
    "total": 104,
    "sold": 26,
    "available": 78,
    "occupancy": 25.0,
    "max_gross": 2860.0,
    "total_gross": 715.0,
    "price": 27.5,
    "error": false,
    "last_error": "'utf-8' codec can't decode byte 0xb5 in position 1: invalid start byte"
  },
  {
    "id": 249161,
    "cinemaId": "SUNBNK",
    "movieId": "HO00010652",
    "date": "2025-09-25T18:00:00",
    "typeId": "XTREME",
    "screenName": "Xtremescreen 3",
    "operator": "SUN",
    "total": 130,
    "sold": 49,
    "available": 81,
    "occupancy": 37.69,
    "max_gross": 3770.0,
    "total_gross": 1421.0,
    "price": 29.0,
    "error": false
  },
  {
    "id": 141655,
    "cinemaId": "DOCCIN",
    "movieId": "HO00010652",
    "date": "2025-09-25T17:30:00",
    "typeId": "XTREME",
    "screenName": "Xtremescreen 01",
    "operator": "DOC",
    "total": 408,
    "sold": 181,
    "available": 227,
    "occupancy": 44.36,
    "max_gross": 13464.0,
    "total_gross": 5973.0,
    "price": 33.0,
    "error": false
  },
  {
    "id": 314059,
    "cinemaId": "CHDSTN",
    "movieId": "HO00010652",
    "date": "2025-09-25T17:45:00",
    "typeId": "XTREME",
    "screenName": "Xtremescreen 01",
    "operator": "CDS",
    "total": 278,
    "sold": 87,
    "available": 191,
    "occupancy": 31.29,
    "max_gross": 9174.0,
    "total_gross": 2871.0,
    "price": 33.0,
    "error": false
  },
  {
    "id": 359003,
    "cinemaId": "WESCIN",
    "movieId": "HO00010652",
    "date": "2025-09-25T08:15:00",
    "typeId": "XTREME",
    "screenName": "Xtremescreen 05",
    "operator": "WES",
    "total": 408,
    "sold": 192,
    "available": 216,
    "occupancy": 47.06,
    "max_gross": 13464.0,
    "total_gross": 6336.0,
    "price": 33.0,
    "error": false
  },
  {
    "id": 359019,
    "cinemaId": "WESCIN",
    "movieId": "HO00010652",
    "date": "2025-09-25T11:45:00",
    "typeId": "XTREME",
    "screenName": "Xtremescreen 05",
    "operator": "WES",
    "total": 408,
    "sold": 34,
    "available": 374,
    "occupancy": 8.33,
    "max_gross": 13464.0,
    "total_gross": 1122.0,
    "price": 33.0,
    "error": false
  },
  {
    "id": 359016,
    "cinemaId": "WESCIN",
    "movieId": "HO00010652",
    "date": "2025-09-25T14:15:00",
    "typeId": "XTREME",
    "screenName": "Xtremescreen 01",
    "operator": "WES",
    "total": 264,
    "sold": 7,
    "available": 257,
    "occupancy": 2.65,
    "max_gross": 8712.0,
    "total_gross": 231.0,
    "price": 33.0,
    "error": false
  },
  {
    "id": 359017,
    "cinemaId": "WESCIN",
    "movieId": "HO00010652",
    "date": "2025-09-25T18:00:00",
    "typeId": "XTREME",
    "screenName": "Xtremescreen 01",
    "operator": "WES",
    "total": 264,
    "sold": 106,
    "available": 158,
    "occupancy": 40.15,
    "max_gross": 8712.0,
    "total_gross": 3498.0,
    "price": 33.0,
    "error": false
  },
  {
    "id": 275197,
    "cinemaId": "TAYLOR",
    "movieId": "HO00010652",
    "date": "2025-09-25T08:00:00",
    "typeId": "XTREME",
    "screenName": "Xtremescreen 03",
    "operator": "TAY",
    "total": 252,
    "sold": 71,
    "available": 181,
    "occupancy": 28.17,
    "max_gross": 8316.0,
    "total_gross": 2343.0,
    "price": 33.0,
    "error": false
  },
  {
    "id": 275192,
    "cinemaId": "TAYLOR",
    "movieId": "HO00010652",
    "date": "2025-09-25T17:40:00",
    "typeId": "XTREME",
    "screenName": "Xtremescreen 03",
    "operator": "TAY",
    "total": 252,
    "sold": 78,
    "available": 174,
    "occupancy": 30.95,
    "max_gross": 8316.0,
    "total_gross": 2574.0,
    "price": 33.0,
    "error": false
  },
  {
    "id": 275195,
    "cinemaId": "TAYLOR",
    "movieId": "HO00010652",
    "date": "2025-09-25T14:00:00",
    "typeId": "XTREME",
    "screenName": "Xtremescreen 03",
    "operator": "TAY",
    "total": 252,
    "sold": 4,
    "available": 248,
    "occupancy": 1.59,
    "max_gross": 8316.0,
    "total_gross": 132.0,
    "price": 33.0,
    "error": false
  },
  {
    "id": 346778,
    "cinemaId": "BELCON",
    "movieId": "HO00010652",
    "date": "2025-09-25T10:00:00",
    "typeId": "XTREME",
    "screenName": "Xtremescreen 06",
    "operator": "BEL",
    "total": 168,
    "sold": 18,
    "available": 150,
    "occupancy": 10.71,
    "max_gross": 5292.0,
    "total_gross": 567.0,
    "price": 31.5,
    "error": false,
    "last_error": "'utf-8' codec can't decode byte 0xb5 in position 1: invalid start byte"
  },
  {
    "id": 346779,
    "cinemaId": "BELCON",
    "movieId": "HO00010652",
    "date": "2025-09-25T17:45:00",
    "typeId": "XTREME",
    "screenName": "Xtremescreen 05",
    "operator": "BEL",
    "total": 160,
    "sold": 36,
    "available": 124,
    "occupancy": 22.5,
    "max_gross": 5040.0,
    "total_gross": 1134.0,
    "price": 31.5,
    "error": false
  },
  {
    "id": 501188,
    "cinemaId": "CAROUS",
    "movieId": "HO00010652",
    "date": "2025-09-25T10:00:00",
    "typeId": "XTREME",
    "screenName": "Xtreme 02",
    "operator": "CAR",
    "total": 287,
    "sold": 99,
    "available": 188,
    "occupancy": 34.49,
    "max_gross": 8897.0,
    "total_gross": 3069.0,
    "price": 31.0,
    "error": false
  },
  {
    "id": 501187,
    "cinemaId": "CAROUS",
    "movieId": "HO00010652",
    "date": "2025-09-25T17:45:00",
    "typeId": "XTREME",
    "screenName": "Xtreme 01",
    "operator": "CAR",
    "total": 326,
    "sold": 143,
    "available": 183,
    "occupancy": 43.87,
    "max_gross": 10106.0,
    "total_gross": 4433.0,
    "price": 31.0,
    "error": false
  },
  {
    "id": 141683,
    "cinemaId": "DOCCIN",
    "movieId": "HO00010652",
    "date": "2025-09-25T14:00:00",
    "typeId": "XTREME",
    "screenName": "Xtremescreen 01",
    "operator": "DOC",
    "total": 408,
    "sold": 23,
    "available": 385,
    "occupancy": 5.64,
    "max_gross": 13464.0,
    "total_gross": 759.0,
    "price": 33.0,
    "error": false
  },
  {
    "id": 141685,
    "cinemaId": "DOCCIN",
    "movieId": "HO00010652",
    "date": "2025-09-25T08:15:00",
    "typeId": "XTREME",
    "screenName": "Xtremescreen 01",
    "operator": "DOC",
    "total": 408,
    "sold": 82,
    "available": 326,
    "occupancy": 20.1,
    "max_gross": 13464.0,
    "total_gross": 2706.0,
    "price": 33.0,
    "error": false,
    "last_error": "'utf-8' codec can't decode byte 0xb5 in position 1: invalid start byte"
  },
  {
    "id": 518229,
    "cinemaId": "HIGPNT",
    "movieId": "HO00010652",
    "date": "2025-09-25T08:00:00",
    "typeId": "XTREME",
    "screenName": "Xtremescreen 06",
    "operator": "HIG",
    "total": 316,
    "sold": 106,
    "available": 210,
    "occupancy": 33.54,
    "max_gross": 10428.0,
    "total_gross": 3498.0,
    "price": 33.0,
    "error": false
  },
  {
    "id": 314061,
    "cinemaId": "CHDSTN",
    "movieId": "HO00010652",
    "date": "2025-09-25T08:00:00",
    "typeId": "XTREME",
    "screenName": "Xtremescreen 01",
    "operator": "CDS",
    "total": 278,
    "sold": 76,
    "available": 202,
    "occupancy": 27.34,
    "max_gross": 9174.0,
    "total_gross": 2508.0,
    "price": 33.0,
    "error": false
  },
  {
    "id": 314062,
    "cinemaId": "CHDSTN",
    "movieId": "HO00010652",
    "date": "2025-09-25T11:40:00",
    "typeId": "XTREME",
    "screenName": "Xtremescreen 01",
    "operator": "CDS",
    "total": 278,
    "sold": 20,
    "available": 258,
    "occupancy": 7.19,
    "max_gross": 9174.0,
    "total_gross": 660.0,
    "price": 33.0,
    "error": false
  },
  {
    "id": 336785,
    "cinemaId": "FRANKS",
    "movieId": "HO00010652",
    "date": "2025-09-25T21:15:00",
    "typeId": "XTREME",
    "screenName": "Xtremescreen 03",
    "operator": "FRA",
    "total": 114,
    "sold": 26,
    "available": 88,
    "occupancy": 22.81,
    "max_gross": 3762.0,
    "total_gross": 858.0,
    "price": 33.0,
    "error": false,
    "last_error": "'utf-8' codec can't decode byte 0xb5 in position 1: invalid start byte"
  },
  {
    "id": 334752,
    "cinemaId": "WODENP",
    "movieId": "HO00010652",
    "date": "2025-09-25T17:45:00",
    "typeId": "XTREME",
    "screenName": "Xtremescreen 04",
    "operator": "WOD",
    "total": 161,
    "sold": 18,
    "available": 143,
    "occupancy": 11.18,
    "max_gross": 5071.5,
    "total_gross": 567.0,
    "price": 31.5,
    "error": false,
    "last_error": "'utf-8' codec can't decode byte 0xb5 in position 1: invalid start byte"
  },
  {
    "id": 334751,
    "cinemaId": "WODENP",
    "movieId": "HO00010652",
    "date": "2025-09-25T10:00:00",
    "typeId": "XTREME",
    "screenName": "Xtremescreen 03",
    "operator": "WOD",
    "total": 147,
    "sold": 3,
    "available": 144,
    "occupancy": 2.04,
    "max_gross": 4630.5,
    "total_gross": 94.5,
    "price": 31.5,
    "error": false
  },
  {
    "id": 249173,
    "cinemaId": "SUNBNK",
    "movieId": "HO00010652",
    "date": "2025-09-25T08:30:00",
    "typeId": "XTREME",
    "screenName": "Xtremescreen 7",
    "operator": "SUN",
    "total": 130,
    "sold": 70,
    "available": 60,
    "occupancy": 53.85,
    "max_gross": 3770.0,
    "total_gross": 2030.0,
    "price": 29.0,
    "error": false
  },
  {
    "id": 73904,
    "cinemaId": "ARNCIN",
    "movieId": "HO00010652",
    "date": "2025-09-25T10:00:00",
    "typeId": "XTREME",
    "screenName": "Xtremescreen 01",
    "operator": "ARN",
    "total": 684,
    "sold": 11,
    "available": 673,
    "occupancy": 1.61,
    "max_gross": 12996.0,
    "total_gross": 209.0,
    "price": 19.0,
    "error": false
  },
  {
    "id": 359033,
    "cinemaId": "WESCIN",
    "movieId": "HO00010652",
    "date": "2025-09-25T08:00:00",
    "typeId": "XTREME",
    "screenName": "Xtremescreen 01",
    "operator": "WES",
    "total": 264,
    "sold": 84,
    "available": 180,
    "occupancy": 31.82,
    "max_gross": 8712.0,
    "total_gross": 2772.0,
    "price": 33.0,
    "error": false
  },
  {
    "id": 12083,
    "cinemaId": "IPSCIN",
    "movieId": "HO00010652",
    "date": "2025-09-25T09:30:00",
    "typeId": "STANDARD",
    "screenName": "Cinema 03",
    "operator": "IPS",
    "total": 174,
    "sold": 0,
    "available": 174,
    "occupancy": 0.0,
    "max_gross": 3306.0,
    "total_gross": 0.0,
    "price": 19.0,
    "error": false
  },
  {
    "id": 12081,
    "cinemaId": "IPSCIN",
    "movieId": "HO00010652",
    "date": "2025-09-25T20:30:00",
    "typeId": "STANDARD",
    "screenName": "Cinema 03",
    "operator": "IPS",
    "total": 174,
    "sold": 0,
    "available": 174,
    "occupancy": 0.0,
    "max_gross": 3306.0,
    "total_gross": 0.0,
    "price": 19.0,
    "error": false
  },
  {
    "id": 79045,
    "cinemaId": "KYPCIN",
    "movieId": "HO00010652",
    "date": "2025-09-25T11:15:00",
    "typeId": "XTREME",
    "screenName": "Xtremescreen 02",
    "operator": "KYP",
    "total": 398,
    "sold": 4,
    "available": 394,
    "occupancy": 1.01,
    "max_gross": 13134.0,
    "total_gross": 132.0,
    "price": 33.0,
    "error": false
  },
  {
    "id": 245872,
    "cinemaId": "BMWCIN",
    "movieId": "HO00010652",
    "date": "2025-09-25T08:30:00",
    "typeId": "XTREME",
    "screenName": "Xtremescreen 01",
    "operator": "BMW",
    "total": 134,
    "sold": 6,
    "available": 128,
    "occupancy": 4.48,
    "max_gross": 3886.0,
    "total_gross": 174.0,
    "price": 29.0,
    "error": false
  },
  {
    "id": 318846,
    "cinemaId": "MTDRTT",
    "movieId": "HO00010652",
    "date": "2025-09-25T09:00:00",
    "typeId": "XTREME",
    "screenName": "Xtremescreen 03",
    "operator": "MTD",
    "total": 198,
    "sold": 0,
    "available": 198,
    "occupancy": 0.0,
    "max_gross": 6336.0,
    "total_gross": 0.0,
    "price": 32.0,
    "error": false
  },
  {
    "id": 518228,
    "cinemaId": "HIGPNT",
    "movieId": "HO00010652",
    "date": "2025-09-25T17:40:00",
    "typeId": "XTREME",
    "screenName": "Xtremescreen 06",
    "operator": "HIG",
    "total": 316,
    "sold": 86,
    "available": 230,
    "occupancy": 27.22,
    "max_gross": 10428.0,
    "total_gross": 2838.0,
    "price": 33.0,
    "error": false
  },
  {
    "id": 518231,
    "cinemaId": "HIGPNT",
    "movieId": "HO00010652",
    "date": "2025-09-25T14:00:00",
    "typeId": "XTREME",
    "screenName": "Xtremescreen 06",
    "operator": "HIG",
    "total": 316,
    "sold": 7,
    "available": 309,
    "occupancy": 2.22,
    "max_gross": 10428.0,
    "total_gross": 231.0,
    "price": 33.0,
    "error": false
  }
]